Workbook
Name cfgAcademyClass: 'Settings'!$C$6
Name cfgStartDate: 'Settings'!$C$7
Name cfgEndDate: 'Settings'!$C$8
Name cfgTotalScheduledMinutes: 'Settings'!$C$9
Name cfgPassingScore: 'Settings'!$C$10
Name cfgThresholdScore: 'Settings'!$C$11
Name cfgRetakeRecordedCap: 'Settings'!$C$12
Name cfgThresholdAfterExam: 'Settings'!$C$13
Name cfgRetestClassDays: 'Settings'!$C$14
Name cfgMemoDueClassDays: 'Settings'!$C$15
Name cfgWeightMajor: 'Settings'!$C$16
Name cfgWeightMinor: 'Settings'!$C$17
Name cfgWeightSpelling: 'Settings'!$C$18
Name cfgWeightFinal: 'Settings'!$C$19
Name cfgSpellInterventionAvg: 'Settings'!$C$20
Name cfgMakeupAdvisoryMin: 'Settings'!$C$21
Name cfgMakeupCriticalMin: 'Settings'!$C$22
Name cfgPTCapSessions: 'Settings'!$C$23
Name cfgAttendanceAdvisoryPct: 'Settings'!$C$24
Name cfgAttendanceCriticalPct: 'Settings'!$C$25
Name cfgHomeAgency: 'Settings'!$C$26
Name cfgCurrentExamNum: 'Settings'!$C$27
Name cfgCurrentSpellingNum: 'Settings'!$C$28
Name cfgWritingDueTime: 'Settings'!$C$29
Name cfgPTFinalMinPoints: 'Settings'!$C$30
Name cfgFlagConsecFails: 'Settings'!$C$31
Name cfgFlagGradeDrop: 'Settings'!$C$32
Name cfgFlagCategoryMargin: 'Settings'!$C$33
Name cfgFlagAttendancePct: 'Settings'!$C$34
Name cfgFlagOpenIncidents: 'Settings'!$C$35
Name cfgFlagOverdueWriting: 'Settings'!$C$36
Name cfgWeightsTotal: 'Settings'!$C$37
Name nrPTTierPts: 'Settings'!$D$43:$H$43
Name nrPTBands: 'Settings'!$D$44:$H$48
Name nrPTBandEvents: 'Settings'!$B$44:$B$48
Name lstYesNo: 'Lists'!$B$6:$B$7
Name lstCadetStatus: 'Lists'!$C$6:$C$9
Name lstExamType: 'Lists'!$D$6:$D$8
Name lstAttendanceEvent: 'Lists'!$E$6:$E$14
Name lstReason: 'Lists'!$F$6:$F$12
Name lstDocumentation: 'Lists'!$G$6:$G$8
Name lstExcused: 'Lists'!$H$6:$H$7
Name lstMakeupType: 'Lists'!$I$6:$I$7
Name lstScoringMode: 'Lists'!$J$6:$J$7
Name lstSkillResult: 'Lists'!$K$6:$K$8
Name lstIncidentDirection: 'Lists'!$L$6:$L$8
Name lstSeverity: 'Lists'!$M$6:$M$10
Name lstResolution: 'Lists'!$N$6:$N$9
Name lstAssignmentType: 'Lists'!$O$6:$O$10
Name lstSubmission: 'Lists'!$P$6:$P$9
Name lstAttemptNum: 'Lists'!$Q$6:$Q$10
Name lstExamAttemptNum: 'Lists'!$R$6:$R$7
Name lstIssuetype: 'Lists'!$S$6:$S$12
Name lstCounselingType: 'Lists'!$T$6:$T$13
Name lstMedicalStatus: 'Lists'!$U$6:$U$9
Name lstPtSession: 'Lists'!$V$6:$V$8
Name lstAward: 'Lists'!$W$6:$W$9
Name lstInstructorType: 'Lists'!$X$6:$X$9
Name lstMaterialsStatus: 'Lists'!$Y$6:$Y$9
Name lstRequirementSource: 'Lists'!$Z$6:$Z$7

Sheet Dashboard
B5: =cfgAcademyClass&" — Dashboard" | H5: ="As of "&TEXT(TODAY(),"mm/dd/yyyy") | J5: =HYPERLINK("#InputGuide!B5","Data Entry Guide →")
B7: Academy start | D7: Final Exam date | F7: State Exam date | H7: Graduation / end | J7: Active cadets
B8: =TEXT(cfgStartDate,"mm/dd/yyyy") | D8: =_xlfn.LET(_xlpm.d,_xlfn.MAXIFS(nrSCH_Date,nrSCH_Act,"Final Test"),IF(_xlpm.d=0,"(not on schedule)",TEXT(_xlpm.d,"mm/dd/yyyy"))) | F8: =_xlfn.LET(_xlpm.d,_xlfn.MAXIFS(nrSCH_Date,nrSCH_Act,"State Test"),IF(_xlpm.d=0,"(not on schedule)",TEXT(_xlpm.d,"mm/dd/yyyy"))) | H8: =_xlfn.LET(_xlpm.d,_xlfn.MAXIFS(nrSCH_Date,nrSCH_Act,"Graduation"),IF(_xlpm.d=0,TEXT(cfgEndDate,"mm/dd/yyyy"),TEXT(_xlpm.d,"mm/dd/yyyy"))) | J8: =SUMPRODUCT((nrCadetStatus="Active")*1)
B10: Today
B11: =IF(COUNTIF(nrDL_Date,TODAY())=0,"DailyLog: no entry for today yet","DailyLog: entered ✓") | H11: =IFERROR("Training Day #"&_xlfn.XLOOKUP(TODAY(),nrCDdate,nrCDnum)&" (Week "&_xlfn.XLOOKUP(TODAY(),nrCDdate,nrCDweek)&")","(not a class day)")
B13: ="TODAY — "&UPPER(TEXT(TODAY(),"dddd, mmmm d"))&IFERROR(" — TRAINING DAY #"&_xlfn.XLOOKUP(TODAY(),nrCDdate,nrCDnum)&", WEEK "&_xlfn.XLOOKUP(TODAY(),nrCDdate,nrCDweek),"")
B14: =IFERROR(_xlfn.TAKE(_xlfn._xlws.FILTER(_xlfn.HSTACK(TEXT(nrSCH_Start,"h:mm AM/PM"),TEXT(nrSCH_End,"h:mm AM/PM"),nrSCH_Act,nrSCH_Instr,nrSCH_Loc),(nrSCH_Date<>"")*(nrSCH_Date=TODAY()),"No class scheduled today"),9),"⚠ LIST UNAVAILABLE - a reference in this panel is broken; do NOT read it as 'nothing to report'")
B23: Separated / total enrolled | D23: Class current avg | F23: Graduation eligible | H23: Flagged cadets | J23: Retests overdue / late / undated
B24: =SUMPRODUCT((nrCadetStatus="Separated")*1)&" / "&SUMPRODUCT((nrCadetStatus<>"")*1) | D24: =IFERROR(ROUND(AVERAGEIF(nrCadetStatus,"Active",nrGRcurrent),1),"—") | F24: =SUMPRODUCT((nrCadetStatus="Active")*(nrCKgradElig="Yes")) | H24: =SUMPRODUCT((nrCadetStatus="Active")*(nrFLcount>0)) | J24: =COUNTIF(nrES_RetStat,"OVERDUE")+COUNTIF(nrES_RetStat,"CHECK DATE")+COUNTIF(nrES_RetStat,"LATE RETEST*")+COUNTIF(nrES_RetStat,"RETEST UNDATED")+COUNTIF(nrES_RetStat,"RETEST DATE UNCHECKED")
B26: Spelling interventions | D26: Makeup owed (cadets) | F26: Delivered hours | H26: Audit checks failing | J26: Days to graduation | L26: Cert copies to collect
B27: =COUNTIF(nrSpellFlag,"INTERVENTION") | D27: =SUMPRODUCT((nrCadetStatus="Active")*(nrATTmakeupOK="No")) | F27: =ROUND(N(nrCHtotalDelivered),0)&" / "&cfgRequiredHours | H27: =SUMPRODUCT((nrAUDstatus<>"OK")*(nrAUDstatus<>"")) | J27: =MAX(0,cfgEndDate-TODAY()) | L27: =SUMPRODUCT((nrCadetStatus="Active")*(nrCERTmissing<>""))
B29: Watch list — highest flag counts first (full list on WatchList)
B30: =IFERROR(_xlfn.TAKE(_xlfn.SORTBY(_xlfn._xlws.FILTER(_xlfn.HSTACK(rngCadetNames,nrCadetAgency,nrFLcount,nrFLreasons),(nrFLcount>0)*(nrCadetStatus="Active"),"No flags — clear"),_xlfn._xlws.FILTER(nrFLcount,(nrFLcount>0)*(nrCadetStatus="Active"),"No flags — clear"),-1),11),"⚠ LIST UNAVAILABLE - a reference in this panel is broken; do NOT read it as 'nothing to report'")
B41: Certification reminders — copies to collect from cadets (Certifications sheet)
B42: =IFERROR(_xlfn.TAKE(_xlfn._xlws.FILTER(_xlfn.HSTACK(rngCadetNames,nrCadetAgency,nrCERTmissing),(nrCERTmissing<>"")*(nrCadetStatus="Active"),"All certification copies collected"),9),"⚠ LIST UNAVAILABLE - a reference in this panel is broken; do NOT read it as 'nothing to report'")
B51: Open missed-time events — not yet made up (Attendance ↔ Makeup by EventID)
B52: =IFERROR(_xlfn.TAKE(_xlfn.SORTBY(_xlfn._xlws.FILTER(_xlfn.HSTACK(nrAT_ID,Attendance!$D$6:$D$805,TEXT(nrAT_Date,"mm/dd"),Attendance!$G$6:$G$805,Attendance!$H$6:$H$805,nrAT_Balance),(nrAT_Cleared="OPEN"),"All missed time cleared"),_xlfn._xlws.FILTER(nrAT_Date,(nrAT_Cleared="OPEN"),"All missed time cleared"),-1),9),"⚠ LIST UNAVAILABLE - a reference in this panel is broken; do NOT read it as 'nothing to report'")
B61: Outstanding memos (pending / overdue)
B62: =IFERROR(_xlfn.TAKE(_xlfn.SORTBY(_xlfn._xlws.FILTER(_xlfn.HSTACK(Memos!$B$6:$B$305,nrME_Cadet,TEXT(nrME_Assigned,"mm/dd"),nrME_Ref,nrME_Subject,TEXT(nrME_Due,"mm/dd"),nrME_Status),(nrME_Cadet<>"")*(nrME_Received=""),"No memos outstanding"),_xlfn._xlws.FILTER(nrME_Due,(nrME_Cadet<>"")*(nrME_Received=""),"No memos outstanding"),1),8),"⚠ LIST UNAVAILABLE - a reference in this panel is broken; do NOT read it as 'nothing to report'")
B70: Class average by exam
B86: Spelling class average by test

Sheet StartHere
B1: =HYPERLINK("#Dashboard!B5","◄ Dashboard")
B4: Workbook map: CREAM boxes are yours to type (your entries show in blue), PALE BLUE = calculated, sys* sheets are the locked engine.
B5: Step | C5: What to do
B6: 1. Settings | C6: Set academy class label, start/end dates, weights, caps and flag thresholds. Blue cells are yours.
B7: 2. Lists / Agencies / Instructors | C7: Confirm dropdown lists, agency contacts and the instructor roster (PID, certs, SME letters).
B8: 3. ChapterMaster & Schedule | C8: Confirm chapter hours, then enter the class schedule (date, times, chapter, instructor). Delivered hours reconcile automatically.
B9: 4. ExamPlan / WritingMaster / SpellingMaster | C9: Pick this academy's exams; writing due dates compute from the schedule.
B10: 5. Cadets | C10: Enter the roster (PID, names, agency). Everything keys off PID.
B11: 6. Daily operation | C11: Log exam scores, spelling, attendance exceptions, makeup, skills, writing, incidents, counseling, PT and medical as they happen.
B12: 7. Watch the Dashboard / WatchList | C12: Flags, retest deadlines and blocking issues surface automatically.
B13: 8. Print Center | C13: Sign-in sheets, evals, spelling tests, writing handouts, transcripts and rosters — one place.
B14: 9. Agency emails | C14: EmailPreview + buttons draft per-agency Outlook emails for review. Never auto-sent.
B15: 10. New academy | C15: Save-As, then use the New Academy reset button. See the Coordinator Guide in docs/.

Sheet InputGuide
B1: =HYPERLINK("#Dashboard!B5","◄ Dashboard")
B4: Only pages that take input are listed — gray sys* tabs are the locked calculation engine; green tabs are outputs. Cream boxes are yours to type (what you type shows in blue); pale blue cells calculate.
B5: Go to… | C5: What you enter there
B6: Getting set up
B7: =HYPERLINK("#Settings!B6","Settings") | C7: Academy label, start/end dates, grading weights, caps, retest window, flag thresholds, PT points rubric (yellow block).
B8: =HYPERLINK("#Lists!B6","Lists") | C8: Dropdown choices used across the workbook — add items here.
B9: =HYPERLINK("#Agencies!B6","Agencies") | C9: Sending agencies: codes, contacts, email addresses.
B10: =HYPERLINK("#Instructors!B6","Instructors") | C10: Roster with TCOLE PID, certs, SME letters, bio-on-file status. 'On Schedule?' shows who actually teaches — every co-teacher needs documentation.
B11: =HYPERLINK("#InstructorBanks!B6","InstructorBanks") | C11: Per-topic banks: the certified pool (kept between academies) and who you picked to teach THIS academy — those picks become the Schedule's instructor dropdown for that topic.
B12: =HYPERLINK("#ChapterMaster!B6","ChapterMaster") | C12: Chapter hours + the per-chapter TCOLE training-file record (lesson plan, bio, sign-ins, assessment, grade sheet, eval, special requirements).
B13: =HYPERLINK("#Control!B6","Control") | C13: Extra closure dates (holidays compute automatically).
B14: =HYPERLINK("#Schedule!B6","Schedule") | C14: The class schedule: one row per time block — date, times, chapter/activity, instructor. Drives hours, due dates, sign-ins.
B15: =HYPERLINK("#ExamPlan!B6","ExamPlan") | C15: Which exams this academy uses, their sequence and linked chapters.
B16: =HYPERLINK("#ExamMaster!B6","ExamMaster") | C16: The exam library (edit names/types/defaults).
B17: =HYPERLINK("#SkillsMaster!B6","SkillsMaster") | C17: Attempt limits and scoring mode per skill category.
B18: =HYPERLINK("#SpellingMaster!B6","SpellingMaster") | C18: The 12 spelling word lists (printable via Print Center).
B19: =HYPERLINK("#WritingMaster!B6","WritingMaster") | C19: The 40 assignments: prompts, linked chapters, date overrides.
B20: Daily operation
B21: =HYPERLINK("#Cadets!B6","Cadets") | C21: The roster: PID, names, agency, status, enroll/separation.
B22: =HYPERLINK("#ExamScores!B6","ExamScores") | C22: One row per exam attempt: cadet, exam, attempt #, raw score, date. Retest deadlines compute.
B23: =HYPERLINK("#Spelling!B6","Spelling") | C23: Spelling test scores per cadet per test.
B24: =HYPERLINK("#Attendance!B6","Attendance") | C24: Exception log: missed/modified time in minutes (or PT sessions), reason, documentation, excused.
B25: =HYPERLINK("#Makeup!B6","Makeup") | C25: Makeup credit: minutes/sessions, documentation, holds.
B26: =HYPERLINK("#Skills!B6","Skills") | C26: Skills attempts: category, result, score, firearms course of fire.
B27: =HYPERLINK("#SkillsCheck!B6","SkillsCheck") | C27: One Pass/Fail per skills training per cadet — your call, not the attempt log's. Marking any skill Fail blocks graduation and names that skill in Blocking Issues. Blank is not a failure, but it is counted under 'Not Assessed'.
B28: =HYPERLINK("#Writing!B6","Writing") | C28: Type X when an assignment is received (auto-capitalizes).
B29: =HYPERLINK("#Incidents!B6","Incidents") | C29: Positive/negative incidents with severity and resolution.
B30: =HYPERLINK("#Counseling!B6","Counseling") | C30: Every intervention: tutoring, counseling, agency notification, performance plans. 'Agency Notified?' = Yes puts it in the next email digest.
B31: =HYPERLINK("#Memos!B6","Memos") | C31: Deficiency memos: assign, link to the I/A/C record, due auto-computes, mark received. 'Report to Agency?' is your call.
B32: =HYPERLINK("#DailyLog!B6","DailyLog") | C32: One row per training day — the digital daily report. Counters compute; mark when the leader's signed report is scanned.
B33: =HYPERLINK("#PT!B6","PT") | C33: Baseline and final raw values per event; final points once the rubric arrives.
B34: =HYPERLINK("#Medical!B6","Medical") | C34: Injuries, restrictions, clearances and expirations.
B35: =HYPERLINK("#Certifications!B6","Certifications") | C35: Per-cadet TIM/SFST/TCIC/CPR/ALERRT/ICS completion dates and certificate copies collected.
B36: =HYPERLINK("#StateExam!B6","StateExam") | C36: TCOLE licensing exam attempts and results (3 max).
B37: =HYPERLINK("#DismissalLog!B6","DismissalLog") | C37: Formal reviews: trigger, decision, approvals.
B38: =HYPERLINK("#AdvisoryBoard!B6","AdvisoryBoard") | C38: Governance: this academy's alignment record (policy version, minutes reviewed, workbook aligned) + the running board-meeting list with minutes folder locations. The Startup Review button fills it.
B39: End of academy / as needed
B40: =HYPERLINK("#Audit!B6","Audit") | C40: Program-requirement checklist answers + per-cadet enrollment documents grid.
B41: =HYPERLINK("#EmailPreview!B6","EmailPreview") | C41: Pick an agency to preview its email; the button builds Outlook drafts.
B42: =HYPERLINK("#sysAwards!B6","sysAwards") | C42: Award override cells — your pick always wins.
B43: =HYPERLINK("#PrintCenter!B6","PrintCenter") | C43: Every printable in one place (buttons after VBA install).

Sheet PrintCenter
B1: =HYPERLINK("#Dashboard!B5","◄ Dashboard")
B5: Print Center
B7: What | C7: How | D7: Sheet | E7: Macro (button)
B8: Daily report & roster (one day) | C8: Set the date on SignIn; blank date prints a generic form the leader dates by hand | D8: SignIn | E8: btnPrintSignIn
B9: Daily report & roster (week) | C9: Prints the next 5 class days, each pre-filled with its own date, day # and schedule | D9: SignIn | E9: btnPrintSignInWeek
B10: Academy book (all days) | C10: Every class day's form in one run — the class leader's bound book for the whole academy (print to PDF for the print shop) | D10: SignIn | E10: btnPrintSignInAcademy
B11: Course critique stack | C11: Set chapter on EvalSheet; prints one per active cadet | D11: EvalSheet | E11: btnPrintEvals
B12: Spelling test / key | C12: Set test # and mode on SpellingPrint | D12: SpellingPrint | E12: btnPrintSpelling
B13: Writing handout (week) | C13: Set week # on WritingHandout | D13: WritingHandout | E13: btnPrintWriting
B14: Cadet profile | C14: Set cadet on CadetProfile | D14: CadetProfile | E14: btnPrintProfile
B15: Transcript | C15: Set cadet on Transcript (button can run all cadets) | D15: Transcript | E15: btnPrintTranscript
B16: Class ranking | C16: Prints as-is | D16: Ranking | E16: btnPrintRanking
B17: Graduation checklist | C17: Prints as-is | D17: GradChecklist | E17: btnPrintGradCheck
B18: Audit packet | C18: Program checks + enrollment docs | D18: Audit | E18: btnPrintAudit
... B22: Schedule | C22: Full schedule listing | D22: Schedule | E22: btnPrintSchedule
B24: Buttons are added by the BPOC VBA install — run tools/Install-BPOC-VBA.ps1 (see docs/BPOC-Coordinator-Guide.md, 'Rebuilding from source'). Each button prints its sheet's defined print area to the default printer; Ctrl+P on the sheet does the same thing manually.

Sheet Cadets
B1: =HYPERLINK("#Dashboard!B5","◄ Dashboard")
B4: PID never changes once set — every other sheet keys off it. Capacity 50 cadets. A red PID (or red Cadet Name) means two rows share it: fix it immediately, both cadets' records are being merged.
B5: PID | C5: Last Name | D5: First Name | E5: MI | F5: Cadet Name | G5: AgencyID | H5: Agency Name | I5: Status | J5: Sort | K5: Enroll Date | L5: Separation Date | M5: Separation Reason
F6: =IF($B6="","",$C6&", "&$D6&IF($E6="",""," "&$E6&".")) | H6: =IF($G6="","",IFERROR(INDEX(rngAgencyNames,MATCH($G6,rngAgencyIDs,0)),"?")) | J6: =IF($B6="","",ROW()-5)
F7: =IF($B7="","",$C7&", "&$D7&IF($E7="",""," "&$E7&".")) | H7: =IF($G7="","",IFERROR(INDEX(rngAgencyNames,MATCH($G7,rngAgencyIDs,0)),"?")) | J7: =IF($B7="","",ROW()-5)
F8: =IF($B8="","",$C8&", "&$D8&IF($E8="",""," "&$E8&".")) | H8: =IF($G8="","",IFERROR(INDEX(rngAgencyNames,MATCH($G8,rngAgencyIDs,0)),"?")) | J8: =IF($B8="","",ROW()-5)
F9: =IF($B9="","",$C9&", "&$D9&IF($E9="",""," "&$E9&".")) | H9: =IF($G9="","",IFERROR(INDEX(rngAgencyNames,MATCH($G9,rngAgencyIDs,0)),"?")) | J9: =IF($B9="","",ROW()-5)
F10: =IF($B10="","",$C10&", "&$D10&IF($E10="",""," "&$E10&".")) | H10: =IF($G10="","",IFERROR(INDEX(rngAgencyNames,MATCH($G10,rngAgencyIDs,0)),"?")) | J10: =IF($B10="","",ROW()-5)
F11: =IF($B11="","",$C11&", "&$D11&IF($E11="",""," "&$E11&".")) | H11: =IF($G11="","",IFERROR(INDEX(rngAgencyNames,MATCH($G11,rngAgencyIDs,0)),"?")) | J11: =IF($B11="","",ROW()-5)
F12: =IF($B12="","",$C12&", "&$D12&IF($E12="",""," "&$E12&".")) | H12: =IF($G12="","",IFERROR(INDEX(rngAgencyNames,MATCH($G12,rngAgencyIDs,0)),"?")) | J12: =IF($B12="","",ROW()-5)
F13: =IF($B13="","",$C13&", "&$D13&IF($E13="",""," "&$E13&".")) | H13: =IF($G13="","",IFERROR(INDEX(rngAgencyNames,MATCH($G13,rngAgencyIDs,0)),"?")) | J13: =IF($B13="","",ROW()-5)
F14: =IF($B14="","",$C14&", "&$D14&IF($E14="",""," "&$E14&".")) | H14: =IF($G14="","",IFERROR(INDEX(rngAgencyNames,MATCH($G14,rngAgencyIDs,0)),"?")) | J14: =IF($B14="","",ROW()-5)
F15: =IF($B15="","",$C15&", "&$D15&IF($E15="",""," "&$E15&".")) | H15: =IF($G15="","",IFERROR(INDEX(rngAgencyNames,MATCH($G15,rngAgencyIDs,0)),"?")) | J15: =IF($B15="","",ROW()-5)
F16: =IF($B16="","",$C16&", "&$D16&IF($E16="",""," "&$E16&".")) | H16: =IF($G16="","",IFERROR(INDEX(rngAgencyNames,MATCH($G16,rngAgencyIDs,0)),"?")) | J16: =IF($B16="","",ROW()-5)
F17: =IF($B17="","",$C17&", "&$D17&IF($E17="",""," "&$E17&".")) | H17: =IF($G17="","",IFERROR(INDEX(rngAgencyNames,MATCH($G17,rngAgencyIDs,0)),"?")) | J17: =IF($B17="","",ROW()-5)
... F55: =IF($B55="","",$C55&", "&$D55&IF($E55="",""," "&$E55&".")) | H55: =IF($G55="","",IFERROR(INDEX(rngAgencyNames,MATCH($G55,rngAgencyIDs,0)),"?")) | J55: =IF($B55="","",ROW()-5)

Sheet ExamScores
B1: =HYPERLINK("#Dashboard!B5","◄ Dashboard")
B4: One row per attempt. Attempt 2 of a failed exam records at the 70 cap when passed (policy 300.5). Retest Due By = 5 class days after the failed attempt's date (a date that is not a class day rolls to the next one). Watch Row Check: a score that is not a number, a duplicate RecordID, an attempt 2 with no attempt 1 on file, or an attempt 2 logged against a first attempt that already PASSED each distort the category average. ABSENCE (last column): Unexcused = key Raw Score 0 as well - the zero is the record and it starts the retest clock; Excused = leave Raw Score blank, the first attempt is simply taken later and Retest Status reads EXCUSED - 1st attempt pending until the score is keyed on this same row.
B5: RecordID | C5: Cadet Name | D5: PID | E5: Agency | F5: ExamCode | G5: Exam Name | H5: Type | I5: Seq | J5: Passing | K5: Attempt # | L5: Raw Score | M5: Recorded | N5: AttemptPass | O5: Pass? | P5: FinalAttempt? | Q5: RetakeReq? | R5: DismissReview? | S5: Date | T5: Retest Due By | U5: Retest Status | V5: Entered By | W5: Notes | X5: Row Check | Y5: Absence
B6: =IF($C6="","",$D6&"-"&$F6&"-"&$K6) | D6: =IF($C6="","",IFERROR(INDEX(rngCadetPIDs,MATCH($C6,rngCadetNames,0)),"?")) | E6: =IF($D6="","",IFERROR(INDEX(nrCadetAgency,MATCH($D6,rngCadetPIDs,0)),"")) | G6: =IF($F6="","",IFERROR(INDEX(rngEPname,MATCH($F6,rngEPcode,0)),"?")) | H6: =IF($F6="","",IFERROR(INDEX(rngEPtype,MATCH($F6,rngEPcode,0)),"?")) | I6: =IF($F6="","",IFERROR(INDEX(rngEPseq,MATCH($F6,rngEPcode,0)),"")) | J6: =IF($F6="","",IFERROR(INDEX(rngEPpass,MATCH($F6,rngEPcode,0)),cfgPassingScore)) | M6: =IF($C6="","",IF($L6="","",IF(NOT(ISNUMBER($L6)),$L6,IF(N($K6)>2,"",IF($K6=1,IF(COUNTIFS(nrES_PID,$D6,nrES_Code,$F6,nrES_Att,2,nrES_Raw,">=0")>0,"",$L6),IF($L6>=$J6,MAX($J6,cfgRetakeRecordedCap),IF(COUNTIFS(nrES_PID,$D6,nrES_Code,$F6,nrES_Att,1)=0,$L6,SUMIFS(nrES_Raw,nrES_PID,$D6,nrES_Code,$F6,nrES_Att,1)))))))) | N6: =IF($C6="","",IF($L6="","",IF(NOT(ISNUMBER($L6)),"(not a score)",IF($L6>=$J6,"Yes","No")))) | O6: =IF($C6="","",IF($M6="","",IF(NOT(ISNUMBER($M6)),"(not a score)",IF($M6>=$J6,"Yes","No")))) | P6: =IF($C6="","",IF($K6="","",IF(N($K6)>2,"No",IF(COUNTIFS(nrES_PID,$D6,nrES_Code,$F6,nrES_Att,">"&$K6,nrES_Att,"<=2",nrES_Raw,">=0")=0,"Yes","No")))) | Q6: =IF($C6="","",IF($L6="","",IF(AND($K6=1,ISNUMBER($L6),$L6<$J6,COUNTIFS(nrES_PID,$D6,nrES_Code,$F6,nrES_Att,2,nrES_Raw,">=0")=0),"Yes","No"))) | R6: =IF($C6="","",IF($L6="","",IF(AND(N($K6)>=2,ISNUMBER($L6),$L6<$J6),"Yes","No"))) | T6: =IF(OR($C6="",$L6="",$K6<>1,NOT(ISNUMBER($L6)),$L6>=$J6),"",IF($S6="","(enter date)",_xlfn.LET(_xlpm.dn,_xlfn.XLOOKUP($S6,nrCDdate,nrCDnum,"",1),IF(_xlpm.dn="","(after last class day)",_xlfn.LET(_xlpm.dd,_xlfn.XLOOKUP(_xlpm.dn+cfgRetestClassDays,nrCDnum,nrCDdate,""),_xlpm.ok,_xlfn.XLOOKUP(_xlpm.dn+cfgRetestClassDays,nrCDnum,nrCDinsession,"No"),IF(OR(_xlpm.dd="",_xlpm.ok<>"Yes"),"(after last class day)",_xlpm.dd)))))) | U6: =IF($C6="","",IF(AND($Y6="Excused",$L6="",N($K6)<=1),"EXCUSED - 1st attempt pending",IF(OR($L6="",$K6<>1,NOT(ISNUMBER($L6)),$L6>=$J6),"",IF(COUNTIFS(nrES_PID,$D6,nrES_Code,$F6,nrES_Att,2,nrES_Raw,">=0")>0,IF(IFERROR(_xlfn.MINIFS(nrES_Date,nrES_PID,$D6,nrES_Code,$F6,nrES_Att,2,nrES_Raw,">=0",nrES_Date,">0"),0)=0,"RETEST UNDATED",IF(NOT(ISNUMBER($T6)),"RETEST DATE UNCHECKED",IF(_xlfn.MINIFS(nrES_Date,nrES_PID,$D6,nrES_Code,$F6,nrES_Att,2,nrES_Raw,">=0",nrES_Date,">0")>$T6,"LATE RETEST "&TEXT(_xlfn.MINIFS(nrES_Date,nrES_PID,$D6,nrES_Code,$F6,nrES_Att,2,nrES_Raw,">=0",nrES_Date,">0"),"mm/dd")&" (due "&TEXT($T6,"mm/dd")&")","Retested"))),IF(NOT(ISNUMBER($T6)),"CHECK DATE",IF(TODAY()>$T6,"OVERDUE","Due "&TEXT($T6,"mm/dd"))))))) | X6: =IF($C6="","",IF(AND($L6<>"",NOT(ISNUMBER($L6))),"RAW SCORE NOT A NUMBER",IF(AND(ISNUMBER($L6),OR($L6<0,$L6>100)),"RAW SCORE OUT OF RANGE",IF(AND($Y6="Unexcused",OR($L6="",NOT(ISNUMBER($L6)),$L6<>0)),"UNEXCUSED ABSENCE MUST RECORD 0",IF(COUNTIF(nrES_RecID,$B6)>1,"DUPLICATE RECORD",IF(N($K6)>2,"ATTEMPT 3+ NOT ALLOWED - policy 300.5 permits one retest per exam; this row records nothing",IF(AND($K6=2,COUNTIFS(nrES_PID,$D6,nrES_Code,$F6,nrES_Att,1)=0),"ATTEMPT 2 WITHOUT ATTEMPT 1",IF(AND($K6=2,$L6=""),"RETEST ROW HAS NO SCORE",IF(AND($H6="Final",$L6<>"",IFERROR(INDEX(nrCKfinalExamElig,MATCH($D6,rngCadetPIDs,0)),"")="No"),"FINAL EXAM AFTER FAILED FINAL PT (500.1.H)",IF(AND($K6=2,ISNUMBER($L6),COUNTIFS(nrES_PID,$D6,nrES_Code,$F6,nrES_Att,1)>0,SUMIFS(nrES_Raw,nrES_PID,$D6,nrES_Code,$F6,nrES_Att,1)>=$J6),"RETEST AFTER A PASSING FIRST ATTEMPT","OK"))))))))))
B7: =IF($C7="","",$D7&"-"&$F7&"-"&$K7) | D7: =IF($C7="","",IFERROR(INDEX(rngCadetPIDs,MATCH($C7,rngCadetNames,0)),"?")) | E7: =IF($D7="","",IFERROR(INDEX(nrCadetAgency,MATCH($D7,rngCadetPIDs,0)),"")) | G7: =IF($F7="","",IFERROR(INDEX(rngEPname,MATCH($F7,rngEPcode,0)),"?")) | H7: =IF($F7="","",IFERROR(INDEX(rngEPtype,MATCH($F7,rngEPcode,0)),"?")) | I7: =IF($F7="","",IFERROR(INDEX(rngEPseq,MATCH($F7,rngEPcode,0)),"")) | J7: =IF($F7="","",IFERROR(INDEX(rngEPpass,MATCH($F7,rngEPcode,0)),cfgPassingScore)) | M7: =IF($C7="","",IF($L7="","",IF(NOT(ISNUMBER($L7)),$L7,IF(N($K7)>2,"",IF($K7=1,IF(COUNTIFS(nrES_PID,$D7,nrES_Code,$F7,nrES_Att,2,nrES_Raw,">=0")>0,"",$L7),IF($L7>=$J7,MAX($J7,cfgRetakeRecordedCap),IF(COUNTIFS(nrES_PID,$D7,nrES_Code,$F7,nrES_Att,1)=0,$L7,SUMIFS(nrES_Raw,nrES_PID,$D7,nrES_Code,$F7,nrES_Att,1)))))))) | N7: =IF($C7="","",IF($L7="","",IF(NOT(ISNUMBER($L7)),"(not a score)",IF($L7>=$J7,"Yes","No")))) | O7: =IF($C7="","",IF($M7="","",IF(NOT(ISNUMBER($M7)),"(not a score)",IF($M7>=$J7,"Yes","No")))) | P7: =IF($C7="","",IF($K7="","",IF(N($K7)>2,"No",IF(COUNTIFS(nrES_PID,$D7,nrES_Code,$F7,nrES_Att,">"&$K7,nrES_Att,"<=2",nrES_Raw,">=0")=0,"Yes","No")))) | Q7: =IF($C7="","",IF($L7="","",IF(AND($K7=1,ISNUMBER($L7),$L7<$J7,COUNTIFS(nrES_PID,$D7,nrES_Code,$F7,nrES_Att,2,nrES_Raw,">=0")=0),"Yes","No"))) | R7: =IF($C7="","",IF($L7="","",IF(AND(N($K7)>=2,ISNUMBER($L7),$L7<$J7),"Yes","No"))) | T7: =IF(OR($C7="",$L7="",$K7<>1,NOT(ISNUMBER($L7)),$L7>=$J7),"",IF($S7="","(enter date)",_xlfn.LET(_xlpm.dn,_xlfn.XLOOKUP($S7,nrCDdate,nrCDnum,"",1),IF(_xlpm.dn="","(after last class day)",_xlfn.LET(_xlpm.dd,_xlfn.XLOOKUP(_xlpm.dn+cfgRetestClassDays,nrCDnum,nrCDdate,""),_xlpm.ok,_xlfn.XLOOKUP(_xlpm.dn+cfgRetestClassDays,nrCDnum,nrCDinsession,"No"),IF(OR(_xlpm.dd="",_xlpm.ok<>"Yes"),"(after last class day)",_xlpm.dd)))))) | U7: =IF($C7="","",IF(AND($Y7="Excused",$L7="",N($K7)<=1),"EXCUSED - 1st attempt pending",IF(OR($L7="",$K7<>1,NOT(ISNUMBER($L7)),$L7>=$J7),"",IF(COUNTIFS(nrES_PID,$D7,nrES_Code,$F7,nrES_Att,2,nrES_Raw,">=0")>0,IF(IFERROR(_xlfn.MINIFS(nrES_Date,nrES_PID,$D7,nrES_Code,$F7,nrES_Att,2,nrES_Raw,">=0",nrES_Date,">0"),0)=0,"RETEST UNDATED",IF(NOT(ISNUMBER($T7)),"RETEST DATE UNCHECKED",IF(_xlfn.MINIFS(nrES_Date,nrES_PID,$D7,nrES_Code,$F7,nrES_Att,2,nrES_Raw,">=0",nrES_Date,">0")>$T7,"LATE RETEST "&TEXT(_xlfn.MINIFS(nrES_Date,nrES_PID,$D7,nrES_Code,$F7,nrES_Att,2,nrES_Raw,">=0",nrES_Date,">0"),"mm/dd")&" (due "&TEXT($T7,"mm/dd")&")","Retested"))),IF(NOT(ISNUMBER($T7)),"CHECK DATE",IF(TODAY()>$T7,"OVERDUE","Due "&TEXT($T7,"mm/dd"))))))) | X7: =IF($C7="","",IF(AND($L7<>"",NOT(ISNUMBER($L7))),"RAW SCORE NOT A NUMBER",IF(AND(ISNUMBER($L7),OR($L7<0,$L7>100)),"RAW SCORE OUT OF RANGE",IF(AND($Y7="Unexcused",OR($L7="",NOT(ISNUMBER($L7)),$L7<>0)),"UNEXCUSED ABSENCE MUST RECORD 0",IF(COUNTIF(nrES_RecID,$B7)>1,"DUPLICATE RECORD",IF(N($K7)>2,"ATTEMPT 3+ NOT ALLOWED - policy 300.5 permits one retest per exam; this row records nothing",IF(AND($K7=2,COUNTIFS(nrES_PID,$D7,nrES_Code,$F7,nrES_Att,1)=0),"ATTEMPT 2 WITHOUT ATTEMPT 1",IF(AND($K7=2,$L7=""),"RETEST ROW HAS NO SCORE",IF(AND($H7="Final",$L7<>"",IFERROR(INDEX(nrCKfinalExamElig,MATCH($D7,rngCadetPIDs,0)),"")="No"),"FINAL EXAM AFTER FAILED FINAL PT (500.1.H)",IF(AND($K7=2,ISNUMBER($L7),COUNTIFS(nrES_PID,$D7,nrES_Code,$F7,nrES_Att,1)>0,SUMIFS(nrES_Raw,nrES_PID,$D7,nrES_Code,$F7,nrES_Att,1)>=$J7),"RETEST AFTER A PASSING FIRST ATTEMPT","OK"))))))))))
B8: =IF($C8="","",$D8&"-"&$F8&"-"&$K8) | D8: =IF($C8="","",IFERROR(INDEX(rngCadetPIDs,MATCH($C8,rngCadetNames,0)),"?")) | E8: =IF($D8="","",IFERROR(INDEX(nrCadetAgency,MATCH($D8,rngCadetPIDs,0)),"")) | G8: =IF($F8="","",IFERROR(INDEX(rngEPname,MATCH($F8,rngEPcode,0)),"?")) | H8: =IF($F8="","",IFERROR(INDEX(rngEPtype,MATCH($F8,rngEPcode,0)),"?")) | I8: =IF($F8="","",IFERROR(INDEX(rngEPseq,MATCH($F8,rngEPcode,0)),"")) | J8: =IF($F8="","",IFERROR(INDEX(rngEPpass,MATCH($F8,rngEPcode,0)),cfgPassingScore)) | M8: =IF($C8="","",IF($L8="","",IF(NOT(ISNUMBER($L8)),$L8,IF(N($K8)>2,"",IF($K8=1,IF(COUNTIFS(nrES_PID,$D8,nrES_Code,$F8,nrES_Att,2,nrES_Raw,">=0")>0,"",$L8),IF($L8>=$J8,MAX($J8,cfgRetakeRecordedCap),IF(COUNTIFS(nrES_PID,$D8,nrES_Code,$F8,nrES_Att,1)=0,$L8,SUMIFS(nrES_Raw,nrES_PID,$D8,nrES_Code,$F8,nrES_Att,1)))))))) | N8: =IF($C8="","",IF($L8="","",IF(NOT(ISNUMBER($L8)),"(not a score)",IF($L8>=$J8,"Yes","No")))) | O8: =IF($C8="","",IF($M8="","",IF(NOT(ISNUMBER($M8)),"(not a score)",IF($M8>=$J8,"Yes","No")))) | P8: =IF($C8="","",IF($K8="","",IF(N($K8)>2,"No",IF(COUNTIFS(nrES_PID,$D8,nrES_Code,$F8,nrES_Att,">"&$K8,nrES_Att,"<=2",nrES_Raw,">=0")=0,"Yes","No")))) | Q8: =IF($C8="","",IF($L8="","",IF(AND($K8=1,ISNUMBER($L8),$L8<$J8,COUNTIFS(nrES_PID,$D8,nrES_Code,$F8,nrES_Att,2,nrES_Raw,">=0")=0),"Yes","No"))) | R8: =IF($C8="","",IF($L8="","",IF(AND(N($K8)>=2,ISNUMBER($L8),$L8<$J8),"Yes","No"))) | T8: =IF(OR($C8="",$L8="",$K8<>1,NOT(ISNUMBER($L8)),$L8>=$J8),"",IF($S8="","(enter date)",_xlfn.LET(_xlpm.dn,_xlfn.XLOOKUP($S8,nrCDdate,nrCDnum,"",1),IF(_xlpm.dn="","(after last class day)",_xlfn.LET(_xlpm.dd,_xlfn.XLOOKUP(_xlpm.dn+cfgRetestClassDays,nrCDnum,nrCDdate,""),_xlpm.ok,_xlfn.XLOOKUP(_xlpm.dn+cfgRetestClassDays,nrCDnum,nrCDinsession,"No"),IF(OR(_xlpm.dd="",_xlpm.ok<>"Yes"),"(after last class day)",_xlpm.dd)))))) | U8: =IF($C8="","",IF(AND($Y8="Excused",$L8="",N($K8)<=1),"EXCUSED - 1st attempt pending",IF(OR($L8="",$K8<>1,NOT(ISNUMBER($L8)),$L8>=$J8),"",IF(COUNTIFS(nrES_PID,$D8,nrES_Code,$F8,nrES_Att,2,nrES_Raw,">=0")>0,IF(IFERROR(_xlfn.MINIFS(nrES_Date,nrES_PID,$D8,nrES_Code,$F8,nrES_Att,2,nrES_Raw,">=0",nrES_Date,">0"),0)=0,"RETEST UNDATED",IF(NOT(ISNUMBER($T8)),"RETEST DATE UNCHECKED",IF(_xlfn.MINIFS(nrES_Date,nrES_PID,$D8,nrES_Code,$F8,nrES_Att,2,nrES_Raw,">=0",nrES_Date,">0")>$T8,"LATE RETEST "&TEXT(_xlfn.MINIFS(nrES_Date,nrES_PID,$D8,nrES_Code,$F8,nrES_Att,2,nrES_Raw,">=0",nrES_Date,">0"),"mm/dd")&" (due "&TEXT($T8,"mm/dd")&")","Retested"))),IF(NOT(ISNUMBER($T8)),"CHECK DATE",IF(TODAY()>$T8,"OVERDUE","Due "&TEXT($T8,"mm/dd"))))))) | X8: =IF($C8="","",IF(AND($L8<>"",NOT(ISNUMBER($L8))),"RAW SCORE NOT A NUMBER",IF(AND(ISNUMBER($L8),OR($L8<0,$L8>100)),"RAW SCORE OUT OF RANGE",IF(AND($Y8="Unexcused",OR($L8="",NOT(ISNUMBER($L8)),$L8<>0)),"UNEXCUSED ABSENCE MUST RECORD 0",IF(COUNTIF(nrES_RecID,$B8)>1,"DUPLICATE RECORD",IF(N($K8)>2,"ATTEMPT 3+ NOT ALLOWED - policy 300.5 permits one retest per exam; this row records nothing",IF(AND($K8=2,COUNTIFS(nrES_PID,$D8,nrES_Code,$F8,nrES_Att,1)=0),"ATTEMPT 2 WITHOUT ATTEMPT 1",IF(AND($K8=2,$L8=""),"RETEST ROW HAS NO SCORE",IF(AND($H8="Final",$L8<>"",IFERROR(INDEX(nrCKfinalExamElig,MATCH($D8,rngCadetPIDs,0)),"")="No"),"FINAL EXAM AFTER FAILED FINAL PT (500.1.H)",IF(AND($K8=2,ISNUMBER($L8),COUNTIFS(nrES_PID,$D8,nrES_Code,$F8,nrES_Att,1)>0,SUMIFS(nrES_Raw,nrES_PID,$D8,nrES_Code,$F8,nrES_Att,1)>=$J8),"RETEST AFTER A PASSING FIRST ATTEMPT","OK"))))))))))
B9: =IF($C9="","",$D9&"-"&$F9&"-"&$K9) | D9: =IF($C9="","",IFERROR(INDEX(rngCadetPIDs,MATCH($C9,rngCadetNames,0)),"?")) | E9: =IF($D9="","",IFERROR(INDEX(nrCadetAgency,MATCH($D9,rngCadetPIDs,0)),"")) | G9: =IF($F9="","",IFERROR(INDEX(rngEPname,MATCH($F9,rngEPcode,0)),"?")) | H9: =IF($F9="","",IFERROR(INDEX(rngEPtype,MATCH($F9,rngEPcode,0)),"?")) | I9: =IF($F9="","",IFERROR(INDEX(rngEPseq,MATCH($F9,rngEPcode,0)),"")) | J9: =IF($F9="","",IFERROR(INDEX(rngEPpass,MATCH($F9,rngEPcode,0)),cfgPassingScore)) | M9: =IF($C9="","",IF($L9="","",IF(NOT(ISNUMBER($L9)),$L9,IF(N($K9)>2,"",IF($K9=1,IF(COUNTIFS(nrES_PID,$D9,nrES_Code,$F9,nrES_Att,2,nrES_Raw,">=0")>0,"",$L9),IF($L9>=$J9,MAX($J9,cfgRetakeRecordedCap),IF(COUNTIFS(nrES_PID,$D9,nrES_Code,$F9,nrES_Att,1)=0,$L9,SUMIFS(nrES_Raw,nrES_PID,$D9,nrES_Code,$F9,nrES_Att,1)))))))) | N9: =IF($C9="","",IF($L9="","",IF(NOT(ISNUMBER($L9)),"(not a score)",IF($L9>=$J9,"Yes","No")))) | O9: =IF($C9="","",IF($M9="","",IF(NOT(ISNUMBER($M9)),"(not a score)",IF($M9>=$J9,"Yes","No")))) | P9: =IF($C9="","",IF($K9="","",IF(N($K9)>2,"No",IF(COUNTIFS(nrES_PID,$D9,nrES_Code,$F9,nrES_Att,">"&$K9,nrES_Att,"<=2",nrES_Raw,">=0")=0,"Yes","No")))) | Q9: =IF($C9="","",IF($L9="","",IF(AND($K9=1,ISNUMBER($L9),$L9<$J9,COUNTIFS(nrES_PID,$D9,nrES_Code,$F9,nrES_Att,2,nrES_Raw,">=0")=0),"Yes","No"))) | R9: =IF($C9="","",IF($L9="","",IF(AND(N($K9)>=2,ISNUMBER($L9),$L9<$J9),"Yes","No"))) | T9: =IF(OR($C9="",$L9="",$K9<>1,NOT(ISNUMBER($L9)),$L9>=$J9),"",IF($S9="","(enter date)",_xlfn.LET(_xlpm.dn,_xlfn.XLOOKUP($S9,nrCDdate,nrCDnum,"",1),IF(_xlpm.dn="","(after last class day)",_xlfn.LET(_xlpm.dd,_xlfn.XLOOKUP(_xlpm.dn+cfgRetestClassDays,nrCDnum,nrCDdate,""),_xlpm.ok,_xlfn.XLOOKUP(_xlpm.dn+cfgRetestClassDays,nrCDnum,nrCDinsession,"No"),IF(OR(_xlpm.dd="",_xlpm.ok<>"Yes"),"(after last class day)",_xlpm.dd)))))) | U9: =IF($C9="","",IF(AND($Y9="Excused",$L9="",N($K9)<=1),"EXCUSED - 1st attempt pending",IF(OR($L9="",$K9<>1,NOT(ISNUMBER($L9)),$L9>=$J9),"",IF(COUNTIFS(nrES_PID,$D9,nrES_Code,$F9,nrES_Att,2,nrES_Raw,">=0")>0,IF(IFERROR(_xlfn.MINIFS(nrES_Date,nrES_PID,$D9,nrES_Code,$F9,nrES_Att,2,nrES_Raw,">=0",nrES_Date,">0"),0)=0,"RETEST UNDATED",IF(NOT(ISNUMBER($T9)),"RETEST DATE UNCHECKED",IF(_xlfn.MINIFS(nrES_Date,nrES_PID,$D9,nrES_Code,$F9,nrES_Att,2,nrES_Raw,">=0",nrES_Date,">0")>$T9,"LATE RETEST "&TEXT(_xlfn.MINIFS(nrES_Date,nrES_PID,$D9,nrES_Code,$F9,nrES_Att,2,nrES_Raw,">=0",nrES_Date,">0"),"mm/dd")&" (due "&TEXT($T9,"mm/dd")&")","Retested"))),IF(NOT(ISNUMBER($T9)),"CHECK DATE",IF(TODAY()>$T9,"OVERDUE","Due "&TEXT($T9,"mm/dd"))))))) | X9: =IF($C9="","",IF(AND($L9<>"",NOT(ISNUMBER($L9))),"RAW SCORE NOT A NUMBER",IF(AND(ISNUMBER($L9),OR($L9<0,$L9>100)),"RAW SCORE OUT OF RANGE",IF(AND($Y9="Unexcused",OR($L9="",NOT(ISNUMBER($L9)),$L9<>0)),"UNEXCUSED ABSENCE MUST RECORD 0",IF(COUNTIF(nrES_RecID,$B9)>1,"DUPLICATE RECORD",IF(N($K9)>2,"ATTEMPT 3+ NOT ALLOWED - policy 300.5 permits one retest per exam; this row records nothing",IF(AND($K9=2,COUNTIFS(nrES_PID,$D9,nrES_Code,$F9,nrES_Att,1)=0),"ATTEMPT 2 WITHOUT ATTEMPT 1",IF(AND($K9=2,$L9=""),"RETEST ROW HAS NO SCORE",IF(AND($H9="Final",$L9<>"",IFERROR(INDEX(nrCKfinalExamElig,MATCH($D9,rngCadetPIDs,0)),"")="No"),"FINAL EXAM AFTER FAILED FINAL PT (500.1.H)",IF(AND($K9=2,ISNUMBER($L9),COUNTIFS(nrES_PID,$D9,nrES_Code,$F9,nrES_Att,1)>0,SUMIFS(nrES_Raw,nrES_PID,$D9,nrES_Code,$F9,nrES_Att,1)>=$J9),"RETEST AFTER A PASSING FIRST ATTEMPT","OK"))))))))))
B10: =IF($C10="","",$D10&"-"&$F10&"-"&$K10) | D10: =IF($C10="","",IFERROR(INDEX(rngCadetPIDs,MATCH($C10,rngCadetNames,0)),"?")) | E10: =IF($D10="","",IFERROR(INDEX(nrCadetAgency,MATCH($D10,rngCadetPIDs,0)),"")) | G10: =IF($F10="","",IFERROR(INDEX(rngEPname,MATCH($F10,rngEPcode,0)),"?")) | H10: =IF($F10="","",IFERROR(INDEX(rngEPtype,MATCH($F10,rngEPcode,0)),"?")) | I10: =IF($F10="","",IFERROR(INDEX(rngEPseq,MATCH($F10,rngEPcode,0)),"")) | J10: =IF($F10="","",IFERROR(INDEX(rngEPpass,MATCH($F10,rngEPcode,0)),cfgPassingScore)) | M10: =IF($C10="","",IF($L10="","",IF(NOT(ISNUMBER($L10)),$L10,IF(N($K10)>2,"",IF($K10=1,IF(COUNTIFS(nrES_PID,$D10,nrES_Code,$F10,nrES_Att,2,nrES_Raw,">=0")>0,"",$L10),IF($L10>=$J10,MAX($J10,cfgRetakeRecordedCap),IF(COUNTIFS(nrES_PID,$D10,nrES_Code,$F10,nrES_Att,1)=0,$L10,SUMIFS(nrES_Raw,nrES_PID,$D10,nrES_Code,$F10,nrES_Att,1)))))))) | N10: =IF($C10="","",IF($L10="","",IF(NOT(ISNUMBER($L10)),"(not a score)",IF($L10>=$J10,"Yes","No")))) | O10: =IF($C10="","",IF($M10="","",IF(NOT(ISNUMBER($M10)),"(not a score)",IF($M10>=$J10,"Yes","No")))) | P10: =IF($C10="","",IF($K10="","",IF(N($K10)>2,"No",IF(COUNTIFS(nrES_PID,$D10,nrES_Code,$F10,nrES_Att,">"&$K10,nrES_Att,"<=2",nrES_Raw,">=0")=0,"Yes","No")))) | Q10: =IF($C10="","",IF($L10="","",IF(AND($K10=1,ISNUMBER($L10),$L10<$J10,COUNTIFS(nrES_PID,$D10,nrES_Code,$F10,nrES_Att,2,nrES_Raw,">=0")=0),"Yes","No"))) | R10: =IF($C10="","",IF($L10="","",IF(AND(N($K10)>=2,ISNUMBER($L10),$L10<$J10),"Yes","No"))) | T10: =IF(OR($C10="",$L10="",$K10<>1,NOT(ISNUMBER($L10)),$L10>=$J10),"",IF($S10="","(enter date)",_xlfn.LET(_xlpm.dn,_xlfn.XLOOKUP($S10,nrCDdate,nrCDnum,"",1),IF(_xlpm.dn="","(after last class day)",_xlfn.LET(_xlpm.dd,_xlfn.XLOOKUP(_xlpm.dn+cfgRetestClassDays,nrCDnum,nrCDdate,""),_xlpm.ok,_xlfn.XLOOKUP(_xlpm.dn+cfgRetestClassDays,nrCDnum,nrCDinsession,"No"),IF(OR(_xlpm.dd="",_xlpm.ok<>"Yes"),"(after last class day)",_xlpm.dd)))))) | U10: =IF($C10="","",IF(AND($Y10="Excused",$L10="",N($K10)<=1),"EXCUSED - 1st attempt pending",IF(OR($L10="",$K10<>1,NOT(ISNUMBER($L10)),$L10>=$J10),"",IF(COUNTIFS(nrES_PID,$D10,nrES_Code,$F10,nrES_Att,2,nrES_Raw,">=0")>0,IF(IFERROR(_xlfn.MINIFS(nrES_Date,nrES_PID,$D10,nrES_Code,$F10,nrES_Att,2,nrES_Raw,">=0",nrES_Date,">0"),0)=0,"RETEST UNDATED",IF(NOT(ISNUMBER($T10)),"RETEST DATE UNCHECKED",IF(_xlfn.MINIFS(nrES_Date,nrES_PID,$D10,nrES_Code,$F10,nrES_Att,2,nrES_Raw,">=0",nrES_Date,">0")>$T10,"LATE RETEST "&TEXT(_xlfn.MINIFS(nrES_Date,nrES_PID,$D10,nrES_Code,$F10,nrES_Att,2,nrES_Raw,">=0",nrES_Date,">0"),"mm/dd")&" (due "&TEXT($T10,"mm/dd")&")","Retested"))),IF(NOT(ISNUMBER($T10)),"CHECK DATE",IF(TODAY()>$T10,"OVERDUE","Due "&TEXT($T10,"mm/dd"))))))) | X10: =IF($C10="","",IF(AND($L10<>"",NOT(ISNUMBER($L10))),"RAW SCORE NOT A NUMBER",IF(AND(ISNUMBER($L10),OR($L10<0,$L10>100)),"RAW SCORE OUT OF RANGE",IF(AND($Y10="Unexcused",OR($L10="",NOT(ISNUMBER($L10)),$L10<>0)),"UNEXCUSED ABSENCE MUST RECORD 0",IF(COUNTIF(nrES_RecID,$B10)>1,"DUPLICATE RECORD",IF(N($K10)>2,"ATTEMPT 3+ NOT ALLOWED - policy 300.5 permits one retest per exam; this row records nothing",IF(AND($K10=2,COUNTIFS(nrES_PID,$D10,nrES_Code,$F10,nrES_Att,1)=0),"ATTEMPT 2 WITHOUT ATTEMPT 1",IF(AND($K10=2,$L10=""),"RETEST ROW HAS NO SCORE",IF(AND($H10="Final",$L10<>"",IFERROR(INDEX(nrCKfinalExamElig,MATCH($D10,rngCadetPIDs,0)),"")="No"),"FINAL EXAM AFTER FAILED FINAL PT (500.1.H)",IF(AND($K10=2,ISNUMBER($L10),COUNTIFS(nrES_PID,$D10,nrES_Code,$F10,nrES_Att,1)>0,SUMIFS(nrES_Raw,nrES_PID,$D10,nrES_Code,$F10,nrES_Att,1)>=$J10),"RETEST AFTER A PASSING FIRST ATTEMPT","OK"))))))))))
B11: =IF($C11="","",$D11&"-"&$F11&"-"&$K11) | D11: =IF($C11="","",IFERROR(INDEX(rngCadetPIDs,MATCH($C11,rngCadetNames,0)),"?")) | E11: =IF($D11="","",IFERROR(INDEX(nrCadetAgency,MATCH($D11,rngCadetPIDs,0)),"")) | G11: =IF($F11="","",IFERROR(INDEX(rngEPname,MATCH($F11,rngEPcode,0)),"?")) | H11: =IF($F11="","",IFERROR(INDEX(rngEPtype,MATCH($F11,rngEPcode,0)),"?")) | I11: =IF($F11="","",IFERROR(INDEX(rngEPseq,MATCH($F11,rngEPcode,0)),"")) | J11: =IF($F11="","",IFERROR(INDEX(rngEPpass,MATCH($F11,rngEPcode,0)),cfgPassingScore)) | M11: =IF($C11="","",IF($L11="","",IF(NOT(ISNUMBER($L11)),$L11,IF(N($K11)>2,"",IF($K11=1,IF(COUNTIFS(nrES_PID,$D11,nrES_Code,$F11,nrES_Att,2,nrES_Raw,">=0")>0,"",$L11),IF($L11>=$J11,MAX($J11,cfgRetakeRecordedCap),IF(COUNTIFS(nrES_PID,$D11,nrES_Code,$F11,nrES_Att,1)=0,$L11,SUMIFS(nrES_Raw,nrES_PID,$D11,nrES_Code,$F11,nrES_Att,1)))))))) | N11: =IF($C11="","",IF($L11="","",IF(NOT(ISNUMBER($L11)),"(not a score)",IF($L11>=$J11,"Yes","No")))) | O11: =IF($C11="","",IF($M11="","",IF(NOT(ISNUMBER($M11)),"(not a score)",IF($M11>=$J11,"Yes","No")))) | P11: =IF($C11="","",IF($K11="","",IF(N($K11)>2,"No",IF(COUNTIFS(nrES_PID,$D11,nrES_Code,$F11,nrES_Att,">"&$K11,nrES_Att,"<=2",nrES_Raw,">=0")=0,"Yes","No")))) | Q11: =IF($C11="","",IF($L11="","",IF(AND($K11=1,ISNUMBER($L11),$L11<$J11,COUNTIFS(nrES_PID,$D11,nrES_Code,$F11,nrES_Att,2,nrES_Raw,">=0")=0),"Yes","No"))) | R11: =IF($C11="","",IF($L11="","",IF(AND(N($K11)>=2,ISNUMBER($L11),$L11<$J11),"Yes","No"))) | T11: =IF(OR($C11="",$L11="",$K11<>1,NOT(ISNUMBER($L11)),$L11>=$J11),"",IF($S11="","(enter date)",_xlfn.LET(_xlpm.dn,_xlfn.XLOOKUP($S11,nrCDdate,nrCDnum,"",1),IF(_xlpm.dn="","(after last class day)",_xlfn.LET(_xlpm.dd,_xlfn.XLOOKUP(_xlpm.dn+cfgRetestClassDays,nrCDnum,nrCDdate,""),_xlpm.ok,_xlfn.XLOOKUP(_xlpm.dn+cfgRetestClassDays,nrCDnum,nrCDinsession,"No"),IF(OR(_xlpm.dd="",_xlpm.ok<>"Yes"),"(after last class day)",_xlpm.dd)))))) | U11: =IF($C11="","",IF(AND($Y11="Excused",$L11="",N($K11)<=1),"EXCUSED - 1st attempt pending",IF(OR($L11="",$K11<>1,NOT(ISNUMBER($L11)),$L11>=$J11),"",IF(COUNTIFS(nrES_PID,$D11,nrES_Code,$F11,nrES_Att,2,nrES_Raw,">=0")>0,IF(IFERROR(_xlfn.MINIFS(nrES_Date,nrES_PID,$D11,nrES_Code,$F11,nrES_Att,2,nrES_Raw,">=0",nrES_Date,">0"),0)=0,"RETEST UNDATED",IF(NOT(ISNUMBER($T11)),"RETEST DATE UNCHECKED",IF(_xlfn.MINIFS(nrES_Date,nrES_PID,$D11,nrES_Code,$F11,nrES_Att,2,nrES_Raw,">=0",nrES_Date,">0")>$T11,"LATE RETEST "&TEXT(_xlfn.MINIFS(nrES_Date,nrES_PID,$D11,nrES_Code,$F11,nrES_Att,2,nrES_Raw,">=0",nrES_Date,">0"),"mm/dd")&" (due "&TEXT($T11,"mm/dd")&")","Retested"))),IF(NOT(ISNUMBER($T11)),"CHECK DATE",IF(TODAY()>$T11,"OVERDUE","Due "&TEXT($T11,"mm/dd"))))))) | X11: =IF($C11="","",IF(AND($L11<>"",NOT(ISNUMBER($L11))),"RAW SCORE NOT A NUMBER",IF(AND(ISNUMBER($L11),OR($L11<0,$L11>100)),"RAW SCORE OUT OF RANGE",IF(AND($Y11="Unexcused",OR($L11="",NOT(ISNUMBER($L11)),$L11<>0)),"UNEXCUSED ABSENCE MUST RECORD 0",IF(COUNTIF(nrES_RecID,$B11)>1,"DUPLICATE RECORD",IF(N($K11)>2,"ATTEMPT 3+ NOT ALLOWED - policy 300.5 permits one retest per exam; this row records nothing",IF(AND($K11=2,COUNTIFS(nrES_PID,$D11,nrES_Code,$F11,nrES_Att,1)=0),"ATTEMPT 2 WITHOUT ATTEMPT 1",IF(AND($K11=2,$L11=""),"RETEST ROW HAS NO SCORE",IF(AND($H11="Final",$L11<>"",IFERROR(INDEX(nrCKfinalExamElig,MATCH($D11,rngCadetPIDs,0)),"")="No"),"FINAL EXAM AFTER FAILED FINAL PT (500.1.H)",IF(AND($K11=2,ISNUMBER($L11),COUNTIFS(nrES_PID,$D11,nrES_Code,$F11,nrES_Att,1)>0,SUMIFS(nrES_Raw,nrES_PID,$D11,nrES_Code,$F11,nrES_Att,1)>=$J11),"RETEST AFTER A PASSING FIRST ATTEMPT","OK"))))))))))
B12: =IF($C12="","",$D12&"-"&$F12&"-"&$K12) | D12: =IF($C12="","",IFERROR(INDEX(rngCadetPIDs,MATCH($C12,rngCadetNames,0)),"?")) | E12: =IF($D12="","",IFERROR(INDEX(nrCadetAgency,MATCH($D12,rngCadetPIDs,0)),"")) | G12: =IF($F12="","",IFERROR(INDEX(rngEPname,MATCH($F12,rngEPcode,0)),"?")) | H12: =IF($F12="","",IFERROR(INDEX(rngEPtype,MATCH($F12,rngEPcode,0)),"?")) | I12: =IF($F12="","",IFERROR(INDEX(rngEPseq,MATCH($F12,rngEPcode,0)),"")) | J12: =IF($F12="","",IFERROR(INDEX(rngEPpass,MATCH($F12,rngEPcode,0)),cfgPassingScore)) | M12: =IF($C12="","",IF($L12="","",IF(NOT(ISNUMBER($L12)),$L12,IF(N($K12)>2,"",IF($K12=1,IF(COUNTIFS(nrES_PID,$D12,nrES_Code,$F12,nrES_Att,2,nrES_Raw,">=0")>0,"",$L12),IF($L12>=$J12,MAX($J12,cfgRetakeRecordedCap),IF(COUNTIFS(nrES_PID,$D12,nrES_Code,$F12,nrES_Att,1)=0,$L12,SUMIFS(nrES_Raw,nrES_PID,$D12,nrES_Code,$F12,nrES_Att,1)))))))) | N12: =IF($C12="","",IF($L12="","",IF(NOT(ISNUMBER($L12)),"(not a score)",IF($L12>=$J12,"Yes","No")))) | O12: =IF($C12="","",IF($M12="","",IF(NOT(ISNUMBER($M12)),"(not a score)",IF($M12>=$J12,"Yes","No")))) | P12: =IF($C12="","",IF($K12="","",IF(N($K12)>2,"No",IF(COUNTIFS(nrES_PID,$D12,nrES_Code,$F12,nrES_Att,">"&$K12,nrES_Att,"<=2",nrES_Raw,">=0")=0,"Yes","No")))) | Q12: =IF($C12="","",IF($L12="","",IF(AND($K12=1,ISNUMBER($L12),$L12<$J12,COUNTIFS(nrES_PID,$D12,nrES_Code,$F12,nrES_Att,2,nrES_Raw,">=0")=0),"Yes","No"))) | R12: =IF($C12="","",IF($L12="","",IF(AND(N($K12)>=2,ISNUMBER($L12),$L12<$J12),"Yes","No"))) | T12: =IF(OR($C12="",$L12="",$K12<>1,NOT(ISNUMBER($L12)),$L12>=$J12),"",IF($S12="","(enter date)",_xlfn.LET(_xlpm.dn,_xlfn.XLOOKUP($S12,nrCDdate,nrCDnum,"",1),IF(_xlpm.dn="","(after last class day)",_xlfn.LET(_xlpm.dd,_xlfn.XLOOKUP(_xlpm.dn+cfgRetestClassDays,nrCDnum,nrCDdate,""),_xlpm.ok,_xlfn.XLOOKUP(_xlpm.dn+cfgRetestClassDays,nrCDnum,nrCDinsession,"No"),IF(OR(_xlpm.dd="",_xlpm.ok<>"Yes"),"(after last class day)",_xlpm.dd)))))) | U12: =IF($C12="","",IF(AND($Y12="Excused",$L12="",N($K12)<=1),"EXCUSED - 1st attempt pending",IF(OR($L12="",$K12<>1,NOT(ISNUMBER($L12)),$L12>=$J12),"",IF(COUNTIFS(nrES_PID,$D12,nrES_Code,$F12,nrES_Att,2,nrES_Raw,">=0")>0,IF(IFERROR(_xlfn.MINIFS(nrES_Date,nrES_PID,$D12,nrES_Code,$F12,nrES_Att,2,nrES_Raw,">=0",nrES_Date,">0"),0)=0,"RETEST UNDATED",IF(NOT(ISNUMBER($T12)),"RETEST DATE UNCHECKED",IF(_xlfn.MINIFS(nrES_Date,nrES_PID,$D12,nrES_Code,$F12,nrES_Att,2,nrES_Raw,">=0",nrES_Date,">0")>$T12,"LATE RETEST "&TEXT(_xlfn.MINIFS(nrES_Date,nrES_PID,$D12,nrES_Code,$F12,nrES_Att,2,nrES_Raw,">=0",nrES_Date,">0"),"mm/dd")&" (due "&TEXT($T12,"mm/dd")&")","Retested"))),IF(NOT(ISNUMBER($T12)),"CHECK DATE",IF(TODAY()>$T12,"OVERDUE","Due "&TEXT($T12,"mm/dd"))))))) | X12: =IF($C12="","",IF(AND($L12<>"",NOT(ISNUMBER($L12))),"RAW SCORE NOT A NUMBER",IF(AND(ISNUMBER($L12),OR($L12<0,$L12>100)),"RAW SCORE OUT OF RANGE",IF(AND($Y12="Unexcused",OR($L12="",NOT(ISNUMBER($L12)),$L12<>0)),"UNEXCUSED ABSENCE MUST RECORD 0",IF(COUNTIF(nrES_RecID,$B12)>1,"DUPLICATE RECORD",IF(N($K12)>2,"ATTEMPT 3+ NOT ALLOWED - policy 300.5 permits one retest per exam; this row records nothing",IF(AND($K12=2,COUNTIFS(nrES_PID,$D12,nrES_Code,$F12,nrES_Att,1)=0),"ATTEMPT 2 WITHOUT ATTEMPT 1",IF(AND($K12=2,$L12=""),"RETEST ROW HAS NO SCORE",IF(AND($H12="Final",$L12<>"",IFERROR(INDEX(nrCKfinalExamElig,MATCH($D12,rngCadetPIDs,0)),"")="No"),"FINAL EXAM AFTER FAILED FINAL PT (500.1.H)",IF(AND($K12=2,ISNUMBER($L12),COUNTIFS(nrES_PID,$D12,nrES_Code,$F12,nrES_Att,1)>0,SUMIFS(nrES_Raw,nrES_PID,$D12,nrES_Code,$F12,nrES_Att,1)>=$J12),"RETEST AFTER A PASSING FIRST ATTEMPT","OK"))))))))))
B13: =IF($C13="","",$D13&"-"&$F13&"-"&$K13) | D13: =IF($C13="","",IFERROR(INDEX(rngCadetPIDs,MATCH($C13,rngCadetNames,0)),"?")) | E13: =IF($D13="","",IFERROR(INDEX(nrCadetAgency,MATCH($D13,rngCadetPIDs,0)),"")) | G13: =IF($F13="","",IFERROR(INDEX(rngEPname,MATCH($F13,rngEPcode,0)),"?")) | H13: =IF($F13="","",IFERROR(INDEX(rngEPtype,MATCH($F13,rngEPcode,0)),"?")) | I13: =IF($F13="","",IFERROR(INDEX(rngEPseq,MATCH($F13,rngEPcode,0)),"")) | J13: =IF($F13="","",IFERROR(INDEX(rngEPpass,MATCH($F13,rngEPcode,0)),cfgPassingScore)) | M13: =IF($C13="","",IF($L13="","",IF(NOT(ISNUMBER($L13)),$L13,IF(N($K13)>2,"",IF($K13=1,IF(COUNTIFS(nrES_PID,$D13,nrES_Code,$F13,nrES_Att,2,nrES_Raw,">=0")>0,"",$L13),IF($L13>=$J13,MAX($J13,cfgRetakeRecordedCap),IF(COUNTIFS(nrES_PID,$D13,nrES_Code,$F13,nrES_Att,1)=0,$L13,SUMIFS(nrES_Raw,nrES_PID,$D13,nrES_Code,$F13,nrES_Att,1)))))))) | N13: =IF($C13="","",IF($L13="","",IF(NOT(ISNUMBER($L13)),"(not a score)",IF($L13>=$J13,"Yes","No")))) | O13: =IF($C13="","",IF($M13="","",IF(NOT(ISNUMBER($M13)),"(not a score)",IF($M13>=$J13,"Yes","No")))) | P13: =IF($C13="","",IF($K13="","",IF(N($K13)>2,"No",IF(COUNTIFS(nrES_PID,$D13,nrES_Code,$F13,nrES_Att,">"&$K13,nrES_Att,"<=2",nrES_Raw,">=0")=0,"Yes","No")))) | Q13: =IF($C13="","",IF($L13="","",IF(AND($K13=1,ISNUMBER($L13),$L13<$J13,COUNTIFS(nrES_PID,$D13,nrES_Code,$F13,nrES_Att,2,nrES_Raw,">=0")=0),"Yes","No"))) | R13: =IF($C13="","",IF($L13="","",IF(AND(N($K13)>=2,ISNUMBER($L13),$L13<$J13),"Yes","No"))) | T13: =IF(OR($C13="",$L13="",$K13<>1,NOT(ISNUMBER($L13)),$L13>=$J13),"",IF($S13="","(enter date)",_xlfn.LET(_xlpm.dn,_xlfn.XLOOKUP($S13,nrCDdate,nrCDnum,"",1),IF(_xlpm.dn="","(after last class day)",_xlfn.LET(_xlpm.dd,_xlfn.XLOOKUP(_xlpm.dn+cfgRetestClassDays,nrCDnum,nrCDdate,""),_xlpm.ok,_xlfn.XLOOKUP(_xlpm.dn+cfgRetestClassDays,nrCDnum,nrCDinsession,"No"),IF(OR(_xlpm.dd="",_xlpm.ok<>"Yes"),"(after last class day)",_xlpm.dd)))))) | U13: =IF($C13="","",IF(AND($Y13="Excused",$L13="",N($K13)<=1),"EXCUSED - 1st attempt pending",IF(OR($L13="",$K13<>1,NOT(ISNUMBER($L13)),$L13>=$J13),"",IF(COUNTIFS(nrES_PID,$D13,nrES_Code,$F13,nrES_Att,2,nrES_Raw,">=0")>0,IF(IFERROR(_xlfn.MINIFS(nrES_Date,nrES_PID,$D13,nrES_Code,$F13,nrES_Att,2,nrES_Raw,">=0",nrES_Date,">0"),0)=0,"RETEST UNDATED",IF(NOT(ISNUMBER($T13)),"RETEST DATE UNCHECKED",IF(_xlfn.MINIFS(nrES_Date,nrES_PID,$D13,nrES_Code,$F13,nrES_Att,2,nrES_Raw,">=0",nrES_Date,">0")>$T13,"LATE RETEST "&TEXT(_xlfn.MINIFS(nrES_Date,nrES_PID,$D13,nrES_Code,$F13,nrES_Att,2,nrES_Raw,">=0",nrES_Date,">0"),"mm/dd")&" (due "&TEXT($T13,"mm/dd")&")","Retested"))),IF(NOT(ISNUMBER($T13)),"CHECK DATE",IF(TODAY()>$T13,"OVERDUE","Due "&TEXT($T13,"mm/dd"))))))) | X13: =IF($C13="","",IF(AND($L13<>"",NOT(ISNUMBER($L13))),"RAW SCORE NOT A NUMBER",IF(AND(ISNUMBER($L13),OR($L13<0,$L13>100)),"RAW SCORE OUT OF RANGE",IF(AND($Y13="Unexcused",OR($L13="",NOT(ISNUMBER($L13)),$L13<>0)),"UNEXCUSED ABSENCE MUST RECORD 0",IF(COUNTIF(nrES_RecID,$B13)>1,"DUPLICATE RECORD",IF(N($K13)>2,"ATTEMPT 3+ NOT ALLOWED - policy 300.5 permits one retest per exam; this row records nothing",IF(AND($K13=2,COUNTIFS(nrES_PID,$D13,nrES_Code,$F13,nrES_Att,1)=0),"ATTEMPT 2 WITHOUT ATTEMPT 1",IF(AND($K13=2,$L13=""),"RETEST ROW HAS NO SCORE",IF(AND($H13="Final",$L13<>"",IFERROR(INDEX(nrCKfinalExamElig,MATCH($D13,rngCadetPIDs,0)),"")="No"),"FINAL EXAM AFTER FAILED FINAL PT (500.1.H)",IF(AND($K13=2,ISNUMBER($L13),COUNTIFS(nrES_PID,$D13,nrES_Code,$F13,nrES_Att,1)>0,SUMIFS(nrES_Raw,nrES_PID,$D13,nrES_Code,$F13,nrES_Att,1)>=$J13),"RETEST AFTER A PASSING FIRST ATTEMPT","OK"))))))))))
B14: =IF($C14="","",$D14&"-"&$F14&"-"&$K14) | D14: =IF($C14="","",IFERROR(INDEX(rngCadetPIDs,MATCH($C14,rngCadetNames,0)),"?")) | E14: =IF($D14="","",IFERROR(INDEX(nrCadetAgency,MATCH($D14,rngCadetPIDs,0)),"")) | G14: =IF($F14="","",IFERROR(INDEX(rngEPname,MATCH($F14,rngEPcode,0)),"?")) | H14: =IF($F14="","",IFERROR(INDEX(rngEPtype,MATCH($F14,rngEPcode,0)),"?")) | I14: =IF($F14="","",IFERROR(INDEX(rngEPseq,MATCH($F14,rngEPcode,0)),"")) | J14: =IF($F14="","",IFERROR(INDEX(rngEPpass,MATCH($F14,rngEPcode,0)),cfgPassingScore)) | M14: =IF($C14="","",IF($L14="","",IF(NOT(ISNUMBER($L14)),$L14,IF(N($K14)>2,"",IF($K14=1,IF(COUNTIFS(nrES_PID,$D14,nrES_Code,$F14,nrES_Att,2,nrES_Raw,">=0")>0,"",$L14),IF($L14>=$J14,MAX($J14,cfgRetakeRecordedCap),IF(COUNTIFS(nrES_PID,$D14,nrES_Code,$F14,nrES_Att,1)=0,$L14,SUMIFS(nrES_Raw,nrES_PID,$D14,nrES_Code,$F14,nrES_Att,1)))))))) | N14: =IF($C14="","",IF($L14="","",IF(NOT(ISNUMBER($L14)),"(not a score)",IF($L14>=$J14,"Yes","No")))) | O14: =IF($C14="","",IF($M14="","",IF(NOT(ISNUMBER($M14)),"(not a score)",IF($M14>=$J14,"Yes","No")))) | P14: =IF($C14="","",IF($K14="","",IF(N($K14)>2,"No",IF(COUNTIFS(nrES_PID,$D14,nrES_Code,$F14,nrES_Att,">"&$K14,nrES_Att,"<=2",nrES_Raw,">=0")=0,"Yes","No")))) | Q14: =IF($C14="","",IF($L14="","",IF(AND($K14=1,ISNUMBER($L14),$L14<$J14,COUNTIFS(nrES_PID,$D14,nrES_Code,$F14,nrES_Att,2,nrES_Raw,">=0")=0),"Yes","No"))) | R14: =IF($C14="","",IF($L14="","",IF(AND(N($K14)>=2,ISNUMBER($L14),$L14<$J14),"Yes","No"))) | T14: =IF(OR($C14="",$L14="",$K14<>1,NOT(ISNUMBER($L14)),$L14>=$J14),"",IF($S14="","(enter date)",_xlfn.LET(_xlpm.dn,_xlfn.XLOOKUP($S14,nrCDdate,nrCDnum,"",1),IF(_xlpm.dn="","(after last class day)",_xlfn.LET(_xlpm.dd,_xlfn.XLOOKUP(_xlpm.dn+cfgRetestClassDays,nrCDnum,nrCDdate,""),_xlpm.ok,_xlfn.XLOOKUP(_xlpm.dn+cfgRetestClassDays,nrCDnum,nrCDinsession,"No"),IF(OR(_xlpm.dd="",_xlpm.ok<>"Yes"),"(after last class day)",_xlpm.dd)))))) | U14: =IF($C14="","",IF(AND($Y14="Excused",$L14="",N($K14)<=1),"EXCUSED - 1st attempt pending",IF(OR($L14="",$K14<>1,NOT(ISNUMBER($L14)),$L14>=$J14),"",IF(COUNTIFS(nrES_PID,$D14,nrES_Code,$F14,nrES_Att,2,nrES_Raw,">=0")>0,IF(IFERROR(_xlfn.MINIFS(nrES_Date,nrES_PID,$D14,nrES_Code,$F14,nrES_Att,2,nrES_Raw,">=0",nrES_Date,">0"),0)=0,"RETEST UNDATED",IF(NOT(ISNUMBER($T14)),"RETEST DATE UNCHECKED",IF(_xlfn.MINIFS(nrES_Date,nrES_PID,$D14,nrES_Code,$F14,nrES_Att,2,nrES_Raw,">=0",nrES_Date,">0")>$T14,"LATE RETEST "&TEXT(_xlfn.MINIFS(nrES_Date,nrES_PID,$D14,nrES_Code,$F14,nrES_Att,2,nrES_Raw,">=0",nrES_Date,">0"),"mm/dd")&" (due "&TEXT($T14,"mm/dd")&")","Retested"))),IF(NOT(ISNUMBER($T14)),"CHECK DATE",IF(TODAY()>$T14,"OVERDUE","Due "&TEXT($T14,"mm/dd"))))))) | X14: =IF($C14="","",IF(AND($L14<>"",NOT(ISNUMBER($L14))),"RAW SCORE NOT A NUMBER",IF(AND(ISNUMBER($L14),OR($L14<0,$L14>100)),"RAW SCORE OUT OF RANGE",IF(AND($Y14="Unexcused",OR($L14="",NOT(ISNUMBER($L14)),$L14<>0)),"UNEXCUSED ABSENCE MUST RECORD 0",IF(COUNTIF(nrES_RecID,$B14)>1,"DUPLICATE RECORD",IF(N($K14)>2,"ATTEMPT 3+ NOT ALLOWED - policy 300.5 permits one retest per exam; this row records nothing",IF(AND($K14=2,COUNTIFS(nrES_PID,$D14,nrES_Code,$F14,nrES_Att,1)=0),"ATTEMPT 2 WITHOUT ATTEMPT 1",IF(AND($K14=2,$L14=""),"RETEST ROW HAS NO SCORE",IF(AND($H14="Final",$L14<>"",IFERROR(INDEX(nrCKfinalExamElig,MATCH($D14,rngCadetPIDs,0)),"")="No"),"FINAL EXAM AFTER FAILED FINAL PT (500.1.H)",IF(AND($K14=2,ISNUMBER($L14),COUNTIFS(nrES_PID,$D14,nrES_Code,$F14,nrES_Att,1)>0,SUMIFS(nrES_Raw,nrES_PID,$D14,nrES_Code,$F14,nrES_Att,1)>=$J14),"RETEST AFTER A PASSING FIRST ATTEMPT","OK"))))))))))
B15: =IF($C15="","",$D15&"-"&$F15&"-"&$K15) | D15: =IF($C15="","",IFERROR(INDEX(rngCadetPIDs,MATCH($C15,rngCadetNames,0)),"?")) | E15: =IF($D15="","",IFERROR(INDEX(nrCadetAgency,MATCH($D15,rngCadetPIDs,0)),"")) | G15: =IF($F15="","",IFERROR(INDEX(rngEPname,MATCH($F15,rngEPcode,0)),"?")) | H15: =IF($F15="","",IFERROR(INDEX(rngEPtype,MATCH($F15,rngEPcode,0)),"?")) | I15: =IF($F15="","",IFERROR(INDEX(rngEPseq,MATCH($F15,rngEPcode,0)),"")) | J15: =IF($F15="","",IFERROR(INDEX(rngEPpass,MATCH($F15,rngEPcode,0)),cfgPassingScore)) | M15: =IF($C15="","",IF($L15="","",IF(NOT(ISNUMBER($L15)),$L15,IF(N($K15)>2,"",IF($K15=1,IF(COUNTIFS(nrES_PID,$D15,nrES_Code,$F15,nrES_Att,2,nrES_Raw,">=0")>0,"",$L15),IF($L15>=$J15,MAX($J15,cfgRetakeRecordedCap),IF(COUNTIFS(nrES_PID,$D15,nrES_Code,$F15,nrES_Att,1)=0,$L15,SUMIFS(nrES_Raw,nrES_PID,$D15,nrES_Code,$F15,nrES_Att,1)))))))) | N15: =IF($C15="","",IF($L15="","",IF(NOT(ISNUMBER($L15)),"(not a score)",IF($L15>=$J15,"Yes","No")))) | O15: =IF($C15="","",IF($M15="","",IF(NOT(ISNUMBER($M15)),"(not a score)",IF($M15>=$J15,"Yes","No")))) | P15: =IF($C15="","",IF($K15="","",IF(N($K15)>2,"No",IF(COUNTIFS(nrES_PID,$D15,nrES_Code,$F15,nrES_Att,">"&$K15,nrES_Att,"<=2",nrES_Raw,">=0")=0,"Yes","No")))) | Q15: =IF($C15="","",IF($L15="","",IF(AND($K15=1,ISNUMBER($L15),$L15<$J15,COUNTIFS(nrES_PID,$D15,nrES_Code,$F15,nrES_Att,2,nrES_Raw,">=0")=0),"Yes","No"))) | R15: =IF($C15="","",IF($L15="","",IF(AND(N($K15)>=2,ISNUMBER($L15),$L15<$J15),"Yes","No"))) | T15: =IF(OR($C15="",$L15="",$K15<>1,NOT(ISNUMBER($L15)),$L15>=$J15),"",IF($S15="","(enter date)",_xlfn.LET(_xlpm.dn,_xlfn.XLOOKUP($S15,nrCDdate,nrCDnum,"",1),IF(_xlpm.dn="","(after last class day)",_xlfn.LET(_xlpm.dd,_xlfn.XLOOKUP(_xlpm.dn+cfgRetestClassDays,nrCDnum,nrCDdate,""),_xlpm.ok,_xlfn.XLOOKUP(_xlpm.dn+cfgRetestClassDays,nrCDnum,nrCDinsession,"No"),IF(OR(_xlpm.dd="",_xlpm.ok<>"Yes"),"(after last class day)",_xlpm.dd)))))) | U15: =IF($C15="","",IF(AND($Y15="Excused",$L15="",N($K15)<=1),"EXCUSED - 1st attempt pending",IF(OR($L15="",$K15<>1,NOT(ISNUMBER($L15)),$L15>=$J15),"",IF(COUNTIFS(nrES_PID,$D15,nrES_Code,$F15,nrES_Att,2,nrES_Raw,">=0")>0,IF(IFERROR(_xlfn.MINIFS(nrES_Date,nrES_PID,$D15,nrES_Code,$F15,nrES_Att,2,nrES_Raw,">=0",nrES_Date,">0"),0)=0,"RETEST UNDATED",IF(NOT(ISNUMBER($T15)),"RETEST DATE UNCHECKED",IF(_xlfn.MINIFS(nrES_Date,nrES_PID,$D15,nrES_Code,$F15,nrES_Att,2,nrES_Raw,">=0",nrES_Date,">0")>$T15,"LATE RETEST "&TEXT(_xlfn.MINIFS(nrES_Date,nrES_PID,$D15,nrES_Code,$F15,nrES_Att,2,nrES_Raw,">=0",nrES_Date,">0"),"mm/dd")&" (due "&TEXT($T15,"mm/dd")&")","Retested"))),IF(NOT(ISNUMBER($T15)),"CHECK DATE",IF(TODAY()>$T15,"OVERDUE","Due "&TEXT($T15,"mm/dd"))))))) | X15: =IF($C15="","",IF(AND($L15<>"",NOT(ISNUMBER($L15))),"RAW SCORE NOT A NUMBER",IF(AND(ISNUMBER($L15),OR($L15<0,$L15>100)),"RAW SCORE OUT OF RANGE",IF(AND($Y15="Unexcused",OR($L15="",NOT(ISNUMBER($L15)),$L15<>0)),"UNEXCUSED ABSENCE MUST RECORD 0",IF(COUNTIF(nrES_RecID,$B15)>1,"DUPLICATE RECORD",IF(N($K15)>2,"ATTEMPT 3+ NOT ALLOWED - policy 300.5 permits one retest per exam; this row records nothing",IF(AND($K15=2,COUNTIFS(nrES_PID,$D15,nrES_Code,$F15,nrES_Att,1)=0),"ATTEMPT 2 WITHOUT ATTEMPT 1",IF(AND($K15=2,$L15=""),"RETEST ROW HAS NO SCORE",IF(AND($H15="Final",$L15<>"",IFERROR(INDEX(nrCKfinalExamElig,MATCH($D15,rngCadetPIDs,0)),"")="No"),"FINAL EXAM AFTER FAILED FINAL PT (500.1.H)",IF(AND($K15=2,ISNUMBER($L15),COUNTIFS(nrES_PID,$D15,nrES_Code,$F15,nrES_Att,1)>0,SUMIFS(nrES_Raw,nrES_PID,$D15,nrES_Code,$F15,nrES_Att,1)>=$J15),"RETEST AFTER A PASSING FIRST ATTEMPT","OK"))))))))))
B16: =IF($C16="","",$D16&"-"&$F16&"-"&$K16) | D16: =IF($C16="","",IFERROR(INDEX(rngCadetPIDs,MATCH($C16,rngCadetNames,0)),"?")) | E16: =IF($D16="","",IFERROR(INDEX(nrCadetAgency,MATCH($D16,rngCadetPIDs,0)),"")) | G16: =IF($F16="","",IFERROR(INDEX(rngEPname,MATCH($F16,rngEPcode,0)),"?")) | H16: =IF($F16="","",IFERROR(INDEX(rngEPtype,MATCH($F16,rngEPcode,0)),"?")) | I16: =IF($F16="","",IFERROR(INDEX(rngEPseq,MATCH($F16,rngEPcode,0)),"")) | J16: =IF($F16="","",IFERROR(INDEX(rngEPpass,MATCH($F16,rngEPcode,0)),cfgPassingScore)) | M16: =IF($C16="","",IF($L16="","",IF(NOT(ISNUMBER($L16)),$L16,IF(N($K16)>2,"",IF($K16=1,IF(COUNTIFS(nrES_PID,$D16,nrES_Code,$F16,nrES_Att,2,nrES_Raw,">=0")>0,"",$L16),IF($L16>=$J16,MAX($J16,cfgRetakeRecordedCap),IF(COUNTIFS(nrES_PID,$D16,nrES_Code,$F16,nrES_Att,1)=0,$L16,SUMIFS(nrES_Raw,nrES_PID,$D16,nrES_Code,$F16,nrES_Att,1)))))))) | N16: =IF($C16="","",IF($L16="","",IF(NOT(ISNUMBER($L16)),"(not a score)",IF($L16>=$J16,"Yes","No")))) | O16: =IF($C16="","",IF($M16="","",IF(NOT(ISNUMBER($M16)),"(not a score)",IF($M16>=$J16,"Yes","No")))) | P16: =IF($C16="","",IF($K16="","",IF(N($K16)>2,"No",IF(COUNTIFS(nrES_PID,$D16,nrES_Code,$F16,nrES_Att,">"&$K16,nrES_Att,"<=2",nrES_Raw,">=0")=0,"Yes","No")))) | Q16: =IF($C16="","",IF($L16="","",IF(AND($K16=1,ISNUMBER($L16),$L16<$J16,COUNTIFS(nrES_PID,$D16,nrES_Code,$F16,nrES_Att,2,nrES_Raw,">=0")=0),"Yes","No"))) | R16: =IF($C16="","",IF($L16="","",IF(AND(N($K16)>=2,ISNUMBER($L16),$L16<$J16),"Yes","No"))) | T16: =IF(OR($C16="",$L16="",$K16<>1,NOT(ISNUMBER($L16)),$L16>=$J16),"",IF($S16="","(enter date)",_xlfn.LET(_xlpm.dn,_xlfn.XLOOKUP($S16,nrCDdate,nrCDnum,"",1),IF(_xlpm.dn="","(after last class day)",_xlfn.LET(_xlpm.dd,_xlfn.XLOOKUP(_xlpm.dn+cfgRetestClassDays,nrCDnum,nrCDdate,""),_xlpm.ok,_xlfn.XLOOKUP(_xlpm.dn+cfgRetestClassDays,nrCDnum,nrCDinsession,"No"),IF(OR(_xlpm.dd="",_xlpm.ok<>"Yes"),"(after last class day)",_xlpm.dd)))))) | U16: =IF($C16="","",IF(AND($Y16="Excused",$L16="",N($K16)<=1),"EXCUSED - 1st attempt pending",IF(OR($L16="",$K16<>1,NOT(ISNUMBER($L16)),$L16>=$J16),"",IF(COUNTIFS(nrES_PID,$D16,nrES_Code,$F16,nrES_Att,2,nrES_Raw,">=0")>0,IF(IFERROR(_xlfn.MINIFS(nrES_Date,nrES_PID,$D16,nrES_Code,$F16,nrES_Att,2,nrES_Raw,">=0",nrES_Date,">0"),0)=0,"RETEST UNDATED",IF(NOT(ISNUMBER($T16)),"RETEST DATE UNCHECKED",IF(_xlfn.MINIFS(nrES_Date,nrES_PID,$D16,nrES_Code,$F16,nrES_Att,2,nrES_Raw,">=0",nrES_Date,">0")>$T16,"LATE RETEST "&TEXT(_xlfn.MINIFS(nrES_Date,nrES_PID,$D16,nrES_Code,$F16,nrES_Att,2,nrES_Raw,">=0",nrES_Date,">0"),"mm/dd")&" (due "&TEXT($T16,"mm/dd")&")","Retested"))),IF(NOT(ISNUMBER($T16)),"CHECK DATE",IF(TODAY()>$T16,"OVERDUE","Due "&TEXT($T16,"mm/dd"))))))) | X16: =IF($C16="","",IF(AND($L16<>"",NOT(ISNUMBER($L16))),"RAW SCORE NOT A NUMBER",IF(AND(ISNUMBER($L16),OR($L16<0,$L16>100)),"RAW SCORE OUT OF RANGE",IF(AND($Y16="Unexcused",OR($L16="",NOT(ISNUMBER($L16)),$L16<>0)),"UNEXCUSED ABSENCE MUST RECORD 0",IF(COUNTIF(nrES_RecID,$B16)>1,"DUPLICATE RECORD",IF(N($K16)>2,"ATTEMPT 3+ NOT ALLOWED - policy 300.5 permits one retest per exam; this row records nothing",IF(AND($K16=2,COUNTIFS(nrES_PID,$D16,nrES_Code,$F16,nrES_Att,1)=0),"ATTEMPT 2 WITHOUT ATTEMPT 1",IF(AND($K16=2,$L16=""),"RETEST ROW HAS NO SCORE",IF(AND($H16="Final",$L16<>"",IFERROR(INDEX(nrCKfinalExamElig,MATCH($D16,rngCadetPIDs,0)),"")="No"),"FINAL EXAM AFTER FAILED FINAL PT (500.1.H)",IF(AND($K16=2,ISNUMBER($L16),COUNTIFS(nrES_PID,$D16,nrES_Code,$F16,nrES_Att,1)>0,SUMIFS(nrES_Raw,nrES_PID,$D16,nrES_Code,$F16,nrES_Att,1)>=$J16),"RETEST AFTER A PASSING FIRST ATTEMPT","OK"))))))))))
B17: =IF($C17="","",$D17&"-"&$F17&"-"&$K17) | D17: =IF($C17="","",IFERROR(INDEX(rngCadetPIDs,MATCH($C17,rngCadetNames,0)),"?")) | E17: =IF($D17="","",IFERROR(INDEX(nrCadetAgency,MATCH($D17,rngCadetPIDs,0)),"")) | G17: =IF($F17="","",IFERROR(INDEX(rngEPname,MATCH($F17,rngEPcode,0)),"?")) | H17: =IF($F17="","",IFERROR(INDEX(rngEPtype,MATCH($F17,rngEPcode,0)),"?")) | I17: =IF($F17="","",IFERROR(INDEX(rngEPseq,MATCH($F17,rngEPcode,0)),"")) | J17: =IF($F17="","",IFERROR(INDEX(rngEPpass,MATCH($F17,rngEPcode,0)),cfgPassingScore)) | M17: =IF($C17="","",IF($L17="","",IF(NOT(ISNUMBER($L17)),$L17,IF(N($K17)>2,"",IF($K17=1,IF(COUNTIFS(nrES_PID,$D17,nrES_Code,$F17,nrES_Att,2,nrES_Raw,">=0")>0,"",$L17),IF($L17>=$J17,MAX($J17,cfgRetakeRecordedCap),IF(COUNTIFS(nrES_PID,$D17,nrES_Code,$F17,nrES_Att,1)=0,$L17,SUMIFS(nrES_Raw,nrES_PID,$D17,nrES_Code,$F17,nrES_Att,1)))))))) | N17: =IF($C17="","",IF($L17="","",IF(NOT(ISNUMBER($L17)),"(not a score)",IF($L17>=$J17,"Yes","No")))) | O17: =IF($C17="","",IF($M17="","",IF(NOT(ISNUMBER($M17)),"(not a score)",IF($M17>=$J17,"Yes","No")))) | P17: =IF($C17="","",IF($K17="","",IF(N($K17)>2,"No",IF(COUNTIFS(nrES_PID,$D17,nrES_Code,$F17,nrES_Att,">"&$K17,nrES_Att,"<=2",nrES_Raw,">=0")=0,"Yes","No")))) | Q17: =IF($C17="","",IF($L17="","",IF(AND($K17=1,ISNUMBER($L17),$L17<$J17,COUNTIFS(nrES_PID,$D17,nrES_Code,$F17,nrES_Att,2,nrES_Raw,">=0")=0),"Yes","No"))) | R17: =IF($C17="","",IF($L17="","",IF(AND(N($K17)>=2,ISNUMBER($L17),$L17<$J17),"Yes","No"))) | T17: =IF(OR($C17="",$L17="",$K17<>1,NOT(ISNUMBER($L17)),$L17>=$J17),"",IF($S17="","(enter date)",_xlfn.LET(_xlpm.dn,_xlfn.XLOOKUP($S17,nrCDdate,nrCDnum,"",1),IF(_xlpm.dn="","(after last class day)",_xlfn.LET(_xlpm.dd,_xlfn.XLOOKUP(_xlpm.dn+cfgRetestClassDays,nrCDnum,nrCDdate,""),_xlpm.ok,_xlfn.XLOOKUP(_xlpm.dn+cfgRetestClassDays,nrCDnum,nrCDinsession,"No"),IF(OR(_xlpm.dd="",_xlpm.ok<>"Yes"),"(after last class day)",_xlpm.dd)))))) | U17: =IF($C17="","",IF(AND($Y17="Excused",$L17="",N($K17)<=1),"EXCUSED - 1st attempt pending",IF(OR($L17="",$K17<>1,NOT(ISNUMBER($L17)),$L17>=$J17),"",IF(COUNTIFS(nrES_PID,$D17,nrES_Code,$F17,nrES_Att,2,nrES_Raw,">=0")>0,IF(IFERROR(_xlfn.MINIFS(nrES_Date,nrES_PID,$D17,nrES_Code,$F17,nrES_Att,2,nrES_Raw,">=0",nrES_Date,">0"),0)=0,"RETEST UNDATED",IF(NOT(ISNUMBER($T17)),"RETEST DATE UNCHECKED",IF(_xlfn.MINIFS(nrES_Date,nrES_PID,$D17,nrES_Code,$F17,nrES_Att,2,nrES_Raw,">=0",nrES_Date,">0")>$T17,"LATE RETEST "&TEXT(_xlfn.MINIFS(nrES_Date,nrES_PID,$D17,nrES_Code,$F17,nrES_Att,2,nrES_Raw,">=0",nrES_Date,">0"),"mm/dd")&" (due "&TEXT($T17,"mm/dd")&")","Retested"))),IF(NOT(ISNUMBER($T17)),"CHECK DATE",IF(TODAY()>$T17,"OVERDUE","Due "&TEXT($T17,"mm/dd"))))))) | X17: =IF($C17="","",IF(AND($L17<>"",NOT(ISNUMBER($L17))),"RAW SCORE NOT A NUMBER",IF(AND(ISNUMBER($L17),OR($L17<0,$L17>100)),"RAW SCORE OUT OF RANGE",IF(AND($Y17="Unexcused",OR($L17="",NOT(ISNUMBER($L17)),$L17<>0)),"UNEXCUSED ABSENCE MUST RECORD 0",IF(COUNTIF(nrES_RecID,$B17)>1,"DUPLICATE RECORD",IF(N($K17)>2,"ATTEMPT 3+ NOT ALLOWED - policy 300.5 permits one retest per exam; this row records nothing",IF(AND($K17=2,COUNTIFS(nrES_PID,$D17,nrES_Code,$F17,nrES_Att,1)=0),"ATTEMPT 2 WITHOUT ATTEMPT 1",IF(AND($K17=2,$L17=""),"RETEST ROW HAS NO SCORE",IF(AND($H17="Final",$L17<>"",IFERROR(INDEX(nrCKfinalExamElig,MATCH($D17,rngCadetPIDs,0)),"")="No"),"FINAL EXAM AFTER FAILED FINAL PT (500.1.H)",IF(AND($K17=2,ISNUMBER($L17),COUNTIFS(nrES_PID,$D17,nrES_Code,$F17,nrES_Att,1)>0,SUMIFS(nrES_Raw,nrES_PID,$D17,nrES_Code,$F17,nrES_Att,1)>=$J17),"RETEST AFTER A PASSING FIRST ATTEMPT","OK"))))))))))
... B1505: =IF($C1505="","",$D1505&"-"&$F1505&"-"&$K1505) | D1505: =IF($C1505="","",IFERROR(INDEX(rngCadetPIDs,MATCH($C1505,rngCadetNames,0)),"?")) | E1505: =IF($D1505="","",IFERROR(INDEX(nrCadetAgency,MATCH($D1505,rngCadetPIDs,0)),"")) | G1505: =IF($F1505="","",IFERROR(INDEX(rngEPname,MATCH($F1505,rngEPcode,0)),"?")) | H1505: =IF($F1505="","",IFERROR(INDEX(rngEPtype,MATCH($F1505,rngEPcode,0)),"?")) | I1505: =IF($F1505="","",IFERROR(INDEX(rngEPseq,MATCH($F1505,rngEPcode,0)),"")) | J1505: =IF($F1505="","",IFERROR(INDEX(rngEPpass,MATCH($F1505,rngEPcode,0)),cfgPassingScore)) | M1505: =IF($C1505="","",IF($L1505="","",IF(NOT(ISNUMBER($L1505)),$L1505,IF(N($K1505)>2,"",IF($K1505=1,IF(COUNTIFS(nrES_PID,$D1505,nrES_Code,$F1505,nrES_Att,2,nrES_Raw,">=0")>0,"",$L1505),IF($L1505>=$J1505,MAX($J1505,cfgRetakeRecordedCap),IF(COUNTIFS(nrES_PID,$D1505,nrES_Code,$F1505,nrES_Att,1)=0,$L1505,SUMIFS(nrES_Raw,nrES_PID,$D1505,nrES_Code,$F1505,nrES_Att,1)))))))) | N1505: =IF($C1505="","",IF($L1505="","",IF(NOT(ISNUMBER($L1505)),"(not a score)",IF($L1505>=$J1505,"Yes","No")))) | O1505: =IF($C1505="","",IF($M1505="","",IF(NOT(ISNUMBER($M1505)),"(not a score)",IF($M1505>=$J1505,"Yes","No")))) | P1505: =IF($C1505="","",IF($K1505="","",IF(N($K1505)>2,"No",IF(COUNTIFS(nrES_PID,$D1505,nrES_Code,$F1505,nrES_Att,">"&$K1505,nrES_Att,"<=2",nrES_Raw,">=0")=0,"Yes","No")))) | Q1505: =IF($C1505="","",IF($L1505="","",IF(AND($K1505=1,ISNUMBER($L1505),$L1505<$J1505,COUNTIFS(nrES_PID,$D1505,nrES_Code,$F1505,nrES_Att,2,nrES_Raw,">=0")=0),"Yes","No"))) | R1505: =IF($C1505="","",IF($L1505="","",IF(AND(N($K1505)>=2,ISNUMBER($L1505),$L1505<$J1505),"Yes","No"))) | T1505: =IF(OR($C1505="",$L1505="",$K1505<>1,NOT(ISNUMBER($L1505)),$L1505>=$J1505),"",IF($S1505="","(enter date)",_xlfn.LET(_xlpm.dn,_xlfn.XLOOKUP($S1505,nrCDdate,nrCDnum,"",1),IF(_xlpm.dn="","(after last class day)",_xlfn.LET(_xlpm.dd,_xlfn.XLOOKUP(_xlpm.dn+cfgRetestClassDays,nrCDnum,nrCDdate,""),_xlpm.ok,_xlfn.XLOOKUP(_xlpm.dn+cfgRetestClassDays,nrCDnum,nrCDinsession,"No"),IF(OR(_xlpm.dd="",_xlpm.ok<>"Yes"),"(after last class day)",_xlpm.dd)))))) | U1505: =IF($C1505="","",IF(AND($Y1505="Excused",$L1505="",N($K1505)<=1),"EXCUSED - 1st attempt pending",IF(OR($L1505="",$K1505<>1,NOT(ISNUMBER($L1505)),$L1505>=$J1505),"",IF(COUNTIFS(nrES_PID,$D1505,nrES_Code,$F1505,nrES_Att,2,nrES_Raw,">=0")>0,IF(IFERROR(_xlfn.MINIFS(nrES_Date,nrES_PID,$D1505,nrES_Code,$F1505,nrES_Att,2,nrES_Raw,">=0",nrES_Date,">0"),0)=0,"RETEST UNDATED",IF(NOT(ISNUMBER($T1505)),"RETEST DATE UNCHECKED",IF(_xlfn.MINIFS(nrES_Date,nrES_PID,$D1505,nrES_Code,$F1505,nrES_Att,2,nrES_Raw,">=0",nrES_Date,">0")>$T1505,"LATE RETEST "&TEXT(_xlfn.MINIFS(nrES_Date,nrES_PID,$D1505,nrES_Code,$F1505,nrES_Att,2,nrES_Raw,">=0",nrES_Date,">0"),"mm/dd")&" (due "&TEXT($T1505,"mm/dd")&")","Retested"))),IF(NOT(ISNUMBER($T1505)),"CHECK DATE",IF(TODAY()>$T1505,"OVERDUE","Due "&TEXT($T1505,"mm/dd"))))))) | X1505: =IF($C1505="","",IF(AND($L1505<>"",NOT(ISNUMBER($L1505))),"RAW SCORE NOT A NUMBER",IF(AND(ISNUMBER($L1505),OR($L1505<0,$L1505>100)),"RAW SCORE OUT OF RANGE",IF(AND($Y1505="Unexcused",OR($L1505="",NOT(ISNUMBER($L1505)),$L1505<>0)),"UNEXCUSED ABSENCE MUST RECORD 0",IF(COUNTIF(nrES_RecID,$B1505)>1,"DUPLICATE RECORD",IF(N($K1505)>2,"ATTEMPT 3+ NOT ALLOWED - policy 300.5 permits one retest per exam; this row records nothing",IF(AND($K1505=2,COUNTIFS(nrES_PID,$D1505,nrES_Code,$F1505,nrES_Att,1)=0),"ATTEMPT 2 WITHOUT ATTEMPT 1",IF(AND($K1505=2,$L1505=""),"RETEST ROW HAS NO SCORE",IF(AND($H1505="Final",$L1505<>"",IFERROR(INDEX(nrCKfinalExamElig,MATCH($D1505,rngCadetPIDs,0)),"")="No"),"FINAL EXAM AFTER FAILED FINAL PT (500.1.H)",IF(AND($K1505=2,ISNUMBER($L1505),COUNTIFS(nrES_PID,$D1505,nrES_Code,$F1505,nrES_Att,1)>0,SUMIFS(nrES_Raw,nrES_PID,$D1505,nrES_Code,$F1505,nrES_Att,1)>=$J1505),"RETEST AFTER A PASSING FIRST ATTEMPT","OK"))))))))))

Sheet Spelling
B1: =HYPERLINK("#Dashboard!B5","◄ Dashboard")
B4: Scores 0-100 (25 words x 4 pts). Average below the Settings intervention threshold (default 75) flags INTERVENTION per policy 300.4.B — see Counseling log. Row Check catches a score that is text or outside 0-100: one extra digit hides the intervention flag and moves the class average.
B5: PID | C5: Cadet Name | D5: S01 | E5: S02 | F5: S03 | G5: S04 | H5: S05 | I5: S06 | J5: S07 | K5: S08 | L5: S09 | M5: S10 | N5: S11 | O5: S12 | P5: Spelling Avg | Q5: # Taken | R5: Intervention? | S5: Row Check | T5: Cadet Status
B6: =IF(Cadets!$B6="","",Cadets!$B6) | C6: =IF(Cadets!$B6="","",Cadets!$F6) | P6: =IF($C6="","",IF($Q6=0,"",ROUND(SUMIFS($D6:$O6,$D6:$O6,">=0",$D6:$O6,"<=100")/$Q6,1))) | Q6: =IF($C6="","",COUNTIFS($D6:$O6,">=0",$D6:$O6,"<=100")) | R6: =IF($C6="","",IF($P6="","",IF($P6<cfgSpellInterventionAvg,"INTERVENTION","OK"))) | S6: =IF($C6="","",IF(COUNT($D6:$O6)<>COUNTA($D6:$O6),"SCORE NOT A NUMBER",IF(SUMPRODUCT(($D6:$O6<>"")*((N($D6:$O6)<0)+(N($D6:$O6)>100)))>0,"SCORE OUT OF RANGE","OK"))) | T6: =IF(Cadets!$B6="","",Cadets!$I6)
B7: =IF(Cadets!$B7="","",Cadets!$B7) | C7: =IF(Cadets!$B7="","",Cadets!$F7) | P7: =IF($C7="","",IF($Q7=0,"",ROUND(SUMIFS($D7:$O7,$D7:$O7,">=0",$D7:$O7,"<=100")/$Q7,1))) | Q7: =IF($C7="","",COUNTIFS($D7:$O7,">=0",$D7:$O7,"<=100")) | R7: =IF($C7="","",IF($P7="","",IF($P7<cfgSpellInterventionAvg,"INTERVENTION","OK"))) | S7: =IF($C7="","",IF(COUNT($D7:$O7)<>COUNTA($D7:$O7),"SCORE NOT A NUMBER",IF(SUMPRODUCT(($D7:$O7<>"")*((N($D7:$O7)<0)+(N($D7:$O7)>100)))>0,"SCORE OUT OF RANGE","OK"))) | T7: =IF(Cadets!$B7="","",Cadets!$I7)
B8: =IF(Cadets!$B8="","",Cadets!$B8) | C8: =IF(Cadets!$B8="","",Cadets!$F8) | P8: =IF($C8="","",IF($Q8=0,"",ROUND(SUMIFS($D8:$O8,$D8:$O8,">=0",$D8:$O8,"<=100")/$Q8,1))) | Q8: =IF($C8="","",COUNTIFS($D8:$O8,">=0",$D8:$O8,"<=100")) | R8: =IF($C8="","",IF($P8="","",IF($P8<cfgSpellInterventionAvg,"INTERVENTION","OK"))) | S8: =IF($C8="","",IF(COUNT($D8:$O8)<>COUNTA($D8:$O8),"SCORE NOT A NUMBER",IF(SUMPRODUCT(($D8:$O8<>"")*((N($D8:$O8)<0)+(N($D8:$O8)>100)))>0,"SCORE OUT OF RANGE","OK"))) | T8: =IF(Cadets!$B8="","",Cadets!$I8)
B9: =IF(Cadets!$B9="","",Cadets!$B9) | C9: =IF(Cadets!$B9="","",Cadets!$F9) | P9: =IF($C9="","",IF($Q9=0,"",ROUND(SUMIFS($D9:$O9,$D9:$O9,">=0",$D9:$O9,"<=100")/$Q9,1))) | Q9: =IF($C9="","",COUNTIFS($D9:$O9,">=0",$D9:$O9,"<=100")) | R9: =IF($C9="","",IF($P9="","",IF($P9<cfgSpellInterventionAvg,"INTERVENTION","OK"))) | S9: =IF($C9="","",IF(COUNT($D9:$O9)<>COUNTA($D9:$O9),"SCORE NOT A NUMBER",IF(SUMPRODUCT(($D9:$O9<>"")*((N($D9:$O9)<0)+(N($D9:$O9)>100)))>0,"SCORE OUT OF RANGE","OK"))) | T9: =IF(Cadets!$B9="","",Cadets!$I9)
B10: =IF(Cadets!$B10="","",Cadets!$B10) | C10: =IF(Cadets!$B10="","",Cadets!$F10) | P10: =IF($C10="","",IF($Q10=0,"",ROUND(SUMIFS($D10:$O10,$D10:$O10,">=0",$D10:$O10,"<=100")/$Q10,1))) | Q10: =IF($C10="","",COUNTIFS($D10:$O10,">=0",$D10:$O10,"<=100")) | R10: =IF($C10="","",IF($P10="","",IF($P10<cfgSpellInterventionAvg,"INTERVENTION","OK"))) | S10: =IF($C10="","",IF(COUNT($D10:$O10)<>COUNTA($D10:$O10),"SCORE NOT A NUMBER",IF(SUMPRODUCT(($D10:$O10<>"")*((N($D10:$O10)<0)+(N($D10:$O10)>100)))>0,"SCORE OUT OF RANGE","OK"))) | T10: =IF(Cadets!$B10="","",Cadets!$I10)
B11: =IF(Cadets!$B11="","",Cadets!$B11) | C11: =IF(Cadets!$B11="","",Cadets!$F11) | P11: =IF($C11="","",IF($Q11=0,"",ROUND(SUMIFS($D11:$O11,$D11:$O11,">=0",$D11:$O11,"<=100")/$Q11,1))) | Q11: =IF($C11="","",COUNTIFS($D11:$O11,">=0",$D11:$O11,"<=100")) | R11: =IF($C11="","",IF($P11="","",IF($P11<cfgSpellInterventionAvg,"INTERVENTION","OK"))) | S11: =IF($C11="","",IF(COUNT($D11:$O11)<>COUNTA($D11:$O11),"SCORE NOT A NUMBER",IF(SUMPRODUCT(($D11:$O11<>"")*((N($D11:$O11)<0)+(N($D11:$O11)>100)))>0,"SCORE OUT OF RANGE","OK"))) | T11: =IF(Cadets!$B11="","",Cadets!$I11)
B12: =IF(Cadets!$B12="","",Cadets!$B12) | C12: =IF(Cadets!$B12="","",Cadets!$F12) | P12: =IF($C12="","",IF($Q12=0,"",ROUND(SUMIFS($D12:$O12,$D12:$O12,">=0",$D12:$O12,"<=100")/$Q12,1))) | Q12: =IF($C12="","",COUNTIFS($D12:$O12,">=0",$D12:$O12,"<=100")) | R12: =IF($C12="","",IF($P12="","",IF($P12<cfgSpellInterventionAvg,"INTERVENTION","OK"))) | S12: =IF($C12="","",IF(COUNT($D12:$O12)<>COUNTA($D12:$O12),"SCORE NOT A NUMBER",IF(SUMPRODUCT(($D12:$O12<>"")*((N($D12:$O12)<0)+(N($D12:$O12)>100)))>0,"SCORE OUT OF RANGE","OK"))) | T12: =IF(Cadets!$B12="","",Cadets!$I12)
B13: =IF(Cadets!$B13="","",Cadets!$B13) | C13: =IF(Cadets!$B13="","",Cadets!$F13) | P13: =IF($C13="","",IF($Q13=0,"",ROUND(SUMIFS($D13:$O13,$D13:$O13,">=0",$D13:$O13,"<=100")/$Q13,1))) | Q13: =IF($C13="","",COUNTIFS($D13:$O13,">=0",$D13:$O13,"<=100")) | R13: =IF($C13="","",IF($P13="","",IF($P13<cfgSpellInterventionAvg,"INTERVENTION","OK"))) | S13: =IF($C13="","",IF(COUNT($D13:$O13)<>COUNTA($D13:$O13),"SCORE NOT A NUMBER",IF(SUMPRODUCT(($D13:$O13<>"")*((N($D13:$O13)<0)+(N($D13:$O13)>100)))>0,"SCORE OUT OF RANGE","OK"))) | T13: =IF(Cadets!$B13="","",Cadets!$I13)
B14: =IF(Cadets!$B14="","",Cadets!$B14) | C14: =IF(Cadets!$B14="","",Cadets!$F14) | P14: =IF($C14="","",IF($Q14=0,"",ROUND(SUMIFS($D14:$O14,$D14:$O14,">=0",$D14:$O14,"<=100")/$Q14,1))) | Q14: =IF($C14="","",COUNTIFS($D14:$O14,">=0",$D14:$O14,"<=100")) | R14: =IF($C14="","",IF($P14="","",IF($P14<cfgSpellInterventionAvg,"INTERVENTION","OK"))) | S14: =IF($C14="","",IF(COUNT($D14:$O14)<>COUNTA($D14:$O14),"SCORE NOT A NUMBER",IF(SUMPRODUCT(($D14:$O14<>"")*((N($D14:$O14)<0)+(N($D14:$O14)>100)))>0,"SCORE OUT OF RANGE","OK"))) | T14: =IF(Cadets!$B14="","",Cadets!$I14)
B15: =IF(Cadets!$B15="","",Cadets!$B15) | C15: =IF(Cadets!$B15="","",Cadets!$F15) | P15: =IF($C15="","",IF($Q15=0,"",ROUND(SUMIFS($D15:$O15,$D15:$O15,">=0",$D15:$O15,"<=100")/$Q15,1))) | Q15: =IF($C15="","",COUNTIFS($D15:$O15,">=0",$D15:$O15,"<=100")) | R15: =IF($C15="","",IF($P15="","",IF($P15<cfgSpellInterventionAvg,"INTERVENTION","OK"))) | S15: =IF($C15="","",IF(COUNT($D15:$O15)<>COUNTA($D15:$O15),"SCORE NOT A NUMBER",IF(SUMPRODUCT(($D15:$O15<>"")*((N($D15:$O15)<0)+(N($D15:$O15)>100)))>0,"SCORE OUT OF RANGE","OK"))) | T15: =IF(Cadets!$B15="","",Cadets!$I15)
B16: =IF(Cadets!$B16="","",Cadets!$B16) | C16: =IF(Cadets!$B16="","",Cadets!$F16) | P16: =IF($C16="","",IF($Q16=0,"",ROUND(SUMIFS($D16:$O16,$D16:$O16,">=0",$D16:$O16,"<=100")/$Q16,1))) | Q16: =IF($C16="","",COUNTIFS($D16:$O16,">=0",$D16:$O16,"<=100")) | R16: =IF($C16="","",IF($P16="","",IF($P16<cfgSpellInterventionAvg,"INTERVENTION","OK"))) | S16: =IF($C16="","",IF(COUNT($D16:$O16)<>COUNTA($D16:$O16),"SCORE NOT A NUMBER",IF(SUMPRODUCT(($D16:$O16<>"")*((N($D16:$O16)<0)+(N($D16:$O16)>100)))>0,"SCORE OUT OF RANGE","OK"))) | T16: =IF(Cadets!$B16="","",Cadets!$I16)
B17: =IF(Cadets!$B17="","",Cadets!$B17) | C17: =IF(Cadets!$B17="","",Cadets!$F17) | P17: =IF($C17="","",IF($Q17=0,"",ROUND(SUMIFS($D17:$O17,$D17:$O17,">=0",$D17:$O17,"<=100")/$Q17,1))) | Q17: =IF($C17="","",COUNTIFS($D17:$O17,">=0",$D17:$O17,"<=100")) | R17: =IF($C17="","",IF($P17="","",IF($P17<cfgSpellInterventionAvg,"INTERVENTION","OK"))) | S17: =IF($C17="","",IF(COUNT($D17:$O17)<>COUNTA($D17:$O17),"SCORE NOT A NUMBER",IF(SUMPRODUCT(($D17:$O17<>"")*((N($D17:$O17)<0)+(N($D17:$O17)>100)))>0,"SCORE OUT OF RANGE","OK"))) | T17: =IF(Cadets!$B17="","",Cadets!$I17)
... B55: =IF(Cadets!$B55="","",Cadets!$B55) | C55: =IF(Cadets!$B55="","",Cadets!$F55) | P55: =IF($C55="","",IF($Q55=0,"",ROUND(SUMIFS($D55:$O55,$D55:$O55,">=0",$D55:$O55,"<=100")/$Q55,1))) | Q55: =IF($C55="","",COUNTIFS($D55:$O55,">=0",$D55:$O55,"<=100")) | R55: =IF($C55="","",IF($P55="","",IF($P55<cfgSpellInterventionAvg,"INTERVENTION","OK"))) | S55: =IF($C55="","",IF(COUNT($D55:$O55)<>COUNTA($D55:$O55),"SCORE NOT A NUMBER",IF(SUMPRODUCT(($D55:$O55<>"")*((N($D55:$O55)<0)+(N($D55:$O55)>100)))>0,"SCORE OUT OF RANGE","OK"))) | T55: =IF(Cadets!$B55="","",Cadets!$I55)
C57: Scores entered: | D57: =COUNTIFS(D6:D55,">=0",D6:D55,"<=100") | E57: =COUNTIFS(E6:E55,">=0",E6:E55,"<=100") | F57: =COUNTIFS(F6:F55,">=0",F6:F55,"<=100") | G57: =COUNTIFS(G6:G55,">=0",G6:G55,"<=100") | H57: =COUNTIFS(H6:H55,">=0",H6:H55,"<=100") | I57: =COUNTIFS(I6:I55,">=0",I6:I55,"<=100") | J57: =COUNTIFS(J6:J55,">=0",J6:J55,"<=100") | K57: =COUNTIFS(K6:K55,">=0",K6:K55,"<=100") | ... O57: =COUNTIFS(O6:O55,">=0",O6:O55,"<=100")
C58: Class average: | D58: =IF(D57=0,"",ROUND(AVERAGEIFS(D6:D55,D6:D55,">=0",D6:D55,"<=100"),1)) | E58: =IF(E57=0,"",ROUND(AVERAGEIFS(E6:E55,E6:E55,">=0",E6:E55,"<=100"),1)) | F58: =IF(F57=0,"",ROUND(AVERAGEIFS(F6:F55,F6:F55,">=0",F6:F55,"<=100"),1)) | G58: =IF(G57=0,"",ROUND(AVERAGEIFS(G6:G55,G6:G55,">=0",G6:G55,"<=100"),1)) | H58: =IF(H57=0,"",ROUND(AVERAGEIFS(H6:H55,H6:H55,">=0",H6:H55,"<=100"),1)) | I58: =IF(I57=0,"",ROUND(AVERAGEIFS(I6:I55,I6:I55,">=0",I6:I55,"<=100"),1)) | J58: =IF(J57=0,"",ROUND(AVERAGEIFS(J6:J55,J6:J55,">=0",J6:J55,"<=100"),1)) | K58: =IF(K57=0,"",ROUND(AVERAGEIFS(K6:K55,K6:K55,">=0",K6:K55,"<=100"),1)) | ... O58: =IF(O57=0,"",ROUND(AVERAGEIFS(O6:O55,O6:O55,">=0",O6:O55,"<=100"),1))
C59: Test #: | D59: 1 | E59: 2 | F59: 3 | G59: 4 | H59: 5 | I59: 6 | J59: 7 | K59: 8 | L59: 9 | M59: 10 | N59: 11 | O59: 12

Sheet Attendance
B1: =HYPERLINK("#Dashboard!B5","◄ Dashboard")
B4: Exception log: only missed/modified time gets a row. Minutes count toward the classroom cap; Sessions toward the PT cap. Excused or documented-modified-PT rows don't count (policy 400). Each counting event stays OPEN until Makeup rows linked to its EventID cover the balance — then it shows CLEARED with the makeup date. Watch Row Check (last column): a counted row with no minutes (or no sessions on a PT event) is dropped from BOTH caps, and a row carrying the unit that does not match its own 'Is PT?' flag has that value discarded everywhere — balance, makeup reconciliation and the caps.
B5: EventID | C5: Date | D5: Cadet Name | E5: PID | F5: Agency | G5: Event Type | H5: Reason | I5: Minutes | J5: Sessions | K5: Is PT? | L5: Doc Status | M5: Excused? | N5: Counts? | O5: Notes | P5: Made-Up Min | Q5: Made-Up Sess | R5: Balance | S5: Cleared? | T5: Row Check
B6: =IF($D6="","","A"&TEXT(ROW()-5,"000")) | E6: =IF($D6="","",IFERROR(INDEX(rngCadetPIDs,MATCH($D6,rngCadetNames,0)),"?")) | F6: =IF($E6="","",IFERROR(INDEX(nrCadetAgency,MATCH($E6,rngCadetPIDs,0)),"")) | K6: =IF($G6="","",IF(OR($G6="PT Missed",$G6="PT Modified",$G6="PT Refused"),"Yes","No")) | N6: =IF($D6="","",IF($M6="Excused","No",IF(AND($G6="PT Modified",$L6="Received"),"No","Yes"))) | P6: =IF(OR($B6="",N($I6)=0),"",MIN(N($I6),SUMIFS(nrMK_Min,nrMK_Link,$B6,nrMK_Credit,"Yes",nrMK_PID,$E6,nrMK_Type,"Classroom"))) | Q6: =IF(OR($B6="",N($J6)=0),"",MIN(N($J6),SUMIFS(nrMK_Sess,nrMK_Link,$B6,nrMK_Credit,"Yes",nrMK_PID,$E6,nrMK_Type,"PT"))) | R6: =IF(OR($B6="",$N6<>"Yes"),"",IF($K6="Yes",IF(N($J6)>0,N($J6)-N($Q6),""),IF(N($I6)>0,N($I6)-N($P6),""))) | S6: =IF(OR($B6="",$R6=""),"",IF($R6<=0,IF(IFERROR(_xlfn.MAXIFS(nrMK_Date,nrMK_Link,$B6,nrMK_Credit,"Yes",nrMK_PID,$E6),0)=0,"CLEARED (makeup date missing)","CLEARED "&TEXT(_xlfn.MAXIFS(nrMK_Date,nrMK_Link,$B6,nrMK_Credit,"Yes",nrMK_PID,$E6),"mm/dd")),"OPEN")) | T6: =IF($D6="","",IF($C6="","NO DATE",IF($G6="","NO EVENT TYPE",IF(AND($I6<>"",NOT(ISNUMBER($I6))),"MINUTES NOT A NUMBER",IF(AND($J6<>"",NOT(ISNUMBER($J6))),"SESSIONS NOT A NUMBER",IF(OR(N($I6)<0,N($J6)<0),"NEGATIVE MINUTES/SESSIONS",IF(AND($K6="Yes",N($I6)>0),"MINUTES ON A PT EVENT - not counted (PT counts sessions)",IF(AND($K6="No",N($J6)>0),"SESSIONS ON A CLASSROOM EVENT - not counted (classroom counts minutes)",IF(AND($N6="Yes",$K6="Yes",N($J6)=0),"COUNTED PT EVENT WITH NO SESSIONS - dropped from the PT cap",IF(AND($N6="Yes",$K6="No",N($I6)=0),"COUNTED EVENT WITH NO MINUTES - dropped from the classroom cap","OK"))))))))))
B7: =IF($D7="","","A"&TEXT(ROW()-5,"000")) | E7: =IF($D7="","",IFERROR(INDEX(rngCadetPIDs,MATCH($D7,rngCadetNames,0)),"?")) | F7: =IF($E7="","",IFERROR(INDEX(nrCadetAgency,MATCH($E7,rngCadetPIDs,0)),"")) | K7: =IF($G7="","",IF(OR($G7="PT Missed",$G7="PT Modified",$G7="PT Refused"),"Yes","No")) | N7: =IF($D7="","",IF($M7="Excused","No",IF(AND($G7="PT Modified",$L7="Received"),"No","Yes"))) | P7: =IF(OR($B7="",N($I7)=0),"",MIN(N($I7),SUMIFS(nrMK_Min,nrMK_Link,$B7,nrMK_Credit,"Yes",nrMK_PID,$E7,nrMK_Type,"Classroom"))) | Q7: =IF(OR($B7="",N($J7)=0),"",MIN(N($J7),SUMIFS(nrMK_Sess,nrMK_Link,$B7,nrMK_Credit,"Yes",nrMK_PID,$E7,nrMK_Type,"PT"))) | R7: =IF(OR($B7="",$N7<>"Yes"),"",IF($K7="Yes",IF(N($J7)>0,N($J7)-N($Q7),""),IF(N($I7)>0,N($I7)-N($P7),""))) | S7: =IF(OR($B7="",$R7=""),"",IF($R7<=0,IF(IFERROR(_xlfn.MAXIFS(nrMK_Date,nrMK_Link,$B7,nrMK_Credit,"Yes",nrMK_PID,$E7),0)=0,"CLEARED (makeup date missing)","CLEARED "&TEXT(_xlfn.MAXIFS(nrMK_Date,nrMK_Link,$B7,nrMK_Credit,"Yes",nrMK_PID,$E7),"mm/dd")),"OPEN")) | T7: =IF($D7="","",IF($C7="","NO DATE",IF($G7="","NO EVENT TYPE",IF(AND($I7<>"",NOT(ISNUMBER($I7))),"MINUTES NOT A NUMBER",IF(AND($J7<>"",NOT(ISNUMBER($J7))),"SESSIONS NOT A NUMBER",IF(OR(N($I7)<0,N($J7)<0),"NEGATIVE MINUTES/SESSIONS",IF(AND($K7="Yes",N($I7)>0),"MINUTES ON A PT EVENT - not counted (PT counts sessions)",IF(AND($K7="No",N($J7)>0),"SESSIONS ON A CLASSROOM EVENT - not counted (classroom counts minutes)",IF(AND($N7="Yes",$K7="Yes",N($J7)=0),"COUNTED PT EVENT WITH NO SESSIONS - dropped from the PT cap",IF(AND($N7="Yes",$K7="No",N($I7)=0),"COUNTED EVENT WITH NO MINUTES - dropped from the classroom cap","OK"))))))))))
B8: =IF($D8="","","A"&TEXT(ROW()-5,"000")) | E8: =IF($D8="","",IFERROR(INDEX(rngCadetPIDs,MATCH($D8,rngCadetNames,0)),"?")) | F8: =IF($E8="","",IFERROR(INDEX(nrCadetAgency,MATCH($E8,rngCadetPIDs,0)),"")) | K8: =IF($G8="","",IF(OR($G8="PT Missed",$G8="PT Modified",$G8="PT Refused"),"Yes","No")) | N8: =IF($D8="","",IF($M8="Excused","No",IF(AND($G8="PT Modified",$L8="Received"),"No","Yes"))) | P8: =IF(OR($B8="",N($I8)=0),"",MIN(N($I8),SUMIFS(nrMK_Min,nrMK_Link,$B8,nrMK_Credit,"Yes",nrMK_PID,$E8,nrMK_Type,"Classroom"))) | Q8: =IF(OR($B8="",N($J8)=0),"",MIN(N($J8),SUMIFS(nrMK_Sess,nrMK_Link,$B8,nrMK_Credit,"Yes",nrMK_PID,$E8,nrMK_Type,"PT"))) | R8: =IF(OR($B8="",$N8<>"Yes"),"",IF($K8="Yes",IF(N($J8)>0,N($J8)-N($Q8),""),IF(N($I8)>0,N($I8)-N($P8),""))) | S8: =IF(OR($B8="",$R8=""),"",IF($R8<=0,IF(IFERROR(_xlfn.MAXIFS(nrMK_Date,nrMK_Link,$B8,nrMK_Credit,"Yes",nrMK_PID,$E8),0)=0,"CLEARED (makeup date missing)","CLEARED "&TEXT(_xlfn.MAXIFS(nrMK_Date,nrMK_Link,$B8,nrMK_Credit,"Yes",nrMK_PID,$E8),"mm/dd")),"OPEN")) | T8: =IF($D8="","",IF($C8="","NO DATE",IF($G8="","NO EVENT TYPE",IF(AND($I8<>"",NOT(ISNUMBER($I8))),"MINUTES NOT A NUMBER",IF(AND($J8<>"",NOT(ISNUMBER($J8))),"SESSIONS NOT A NUMBER",IF(OR(N($I8)<0,N($J8)<0),"NEGATIVE MINUTES/SESSIONS",IF(AND($K8="Yes",N($I8)>0),"MINUTES ON A PT EVENT - not counted (PT counts sessions)",IF(AND($K8="No",N($J8)>0),"SESSIONS ON A CLASSROOM EVENT - not counted (classroom counts minutes)",IF(AND($N8="Yes",$K8="Yes",N($J8)=0),"COUNTED PT EVENT WITH NO SESSIONS - dropped from the PT cap",IF(AND($N8="Yes",$K8="No",N($I8)=0),"COUNTED EVENT WITH NO MINUTES - dropped from the classroom cap","OK"))))))))))
B9: =IF($D9="","","A"&TEXT(ROW()-5,"000")) | E9: =IF($D9="","",IFERROR(INDEX(rngCadetPIDs,MATCH($D9,rngCadetNames,0)),"?")) | F9: =IF($E9="","",IFERROR(INDEX(nrCadetAgency,MATCH($E9,rngCadetPIDs,0)),"")) | K9: =IF($G9="","",IF(OR($G9="PT Missed",$G9="PT Modified",$G9="PT Refused"),"Yes","No")) | N9: =IF($D9="","",IF($M9="Excused","No",IF(AND($G9="PT Modified",$L9="Received"),"No","Yes"))) | P9: =IF(OR($B9="",N($I9)=0),"",MIN(N($I9),SUMIFS(nrMK_Min,nrMK_Link,$B9,nrMK_Credit,"Yes",nrMK_PID,$E9,nrMK_Type,"Classroom"))) | Q9: =IF(OR($B9="",N($J9)=0),"",MIN(N($J9),SUMIFS(nrMK_Sess,nrMK_Link,$B9,nrMK_Credit,"Yes",nrMK_PID,$E9,nrMK_Type,"PT"))) | R9: =IF(OR($B9="",$N9<>"Yes"),"",IF($K9="Yes",IF(N($J9)>0,N($J9)-N($Q9),""),IF(N($I9)>0,N($I9)-N($P9),""))) | S9: =IF(OR($B9="",$R9=""),"",IF($R9<=0,IF(IFERROR(_xlfn.MAXIFS(nrMK_Date,nrMK_Link,$B9,nrMK_Credit,"Yes",nrMK_PID,$E9),0)=0,"CLEARED (makeup date missing)","CLEARED "&TEXT(_xlfn.MAXIFS(nrMK_Date,nrMK_Link,$B9,nrMK_Credit,"Yes",nrMK_PID,$E9),"mm/dd")),"OPEN")) | T9: =IF($D9="","",IF($C9="","NO DATE",IF($G9="","NO EVENT TYPE",IF(AND($I9<>"",NOT(ISNUMBER($I9))),"MINUTES NOT A NUMBER",IF(AND($J9<>"",NOT(ISNUMBER($J9))),"SESSIONS NOT A NUMBER",IF(OR(N($I9)<0,N($J9)<0),"NEGATIVE MINUTES/SESSIONS",IF(AND($K9="Yes",N($I9)>0),"MINUTES ON A PT EVENT - not counted (PT counts sessions)",IF(AND($K9="No",N($J9)>0),"SESSIONS ON A CLASSROOM EVENT - not counted (classroom counts minutes)",IF(AND($N9="Yes",$K9="Yes",N($J9)=0),"COUNTED PT EVENT WITH NO SESSIONS - dropped from the PT cap",IF(AND($N9="Yes",$K9="No",N($I9)=0),"COUNTED EVENT WITH NO MINUTES - dropped from the classroom cap","OK"))))))))))
B10: =IF($D10="","","A"&TEXT(ROW()-5,"000")) | E10: =IF($D10="","",IFERROR(INDEX(rngCadetPIDs,MATCH($D10,rngCadetNames,0)),"?")) | F10: =IF($E10="","",IFERROR(INDEX(nrCadetAgency,MATCH($E10,rngCadetPIDs,0)),"")) | K10: =IF($G10="","",IF(OR($G10="PT Missed",$G10="PT Modified",$G10="PT Refused"),"Yes","No")) | N10: =IF($D10="","",IF($M10="Excused","No",IF(AND($G10="PT Modified",$L10="Received"),"No","Yes"))) | P10: =IF(OR($B10="",N($I10)=0),"",MIN(N($I10),SUMIFS(nrMK_Min,nrMK_Link,$B10,nrMK_Credit,"Yes",nrMK_PID,$E10,nrMK_Type,"Classroom"))) | Q10: =IF(OR($B10="",N($J10)=0),"",MIN(N($J10),SUMIFS(nrMK_Sess,nrMK_Link,$B10,nrMK_Credit,"Yes",nrMK_PID,$E10,nrMK_Type,"PT"))) | R10: =IF(OR($B10="",$N10<>"Yes"),"",IF($K10="Yes",IF(N($J10)>0,N($J10)-N($Q10),""),IF(N($I10)>0,N($I10)-N($P10),""))) | S10: =IF(OR($B10="",$R10=""),"",IF($R10<=0,IF(IFERROR(_xlfn.MAXIFS(nrMK_Date,nrMK_Link,$B10,nrMK_Credit,"Yes",nrMK_PID,$E10),0)=0,"CLEARED (makeup date missing)","CLEARED "&TEXT(_xlfn.MAXIFS(nrMK_Date,nrMK_Link,$B10,nrMK_Credit,"Yes",nrMK_PID,$E10),"mm/dd")),"OPEN")) | T10: =IF($D10="","",IF($C10="","NO DATE",IF($G10="","NO EVENT TYPE",IF(AND($I10<>"",NOT(ISNUMBER($I10))),"MINUTES NOT A NUMBER",IF(AND($J10<>"",NOT(ISNUMBER($J10))),"SESSIONS NOT A NUMBER",IF(OR(N($I10)<0,N($J10)<0),"NEGATIVE MINUTES/SESSIONS",IF(AND($K10="Yes",N($I10)>0),"MINUTES ON A PT EVENT - not counted (PT counts sessions)",IF(AND($K10="No",N($J10)>0),"SESSIONS ON A CLASSROOM EVENT - not counted (classroom counts minutes)",IF(AND($N10="Yes",$K10="Yes",N($J10)=0),"COUNTED PT EVENT WITH NO SESSIONS - dropped from the PT cap",IF(AND($N10="Yes",$K10="No",N($I10)=0),"COUNTED EVENT WITH NO MINUTES - dropped from the classroom cap","OK"))))))))))
B11: =IF($D11="","","A"&TEXT(ROW()-5,"000")) | E11: =IF($D11="","",IFERROR(INDEX(rngCadetPIDs,MATCH($D11,rngCadetNames,0)),"?")) | F11: =IF($E11="","",IFERROR(INDEX(nrCadetAgency,MATCH($E11,rngCadetPIDs,0)),"")) | K11: =IF($G11="","",IF(OR($G11="PT Missed",$G11="PT Modified",$G11="PT Refused"),"Yes","No")) | N11: =IF($D11="","",IF($M11="Excused","No",IF(AND($G11="PT Modified",$L11="Received"),"No","Yes"))) | P11: =IF(OR($B11="",N($I11)=0),"",MIN(N($I11),SUMIFS(nrMK_Min,nrMK_Link,$B11,nrMK_Credit,"Yes",nrMK_PID,$E11,nrMK_Type,"Classroom"))) | Q11: =IF(OR($B11="",N($J11)=0),"",MIN(N($J11),SUMIFS(nrMK_Sess,nrMK_Link,$B11,nrMK_Credit,"Yes",nrMK_PID,$E11,nrMK_Type,"PT"))) | R11: =IF(OR($B11="",$N11<>"Yes"),"",IF($K11="Yes",IF(N($J11)>0,N($J11)-N($Q11),""),IF(N($I11)>0,N($I11)-N($P11),""))) | S11: =IF(OR($B11="",$R11=""),"",IF($R11<=0,IF(IFERROR(_xlfn.MAXIFS(nrMK_Date,nrMK_Link,$B11,nrMK_Credit,"Yes",nrMK_PID,$E11),0)=0,"CLEARED (makeup date missing)","CLEARED "&TEXT(_xlfn.MAXIFS(nrMK_Date,nrMK_Link,$B11,nrMK_Credit,"Yes",nrMK_PID,$E11),"mm/dd")),"OPEN")) | T11: =IF($D11="","",IF($C11="","NO DATE",IF($G11="","NO EVENT TYPE",IF(AND($I11<>"",NOT(ISNUMBER($I11))),"MINUTES NOT A NUMBER",IF(AND($J11<>"",NOT(ISNUMBER($J11))),"SESSIONS NOT A NUMBER",IF(OR(N($I11)<0,N($J11)<0),"NEGATIVE MINUTES/SESSIONS",IF(AND($K11="Yes",N($I11)>0),"MINUTES ON A PT EVENT - not counted (PT counts sessions)",IF(AND($K11="No",N($J11)>0),"SESSIONS ON A CLASSROOM EVENT - not counted (classroom counts minutes)",IF(AND($N11="Yes",$K11="Yes",N($J11)=0),"COUNTED PT EVENT WITH NO SESSIONS - dropped from the PT cap",IF(AND($N11="Yes",$K11="No",N($I11)=0),"COUNTED EVENT WITH NO MINUTES - dropped from the classroom cap","OK"))))))))))
B12: =IF($D12="","","A"&TEXT(ROW()-5,"000")) | E12: =IF($D12="","",IFERROR(INDEX(rngCadetPIDs,MATCH($D12,rngCadetNames,0)),"?")) | F12: =IF($E12="","",IFERROR(INDEX(nrCadetAgency,MATCH($E12,rngCadetPIDs,0)),"")) | K12: =IF($G12="","",IF(OR($G12="PT Missed",$G12="PT Modified",$G12="PT Refused"),"Yes","No")) | N12: =IF($D12="","",IF($M12="Excused","No",IF(AND($G12="PT Modified",$L12="Received"),"No","Yes"))) | P12: =IF(OR($B12="",N($I12)=0),"",MIN(N($I12),SUMIFS(nrMK_Min,nrMK_Link,$B12,nrMK_Credit,"Yes",nrMK_PID,$E12,nrMK_Type,"Classroom"))) | Q12: =IF(OR($B12="",N($J12)=0),"",MIN(N($J12),SUMIFS(nrMK_Sess,nrMK_Link,$B12,nrMK_Credit,"Yes",nrMK_PID,$E12,nrMK_Type,"PT"))) | R12: =IF(OR($B12="",$N12<>"Yes"),"",IF($K12="Yes",IF(N($J12)>0,N($J12)-N($Q12),""),IF(N($I12)>0,N($I12)-N($P12),""))) | S12: =IF(OR($B12="",$R12=""),"",IF($R12<=0,IF(IFERROR(_xlfn.MAXIFS(nrMK_Date,nrMK_Link,$B12,nrMK_Credit,"Yes",nrMK_PID,$E12),0)=0,"CLEARED (makeup date missing)","CLEARED "&TEXT(_xlfn.MAXIFS(nrMK_Date,nrMK_Link,$B12,nrMK_Credit,"Yes",nrMK_PID,$E12),"mm/dd")),"OPEN")) | T12: =IF($D12="","",IF($C12="","NO DATE",IF($G12="","NO EVENT TYPE",IF(AND($I12<>"",NOT(ISNUMBER($I12))),"MINUTES NOT A NUMBER",IF(AND($J12<>"",NOT(ISNUMBER($J12))),"SESSIONS NOT A NUMBER",IF(OR(N($I12)<0,N($J12)<0),"NEGATIVE MINUTES/SESSIONS",IF(AND($K12="Yes",N($I12)>0),"MINUTES ON A PT EVENT - not counted (PT counts sessions)",IF(AND($K12="No",N($J12)>0),"SESSIONS ON A CLASSROOM EVENT - not counted (classroom counts minutes)",IF(AND($N12="Yes",$K12="Yes",N($J12)=0),"COUNTED PT EVENT WITH NO SESSIONS - dropped from the PT cap",IF(AND($N12="Yes",$K12="No",N($I12)=0),"COUNTED EVENT WITH NO MINUTES - dropped from the classroom cap","OK"))))))))))
B13: =IF($D13="","","A"&TEXT(ROW()-5,"000")) | E13: =IF($D13="","",IFERROR(INDEX(rngCadetPIDs,MATCH($D13,rngCadetNames,0)),"?")) | F13: =IF($E13="","",IFERROR(INDEX(nrCadetAgency,MATCH($E13,rngCadetPIDs,0)),"")) | K13: =IF($G13="","",IF(OR($G13="PT Missed",$G13="PT Modified",$G13="PT Refused"),"Yes","No")) | N13: =IF($D13="","",IF($M13="Excused","No",IF(AND($G13="PT Modified",$L13="Received"),"No","Yes"))) | P13: =IF(OR($B13="",N($I13)=0),"",MIN(N($I13),SUMIFS(nrMK_Min,nrMK_Link,$B13,nrMK_Credit,"Yes",nrMK_PID,$E13,nrMK_Type,"Classroom"))) | Q13: =IF(OR($B13="",N($J13)=0),"",MIN(N($J13),SUMIFS(nrMK_Sess,nrMK_Link,$B13,nrMK_Credit,"Yes",nrMK_PID,$E13,nrMK_Type,"PT"))) | R13: =IF(OR($B13="",$N13<>"Yes"),"",IF($K13="Yes",IF(N($J13)>0,N($J13)-N($Q13),""),IF(N($I13)>0,N($I13)-N($P13),""))) | S13: =IF(OR($B13="",$R13=""),"",IF($R13<=0,IF(IFERROR(_xlfn.MAXIFS(nrMK_Date,nrMK_Link,$B13,nrMK_Credit,"Yes",nrMK_PID,$E13),0)=0,"CLEARED (makeup date missing)","CLEARED "&TEXT(_xlfn.MAXIFS(nrMK_Date,nrMK_Link,$B13,nrMK_Credit,"Yes",nrMK_PID,$E13),"mm/dd")),"OPEN")) | T13: =IF($D13="","",IF($C13="","NO DATE",IF($G13="","NO EVENT TYPE",IF(AND($I13<>"",NOT(ISNUMBER($I13))),"MINUTES NOT A NUMBER",IF(AND($J13<>"",NOT(ISNUMBER($J13))),"SESSIONS NOT A NUMBER",IF(OR(N($I13)<0,N($J13)<0),"NEGATIVE MINUTES/SESSIONS",IF(AND($K13="Yes",N($I13)>0),"MINUTES ON A PT EVENT - not counted (PT counts sessions)",IF(AND($K13="No",N($J13)>0),"SESSIONS ON A CLASSROOM EVENT - not counted (classroom counts minutes)",IF(AND($N13="Yes",$K13="Yes",N($J13)=0),"COUNTED PT EVENT WITH NO SESSIONS - dropped from the PT cap",IF(AND($N13="Yes",$K13="No",N($I13)=0),"COUNTED EVENT WITH NO MINUTES - dropped from the classroom cap","OK"))))))))))
B14: =IF($D14="","","A"&TEXT(ROW()-5,"000")) | E14: =IF($D14="","",IFERROR(INDEX(rngCadetPIDs,MATCH($D14,rngCadetNames,0)),"?")) | F14: =IF($E14="","",IFERROR(INDEX(nrCadetAgency,MATCH($E14,rngCadetPIDs,0)),"")) | K14: =IF($G14="","",IF(OR($G14="PT Missed",$G14="PT Modified",$G14="PT Refused"),"Yes","No")) | N14: =IF($D14="","",IF($M14="Excused","No",IF(AND($G14="PT Modified",$L14="Received"),"No","Yes"))) | P14: =IF(OR($B14="",N($I14)=0),"",MIN(N($I14),SUMIFS(nrMK_Min,nrMK_Link,$B14,nrMK_Credit,"Yes",nrMK_PID,$E14,nrMK_Type,"Classroom"))) | Q14: =IF(OR($B14="",N($J14)=0),"",MIN(N($J14),SUMIFS(nrMK_Sess,nrMK_Link,$B14,nrMK_Credit,"Yes",nrMK_PID,$E14,nrMK_Type,"PT"))) | R14: =IF(OR($B14="",$N14<>"Yes"),"",IF($K14="Yes",IF(N($J14)>0,N($J14)-N($Q14),""),IF(N($I14)>0,N($I14)-N($P14),""))) | S14: =IF(OR($B14="",$R14=""),"",IF($R14<=0,IF(IFERROR(_xlfn.MAXIFS(nrMK_Date,nrMK_Link,$B14,nrMK_Credit,"Yes",nrMK_PID,$E14),0)=0,"CLEARED (makeup date missing)","CLEARED "&TEXT(_xlfn.MAXIFS(nrMK_Date,nrMK_Link,$B14,nrMK_Credit,"Yes",nrMK_PID,$E14),"mm/dd")),"OPEN")) | T14: =IF($D14="","",IF($C14="","NO DATE",IF($G14="","NO EVENT TYPE",IF(AND($I14<>"",NOT(ISNUMBER($I14))),"MINUTES NOT A NUMBER",IF(AND($J14<>"",NOT(ISNUMBER($J14))),"SESSIONS NOT A NUMBER",IF(OR(N($I14)<0,N($J14)<0),"NEGATIVE MINUTES/SESSIONS",IF(AND($K14="Yes",N($I14)>0),"MINUTES ON A PT EVENT - not counted (PT counts sessions)",IF(AND($K14="No",N($J14)>0),"SESSIONS ON A CLASSROOM EVENT - not counted (classroom counts minutes)",IF(AND($N14="Yes",$K14="Yes",N($J14)=0),"COUNTED PT EVENT WITH NO SESSIONS - dropped from the PT cap",IF(AND($N14="Yes",$K14="No",N($I14)=0),"COUNTED EVENT WITH NO MINUTES - dropped from the classroom cap","OK"))))))))))
B15: =IF($D15="","","A"&TEXT(ROW()-5,"000")) | E15: =IF($D15="","",IFERROR(INDEX(rngCadetPIDs,MATCH($D15,rngCadetNames,0)),"?")) | F15: =IF($E15="","",IFERROR(INDEX(nrCadetAgency,MATCH($E15,rngCadetPIDs,0)),"")) | K15: =IF($G15="","",IF(OR($G15="PT Missed",$G15="PT Modified",$G15="PT Refused"),"Yes","No")) | N15: =IF($D15="","",IF($M15="Excused","No",IF(AND($G15="PT Modified",$L15="Received"),"No","Yes"))) | P15: =IF(OR($B15="",N($I15)=0),"",MIN(N($I15),SUMIFS(nrMK_Min,nrMK_Link,$B15,nrMK_Credit,"Yes",nrMK_PID,$E15,nrMK_Type,"Classroom"))) | Q15: =IF(OR($B15="",N($J15)=0),"",MIN(N($J15),SUMIFS(nrMK_Sess,nrMK_Link,$B15,nrMK_Credit,"Yes",nrMK_PID,$E15,nrMK_Type,"PT"))) | R15: =IF(OR($B15="",$N15<>"Yes"),"",IF($K15="Yes",IF(N($J15)>0,N($J15)-N($Q15),""),IF(N($I15)>0,N($I15)-N($P15),""))) | S15: =IF(OR($B15="",$R15=""),"",IF($R15<=0,IF(IFERROR(_xlfn.MAXIFS(nrMK_Date,nrMK_Link,$B15,nrMK_Credit,"Yes",nrMK_PID,$E15),0)=0,"CLEARED (makeup date missing)","CLEARED "&TEXT(_xlfn.MAXIFS(nrMK_Date,nrMK_Link,$B15,nrMK_Credit,"Yes",nrMK_PID,$E15),"mm/dd")),"OPEN")) | T15: =IF($D15="","",IF($C15="","NO DATE",IF($G15="","NO EVENT TYPE",IF(AND($I15<>"",NOT(ISNUMBER($I15))),"MINUTES NOT A NUMBER",IF(AND($J15<>"",NOT(ISNUMBER($J15))),"SESSIONS NOT A NUMBER",IF(OR(N($I15)<0,N($J15)<0),"NEGATIVE MINUTES/SESSIONS",IF(AND($K15="Yes",N($I15)>0),"MINUTES ON A PT EVENT - not counted (PT counts sessions)",IF(AND($K15="No",N($J15)>0),"SESSIONS ON A CLASSROOM EVENT - not counted (classroom counts minutes)",IF(AND($N15="Yes",$K15="Yes",N($J15)=0),"COUNTED PT EVENT WITH NO SESSIONS - dropped from the PT cap",IF(AND($N15="Yes",$K15="No",N($I15)=0),"COUNTED EVENT WITH NO MINUTES - dropped from the classroom cap","OK"))))))))))
B16: =IF($D16="","","A"&TEXT(ROW()-5,"000")) | E16: =IF($D16="","",IFERROR(INDEX(rngCadetPIDs,MATCH($D16,rngCadetNames,0)),"?")) | F16: =IF($E16="","",IFERROR(INDEX(nrCadetAgency,MATCH($E16,rngCadetPIDs,0)),"")) | K16: =IF($G16="","",IF(OR($G16="PT Missed",$G16="PT Modified",$G16="PT Refused"),"Yes","No")) | N16: =IF($D16="","",IF($M16="Excused","No",IF(AND($G16="PT Modified",$L16="Received"),"No","Yes"))) | P16: =IF(OR($B16="",N($I16)=0),"",MIN(N($I16),SUMIFS(nrMK_Min,nrMK_Link,$B16,nrMK_Credit,"Yes",nrMK_PID,$E16,nrMK_Type,"Classroom"))) | Q16: =IF(OR($B16="",N($J16)=0),"",MIN(N($J16),SUMIFS(nrMK_Sess,nrMK_Link,$B16,nrMK_Credit,"Yes",nrMK_PID,$E16,nrMK_Type,"PT"))) | R16: =IF(OR($B16="",$N16<>"Yes"),"",IF($K16="Yes",IF(N($J16)>0,N($J16)-N($Q16),""),IF(N($I16)>0,N($I16)-N($P16),""))) | S16: =IF(OR($B16="",$R16=""),"",IF($R16<=0,IF(IFERROR(_xlfn.MAXIFS(nrMK_Date,nrMK_Link,$B16,nrMK_Credit,"Yes",nrMK_PID,$E16),0)=0,"CLEARED (makeup date missing)","CLEARED "&TEXT(_xlfn.MAXIFS(nrMK_Date,nrMK_Link,$B16,nrMK_Credit,"Yes",nrMK_PID,$E16),"mm/dd")),"OPEN")) | T16: =IF($D16="","",IF($C16="","NO DATE",IF($G16="","NO EVENT TYPE",IF(AND($I16<>"",NOT(ISNUMBER($I16))),"MINUTES NOT A NUMBER",IF(AND($J16<>"",NOT(ISNUMBER($J16))),"SESSIONS NOT A NUMBER",IF(OR(N($I16)<0,N($J16)<0),"NEGATIVE MINUTES/SESSIONS",IF(AND($K16="Yes",N($I16)>0),"MINUTES ON A PT EVENT - not counted (PT counts sessions)",IF(AND($K16="No",N($J16)>0),"SESSIONS ON A CLASSROOM EVENT - not counted (classroom counts minutes)",IF(AND($N16="Yes",$K16="Yes",N($J16)=0),"COUNTED PT EVENT WITH NO SESSIONS - dropped from the PT cap",IF(AND($N16="Yes",$K16="No",N($I16)=0),"COUNTED EVENT WITH NO MINUTES - dropped from the classroom cap","OK"))))))))))
B17: =IF($D17="","","A"&TEXT(ROW()-5,"000")) | E17: =IF($D17="","",IFERROR(INDEX(rngCadetPIDs,MATCH($D17,rngCadetNames,0)),"?")) | F17: =IF($E17="","",IFERROR(INDEX(nrCadetAgency,MATCH($E17,rngCadetPIDs,0)),"")) | K17: =IF($G17="","",IF(OR($G17="PT Missed",$G17="PT Modified",$G17="PT Refused"),"Yes","No")) | N17: =IF($D17="","",IF($M17="Excused","No",IF(AND($G17="PT Modified",$L17="Received"),"No","Yes"))) | P17: =IF(OR($B17="",N($I17)=0),"",MIN(N($I17),SUMIFS(nrMK_Min,nrMK_Link,$B17,nrMK_Credit,"Yes",nrMK_PID,$E17,nrMK_Type,"Classroom"))) | Q17: =IF(OR($B17="",N($J17)=0),"",MIN(N($J17),SUMIFS(nrMK_Sess,nrMK_Link,$B17,nrMK_Credit,"Yes",nrMK_PID,$E17,nrMK_Type,"PT"))) | R17: =IF(OR($B17="",$N17<>"Yes"),"",IF($K17="Yes",IF(N($J17)>0,N($J17)-N($Q17),""),IF(N($I17)>0,N($I17)-N($P17),""))) | S17: =IF(OR($B17="",$R17=""),"",IF($R17<=0,IF(IFERROR(_xlfn.MAXIFS(nrMK_Date,nrMK_Link,$B17,nrMK_Credit,"Yes",nrMK_PID,$E17),0)=0,"CLEARED (makeup date missing)","CLEARED "&TEXT(_xlfn.MAXIFS(nrMK_Date,nrMK_Link,$B17,nrMK_Credit,"Yes",nrMK_PID,$E17),"mm/dd")),"OPEN")) | T17: =IF($D17="","",IF($C17="","NO DATE",IF($G17="","NO EVENT TYPE",IF(AND($I17<>"",NOT(ISNUMBER($I17))),"MINUTES NOT A NUMBER",IF(AND($J17<>"",NOT(ISNUMBER($J17))),"SESSIONS NOT A NUMBER",IF(OR(N($I17)<0,N($J17)<0),"NEGATIVE MINUTES/SESSIONS",IF(AND($K17="Yes",N($I17)>0),"MINUTES ON A PT EVENT - not counted (PT counts sessions)",IF(AND($K17="No",N($J17)>0),"SESSIONS ON A CLASSROOM EVENT - not counted (classroom counts minutes)",IF(AND($N17="Yes",$K17="Yes",N($J17)=0),"COUNTED PT EVENT WITH NO SESSIONS - dropped from the PT cap",IF(AND($N17="Yes",$K17="No",N($I17)=0),"COUNTED EVENT WITH NO MINUTES - dropped from the classroom cap","OK"))))))))))
... B805: =IF($D805="","","A"&TEXT(ROW()-5,"000")) | E805: =IF($D805="","",IFERROR(INDEX(rngCadetPIDs,MATCH($D805,rngCadetNames,0)),"?")) | F805: =IF($E805="","",IFERROR(INDEX(nrCadetAgency,MATCH($E805,rngCadetPIDs,0)),"")) | K805: =IF($G805="","",IF(OR($G805="PT Missed",$G805="PT Modified",$G805="PT Refused"),"Yes","No")) | N805: =IF($D805="","",IF($M805="Excused","No",IF(AND($G805="PT Modified",$L805="Received"),"No","Yes"))) | P805: =IF(OR($B805="",N($I805)=0),"",MIN(N($I805),SUMIFS(nrMK_Min,nrMK_Link,$B805,nrMK_Credit,"Yes",nrMK_PID,$E805,nrMK_Type,"Classroom"))) | Q805: =IF(OR($B805="",N($J805)=0),"",MIN(N($J805),SUMIFS(nrMK_Sess,nrMK_Link,$B805,nrMK_Credit,"Yes",nrMK_PID,$E805,nrMK_Type,"PT"))) | R805: =IF(OR($B805="",$N805<>"Yes"),"",IF($K805="Yes",IF(N($J805)>0,N($J805)-N($Q805),""),IF(N($I805)>0,N($I805)-N($P805),""))) | S805: =IF(OR($B805="",$R805=""),"",IF($R805<=0,IF(IFERROR(_xlfn.MAXIFS(nrMK_Date,nrMK_Link,$B805,nrMK_Credit,"Yes",nrMK_PID,$E805),0)=0,"CLEARED (makeup date missing)","CLEARED "&TEXT(_xlfn.MAXIFS(nrMK_Date,nrMK_Link,$B805,nrMK_Credit,"Yes",nrMK_PID,$E805),"mm/dd")),"OPEN")) | T805: =IF($D805="","",IF($C805="","NO DATE",IF($G805="","NO EVENT TYPE",IF(AND($I805<>"",NOT(ISNUMBER($I805))),"MINUTES NOT A NUMBER",IF(AND($J805<>"",NOT(ISNUMBER($J805))),"SESSIONS NOT A NUMBER",IF(OR(N($I805)<0,N($J805)<0),"NEGATIVE MINUTES/SESSIONS",IF(AND($K805="Yes",N($I805)>0),"MINUTES ON A PT EVENT - not counted (PT counts sessions)",IF(AND($K805="No",N($J805)>0),"SESSIONS ON A CLASSROOM EVENT - not counted (classroom counts minutes)",IF(AND($N805="Yes",$K805="Yes",N($J805)=0),"COUNTED PT EVENT WITH NO SESSIONS - dropped from the PT cap",IF(AND($N805="Yes",$K805="No",N($I805)=0),"COUNTED EVENT WITH NO MINUTES - dropped from the classroom cap","OK"))))))))))

Sheet Makeup
B1: =HYPERLINK("#Dashboard!B5","◄ Dashboard")
B4: Makeup is minute-for-minute (policy 400.5). Only classroom minutes and PT sessions can be made up — skills time cannot, and there is no administrative waiver, so the Type dropdown offers only Classroom and PT. Credit applies only when documentation is Received, no Hold, and Row Check is OK. Pick the missed event's ID in Linked Event — the Attendance sheet clears that event automatically when its balance hits zero. Every credited row must name the event it makes up — Row Check refuses credit with no Linked Event, for another cadet's event, an EventID that no longer exists, a Type the caps don't credit, or minutes booked against a PT (session-counted) event. It also refuses a row with no makeup Date (which used to stamp a fabricated CLEARED date on the attendance ledger) and a zero or NEGATIVE credit (which used to pass as OK and increase the cadet's owed time). Credit is capped at the linked event's own minutes/sessions; split a long session across rows to cover two events.
B5: MakeupID | C5: Date | D5: Cadet Name | E5: PID | F5: Type | G5: Minutes Credit | H5: Sessions Credit | I5: Linked Event | J5: Doc Status | K5: Hold? | L5: Credit Applies? | M5: Notes | N5: Row Check
B6: =IF($D6="","","M"&TEXT(ROW()-5,"000")) | E6: =IF($D6="","",IFERROR(INDEX(rngCadetPIDs,MATCH($D6,rngCadetNames,0)),"?")) | L6: =IF($D6="","",IF(AND($J6="Received",$K6<>"Yes",LEFT($N6,2)="OK"),"Yes","No")) | N6: =IF($D6="","",IF(AND($F6<>"Classroom",$F6<>"PT"),"TYPE NOT CREDITED",IF($C6="","NO MAKEUP DATE",IF(NOT(ISNUMBER($C6)),"MAKEUP DATE NOT A DATE",IF(OR(AND($G6<>"",NOT(ISNUMBER($G6))),AND($H6<>"",NOT(ISNUMBER($H6)))),"CREDIT NOT A NUMBER",IF(OR(N($G6)<0,N($H6)<0),"NEGATIVE CREDIT",IF(AND($F6="Classroom",N($G6)<=0),"NO MINUTES CREDITED",IF(AND($F6="PT",N($H6)<=0),"NO SESSIONS CREDITED",IF($I6="","NO LINKED EVENT",IF(COUNTIF(nrAT_ID,$I6)=0,"NO SUCH EVENT",IF(INDEX(nrAT_PID,MATCH($I6,nrAT_ID,0))<>$E6,"WRONG CADET",IF(INDEX(nrAT_IsPT,MATCH($I6,nrAT_ID,0))<>IF($F6="PT","Yes","No"),"UNIT MISMATCH","OK"))))))))))))
B7: =IF($D7="","","M"&TEXT(ROW()-5,"000")) | E7: =IF($D7="","",IFERROR(INDEX(rngCadetPIDs,MATCH($D7,rngCadetNames,0)),"?")) | L7: =IF($D7="","",IF(AND($J7="Received",$K7<>"Yes",LEFT($N7,2)="OK"),"Yes","No")) | N7: =IF($D7="","",IF(AND($F7<>"Classroom",$F7<>"PT"),"TYPE NOT CREDITED",IF($C7="","NO MAKEUP DATE",IF(NOT(ISNUMBER($C7)),"MAKEUP DATE NOT A DATE",IF(OR(AND($G7<>"",NOT(ISNUMBER($G7))),AND($H7<>"",NOT(ISNUMBER($H7)))),"CREDIT NOT A NUMBER",IF(OR(N($G7)<0,N($H7)<0),"NEGATIVE CREDIT",IF(AND($F7="Classroom",N($G7)<=0),"NO MINUTES CREDITED",IF(AND($F7="PT",N($H7)<=0),"NO SESSIONS CREDITED",IF($I7="","NO LINKED EVENT",IF(COUNTIF(nrAT_ID,$I7)=0,"NO SUCH EVENT",IF(INDEX(nrAT_PID,MATCH($I7,nrAT_ID,0))<>$E7,"WRONG CADET",IF(INDEX(nrAT_IsPT,MATCH($I7,nrAT_ID,0))<>IF($F7="PT","Yes","No"),"UNIT MISMATCH","OK"))))))))))))
B8: =IF($D8="","","M"&TEXT(ROW()-5,"000")) | E8: =IF($D8="","",IFERROR(INDEX(rngCadetPIDs,MATCH($D8,rngCadetNames,0)),"?")) | L8: =IF($D8="","",IF(AND($J8="Received",$K8<>"Yes",LEFT($N8,2)="OK"),"Yes","No")) | N8: =IF($D8="","",IF(AND($F8<>"Classroom",$F8<>"PT"),"TYPE NOT CREDITED",IF($C8="","NO MAKEUP DATE",IF(NOT(ISNUMBER($C8)),"MAKEUP DATE NOT A DATE",IF(OR(AND($G8<>"",NOT(ISNUMBER($G8))),AND($H8<>"",NOT(ISNUMBER($H8)))),"CREDIT NOT A NUMBER",IF(OR(N($G8)<0,N($H8)<0),"NEGATIVE CREDIT",IF(AND($F8="Classroom",N($G8)<=0),"NO MINUTES CREDITED",IF(AND($F8="PT",N($H8)<=0),"NO SESSIONS CREDITED",IF($I8="","NO LINKED EVENT",IF(COUNTIF(nrAT_ID,$I8)=0,"NO SUCH EVENT",IF(INDEX(nrAT_PID,MATCH($I8,nrAT_ID,0))<>$E8,"WRONG CADET",IF(INDEX(nrAT_IsPT,MATCH($I8,nrAT_ID,0))<>IF($F8="PT","Yes","No"),"UNIT MISMATCH","OK"))))))))))))
B9: =IF($D9="","","M"&TEXT(ROW()-5,"000")) | E9: =IF($D9="","",IFERROR(INDEX(rngCadetPIDs,MATCH($D9,rngCadetNames,0)),"?")) | L9: =IF($D9="","",IF(AND($J9="Received",$K9<>"Yes",LEFT($N9,2)="OK"),"Yes","No")) | N9: =IF($D9="","",IF(AND($F9<>"Classroom",$F9<>"PT"),"TYPE NOT CREDITED",IF($C9="","NO MAKEUP DATE",IF(NOT(ISNUMBER($C9)),"MAKEUP DATE NOT A DATE",IF(OR(AND($G9<>"",NOT(ISNUMBER($G9))),AND($H9<>"",NOT(ISNUMBER($H9)))),"CREDIT NOT A NUMBER",IF(OR(N($G9)<0,N($H9)<0),"NEGATIVE CREDIT",IF(AND($F9="Classroom",N($G9)<=0),"NO MINUTES CREDITED",IF(AND($F9="PT",N($H9)<=0),"NO SESSIONS CREDITED",IF($I9="","NO LINKED EVENT",IF(COUNTIF(nrAT_ID,$I9)=0,"NO SUCH EVENT",IF(INDEX(nrAT_PID,MATCH($I9,nrAT_ID,0))<>$E9,"WRONG CADET",IF(INDEX(nrAT_IsPT,MATCH($I9,nrAT_ID,0))<>IF($F9="PT","Yes","No"),"UNIT MISMATCH","OK"))))))))))))
B10: =IF($D10="","","M"&TEXT(ROW()-5,"000")) | E10: =IF($D10="","",IFERROR(INDEX(rngCadetPIDs,MATCH($D10,rngCadetNames,0)),"?")) | L10: =IF($D10="","",IF(AND($J10="Received",$K10<>"Yes",LEFT($N10,2)="OK"),"Yes","No")) | N10: =IF($D10="","",IF(AND($F10<>"Classroom",$F10<>"PT"),"TYPE NOT CREDITED",IF($C10="","NO MAKEUP DATE",IF(NOT(ISNUMBER($C10)),"MAKEUP DATE NOT A DATE",IF(OR(AND($G10<>"",NOT(ISNUMBER($G10))),AND($H10<>"",NOT(ISNUMBER($H10)))),"CREDIT NOT A NUMBER",IF(OR(N($G10)<0,N($H10)<0),"NEGATIVE CREDIT",IF(AND($F10="Classroom",N($G10)<=0),"NO MINUTES CREDITED",IF(AND($F10="PT",N($H10)<=0),"NO SESSIONS CREDITED",IF($I10="","NO LINKED EVENT",IF(COUNTIF(nrAT_ID,$I10)=0,"NO SUCH EVENT",IF(INDEX(nrAT_PID,MATCH($I10,nrAT_ID,0))<>$E10,"WRONG CADET",IF(INDEX(nrAT_IsPT,MATCH($I10,nrAT_ID,0))<>IF($F10="PT","Yes","No"),"UNIT MISMATCH","OK"))))))))))))
B11: =IF($D11="","","M"&TEXT(ROW()-5,"000")) | E11: =IF($D11="","",IFERROR(INDEX(rngCadetPIDs,MATCH($D11,rngCadetNames,0)),"?")) | L11: =IF($D11="","",IF(AND($J11="Received",$K11<>"Yes",LEFT($N11,2)="OK"),"Yes","No")) | N11: =IF($D11="","",IF(AND($F11<>"Classroom",$F11<>"PT"),"TYPE NOT CREDITED",IF($C11="","NO MAKEUP DATE",IF(NOT(ISNUMBER($C11)),"MAKEUP DATE NOT A DATE",IF(OR(AND($G11<>"",NOT(ISNUMBER($G11))),AND($H11<>"",NOT(ISNUMBER($H11)))),"CREDIT NOT A NUMBER",IF(OR(N($G11)<0,N($H11)<0),"NEGATIVE CREDIT",IF(AND($F11="Classroom",N($G11)<=0),"NO MINUTES CREDITED",IF(AND($F11="PT",N($H11)<=0),"NO SESSIONS CREDITED",IF($I11="","NO LINKED EVENT",IF(COUNTIF(nrAT_ID,$I11)=0,"NO SUCH EVENT",IF(INDEX(nrAT_PID,MATCH($I11,nrAT_ID,0))<>$E11,"WRONG CADET",IF(INDEX(nrAT_IsPT,MATCH($I11,nrAT_ID,0))<>IF($F11="PT","Yes","No"),"UNIT MISMATCH","OK"))))))))))))
B12: =IF($D12="","","M"&TEXT(ROW()-5,"000")) | E12: =IF($D12="","",IFERROR(INDEX(rngCadetPIDs,MATCH($D12,rngCadetNames,0)),"?")) | L12: =IF($D12="","",IF(AND($J12="Received",$K12<>"Yes",LEFT($N12,2)="OK"),"Yes","No")) | N12: =IF($D12="","",IF(AND($F12<>"Classroom",$F12<>"PT"),"TYPE NOT CREDITED",IF($C12="","NO MAKEUP DATE",IF(NOT(ISNUMBER($C12)),"MAKEUP DATE NOT A DATE",IF(OR(AND($G12<>"",NOT(ISNUMBER($G12))),AND($H12<>"",NOT(ISNUMBER($H12)))),"CREDIT NOT A NUMBER",IF(OR(N($G12)<0,N($H12)<0),"NEGATIVE CREDIT",IF(AND($F12="Classroom",N($G12)<=0),"NO MINUTES CREDITED",IF(AND($F12="PT",N($H12)<=0),"NO SESSIONS CREDITED",IF($I12="","NO LINKED EVENT",IF(COUNTIF(nrAT_ID,$I12)=0,"NO SUCH EVENT",IF(INDEX(nrAT_PID,MATCH($I12,nrAT_ID,0))<>$E12,"WRONG CADET",IF(INDEX(nrAT_IsPT,MATCH($I12,nrAT_ID,0))<>IF($F12="PT","Yes","No"),"UNIT MISMATCH","OK"))))))))))))
B13: =IF($D13="","","M"&TEXT(ROW()-5,"000")) | E13: =IF($D13="","",IFERROR(INDEX(rngCadetPIDs,MATCH($D13,rngCadetNames,0)),"?")) | L13: =IF($D13="","",IF(AND($J13="Received",$K13<>"Yes",LEFT($N13,2)="OK"),"Yes","No")) | N13: =IF($D13="","",IF(AND($F13<>"Classroom",$F13<>"PT"),"TYPE NOT CREDITED",IF($C13="","NO MAKEUP DATE",IF(NOT(ISNUMBER($C13)),"MAKEUP DATE NOT A DATE",IF(OR(AND($G13<>"",NOT(ISNUMBER($G13))),AND($H13<>"",NOT(ISNUMBER($H13)))),"CREDIT NOT A NUMBER",IF(OR(N($G13)<0,N($H13)<0),"NEGATIVE CREDIT",IF(AND($F13="Classroom",N($G13)<=0),"NO MINUTES CREDITED",IF(AND($F13="PT",N($H13)<=0),"NO SESSIONS CREDITED",IF($I13="","NO LINKED EVENT",IF(COUNTIF(nrAT_ID,$I13)=0,"NO SUCH EVENT",IF(INDEX(nrAT_PID,MATCH($I13,nrAT_ID,0))<>$E13,"WRONG CADET",IF(INDEX(nrAT_IsPT,MATCH($I13,nrAT_ID,0))<>IF($F13="PT","Yes","No"),"UNIT MISMATCH","OK"))))))))))))
B14: =IF($D14="","","M"&TEXT(ROW()-5,"000")) | E14: =IF($D14="","",IFERROR(INDEX(rngCadetPIDs,MATCH($D14,rngCadetNames,0)),"?")) | L14: =IF($D14="","",IF(AND($J14="Received",$K14<>"Yes",LEFT($N14,2)="OK"),"Yes","No")) | N14: =IF($D14="","",IF(AND($F14<>"Classroom",$F14<>"PT"),"TYPE NOT CREDITED",IF($C14="","NO MAKEUP DATE",IF(NOT(ISNUMBER($C14)),"MAKEUP DATE NOT A DATE",IF(OR(AND($G14<>"",NOT(ISNUMBER($G14))),AND($H14<>"",NOT(ISNUMBER($H14)))),"CREDIT NOT A NUMBER",IF(OR(N($G14)<0,N($H14)<0),"NEGATIVE CREDIT",IF(AND($F14="Classroom",N($G14)<=0),"NO MINUTES CREDITED",IF(AND($F14="PT",N($H14)<=0),"NO SESSIONS CREDITED",IF($I14="","NO LINKED EVENT",IF(COUNTIF(nrAT_ID,$I14)=0,"NO SUCH EVENT",IF(INDEX(nrAT_PID,MATCH($I14,nrAT_ID,0))<>$E14,"WRONG CADET",IF(INDEX(nrAT_IsPT,MATCH($I14,nrAT_ID,0))<>IF($F14="PT","Yes","No"),"UNIT MISMATCH","OK"))))))))))))
B15: =IF($D15="","","M"&TEXT(ROW()-5,"000")) | E15: =IF($D15="","",IFERROR(INDEX(rngCadetPIDs,MATCH($D15,rngCadetNames,0)),"?")) | L15: =IF($D15="","",IF(AND($J15="Received",$K15<>"Yes",LEFT($N15,2)="OK"),"Yes","No")) | N15: =IF($D15="","",IF(AND($F15<>"Classroom",$F15<>"PT"),"TYPE NOT CREDITED",IF($C15="","NO MAKEUP DATE",IF(NOT(ISNUMBER($C15)),"MAKEUP DATE NOT A DATE",IF(OR(AND($G15<>"",NOT(ISNUMBER($G15))),AND($H15<>"",NOT(ISNUMBER($H15)))),"CREDIT NOT A NUMBER",IF(OR(N($G15)<0,N($H15)<0),"NEGATIVE CREDIT",IF(AND($F15="Classroom",N($G15)<=0),"NO MINUTES CREDITED",IF(AND($F15="PT",N($H15)<=0),"NO SESSIONS CREDITED",IF($I15="","NO LINKED EVENT",IF(COUNTIF(nrAT_ID,$I15)=0,"NO SUCH EVENT",IF(INDEX(nrAT_PID,MATCH($I15,nrAT_ID,0))<>$E15,"WRONG CADET",IF(INDEX(nrAT_IsPT,MATCH($I15,nrAT_ID,0))<>IF($F15="PT","Yes","No"),"UNIT MISMATCH","OK"))))))))))))
B16: =IF($D16="","","M"&TEXT(ROW()-5,"000")) | E16: =IF($D16="","",IFERROR(INDEX(rngCadetPIDs,MATCH($D16,rngCadetNames,0)),"?")) | L16: =IF($D16="","",IF(AND($J16="Received",$K16<>"Yes",LEFT($N16,2)="OK"),"Yes","No")) | N16: =IF($D16="","",IF(AND($F16<>"Classroom",$F16<>"PT"),"TYPE NOT CREDITED",IF($C16="","NO MAKEUP DATE",IF(NOT(ISNUMBER($C16)),"MAKEUP DATE NOT A DATE",IF(OR(AND($G16<>"",NOT(ISNUMBER($G16))),AND($H16<>"",NOT(ISNUMBER($H16)))),"CREDIT NOT A NUMBER",IF(OR(N($G16)<0,N($H16)<0),"NEGATIVE CREDIT",IF(AND($F16="Classroom",N($G16)<=0),"NO MINUTES CREDITED",IF(AND($F16="PT",N($H16)<=0),"NO SESSIONS CREDITED",IF($I16="","NO LINKED EVENT",IF(COUNTIF(nrAT_ID,$I16)=0,"NO SUCH EVENT",IF(INDEX(nrAT_PID,MATCH($I16,nrAT_ID,0))<>$E16,"WRONG CADET",IF(INDEX(nrAT_IsPT,MATCH($I16,nrAT_ID,0))<>IF($F16="PT","Yes","No"),"UNIT MISMATCH","OK"))))))))))))
B17: =IF($D17="","","M"&TEXT(ROW()-5,"000")) | E17: =IF($D17="","",IFERROR(INDEX(rngCadetPIDs,MATCH($D17,rngCadetNames,0)),"?")) | L17: =IF($D17="","",IF(AND($J17="Received",$K17<>"Yes",LEFT($N17,2)="OK"),"Yes","No")) | N17: =IF($D17="","",IF(AND($F17<>"Classroom",$F17<>"PT"),"TYPE NOT CREDITED",IF($C17="","NO MAKEUP DATE",IF(NOT(ISNUMBER($C17)),"MAKEUP DATE NOT A DATE",IF(OR(AND($G17<>"",NOT(ISNUMBER($G17))),AND($H17<>"",NOT(ISNUMBER($H17)))),"CREDIT NOT A NUMBER",IF(OR(N($G17)<0,N($H17)<0),"NEGATIVE CREDIT",IF(AND($F17="Classroom",N($G17)<=0),"NO MINUTES CREDITED",IF(AND($F17="PT",N($H17)<=0),"NO SESSIONS CREDITED",IF($I17="","NO LINKED EVENT",IF(COUNTIF(nrAT_ID,$I17)=0,"NO SUCH EVENT",IF(INDEX(nrAT_PID,MATCH($I17,nrAT_ID,0))<>$E17,"WRONG CADET",IF(INDEX(nrAT_IsPT,MATCH($I17,nrAT_ID,0))<>IF($F17="PT","Yes","No"),"UNIT MISMATCH","OK"))))))))))))
... B505: =IF($D505="","","M"&TEXT(ROW()-5,"000")) | E505: =IF($D505="","",IFERROR(INDEX(rngCadetPIDs,MATCH($D505,rngCadetNames,0)),"?")) | L505: =IF($D505="","",IF(AND($J505="Received",$K505<>"Yes",LEFT($N505,2)="OK"),"Yes","No")) | N505: =IF($D505="","",IF(AND($F505<>"Classroom",$F505<>"PT"),"TYPE NOT CREDITED",IF($C505="","NO MAKEUP DATE",IF(NOT(ISNUMBER($C505)),"MAKEUP DATE NOT A DATE",IF(OR(AND($G505<>"",NOT(ISNUMBER($G505))),AND($H505<>"",NOT(ISNUMBER($H505)))),"CREDIT NOT A NUMBER",IF(OR(N($G505)<0,N($H505)<0),"NEGATIVE CREDIT",IF(AND($F505="Classroom",N($G505)<=0),"NO MINUTES CREDITED",IF(AND($F505="PT",N($H505)<=0),"NO SESSIONS CREDITED",IF($I505="","NO LINKED EVENT",IF(COUNTIF(nrAT_ID,$I505)=0,"NO SUCH EVENT",IF(INDEX(nrAT_PID,MATCH($I505,nrAT_ID,0))<>$E505,"WRONG CADET",IF(INDEX(nrAT_IsPT,MATCH($I505,nrAT_ID,0))<>IF($F505="PT","Yes","No"),"UNIT MISMATCH","OK"))))))))))))

Sheet Skills
B1: =HYPERLINK("#Dashboard!B5","◄ Dashboard")
B4: One row per attempt (firearms scores recorded; Top Gun uses the firearms Score column). Firearms rows: set Course of Fire 1 or 2 — TCOLE requires 70%+ on BOTH. Exhausting max attempts = separation review (300.7). A next-attempt row logged before it is scored does NOT supersede the previous result and does not consume an attempt: Status stays 'Pending' on the new row and the real result keeps driving Skills eligibility until a Pass or Fail is entered. Watch Row Check (last column): a Score outside 0-100 counts toward NOTHING - not the firearms average, not Top Gun and not the both-courses-of-fire graduation gate - until it is corrected.
B5: RecordID | C5: Cadet Name | D5: PID | E5: Category | F5: Max | G5: Mode | H5: Passing | I5: Attempt # | J5: Result | K5: Score | L5: Date | M5: Assessed By | N5: Attempts Used | O5: Status | P5: DismissReview | Q5: Notes | R5: Course of Fire | S5: Row Check
B6: =IF($C6="","",$D6&"-"&$E6&"-"&$I6) | D6: =IF($C6="","",IFERROR(INDEX(rngCadetPIDs,MATCH($C6,rngCadetNames,0)),"?")) | F6: =IF($E6="","",IFERROR(INDEX(rngSM_max,MATCH($E6,rngSM_cat,0)),"")) | G6: =IF($E6="","",IFERROR(INDEX(rngSM_mode,MATCH($E6,rngSM_cat,0)),"")) | H6: =IF($E6="","",IFERROR(INDEX(rngSM_pass,MATCH($E6,rngSM_cat,0)),"")) | N6: =IF($C6="","",MAX(_xlfn.MAXIFS(nrSK_Att,nrSK_PID,$D6,nrSK_Cat,$E6,nrSK_Res,"Pass"),_xlfn.MAXIFS(nrSK_Att,nrSK_PID,$D6,nrSK_Cat,$E6,nrSK_Res,"Fail"))) | O6: =IF($C6="","",IF(AND(MAX(_xlfn.MAXIFS(nrSK_Att,nrSK_PID,$D6,nrSK_Cat,$E6,nrSK_Res,"Pass"),_xlfn.MAXIFS(nrSK_Att,nrSK_PID,$D6,nrSK_Cat,$E6,nrSK_Res,"Fail"))>0,N($I6)<MAX(_xlfn.MAXIFS(nrSK_Att,nrSK_PID,$D6,nrSK_Cat,$E6,nrSK_Res,"Pass"),_xlfn.MAXIFS(nrSK_Att,nrSK_PID,$D6,nrSK_Cat,$E6,nrSK_Res,"Fail"))),"(superseded)",IF(OR($J6="",$J6="Pending"),"Pending",IF($J6="Pass","Qualified",IF(AND($J6="Fail",$N6>=$F6),"FAILED OUT","Needs Remediation"))))) | P6: =IF($C6="","",IF($O6="FAILED OUT","Yes","No")) | S6: =IF($C6="","",IF(AND($K6<>"",NOT(ISNUMBER($K6))),"SCORE NOT A NUMBER",IF(AND(ISNUMBER($K6),OR($K6<0,$K6>100)),"SCORE OUT OF RANGE - this score counts toward nothing",IF(AND($G6="Score",$K6="",$J6<>"",$J6<>"Pending"),"RESULT WITHOUT A SCORE",IF(AND($G6="Pass/Fail",$K6<>""),"SCORE ON A PASS-FAIL CATEGORY - it is ignored",IF(AND($E6="Firearms",$J6<>"",$J6<>"Pending",$R6=""),"FIREARMS ROW WITH NO COURSE OF FIRE","OK"))))))
B7: =IF($C7="","",$D7&"-"&$E7&"-"&$I7) | D7: =IF($C7="","",IFERROR(INDEX(rngCadetPIDs,MATCH($C7,rngCadetNames,0)),"?")) | F7: =IF($E7="","",IFERROR(INDEX(rngSM_max,MATCH($E7,rngSM_cat,0)),"")) | G7: =IF($E7="","",IFERROR(INDEX(rngSM_mode,MATCH($E7,rngSM_cat,0)),"")) | H7: =IF($E7="","",IFERROR(INDEX(rngSM_pass,MATCH($E7,rngSM_cat,0)),"")) | N7: =IF($C7="","",MAX(_xlfn.MAXIFS(nrSK_Att,nrSK_PID,$D7,nrSK_Cat,$E7,nrSK_Res,"Pass"),_xlfn.MAXIFS(nrSK_Att,nrSK_PID,$D7,nrSK_Cat,$E7,nrSK_Res,"Fail"))) | O7: =IF($C7="","",IF(AND(MAX(_xlfn.MAXIFS(nrSK_Att,nrSK_PID,$D7,nrSK_Cat,$E7,nrSK_Res,"Pass"),_xlfn.MAXIFS(nrSK_Att,nrSK_PID,$D7,nrSK_Cat,$E7,nrSK_Res,"Fail"))>0,N($I7)<MAX(_xlfn.MAXIFS(nrSK_Att,nrSK_PID,$D7,nrSK_Cat,$E7,nrSK_Res,"Pass"),_xlfn.MAXIFS(nrSK_Att,nrSK_PID,$D7,nrSK_Cat,$E7,nrSK_Res,"Fail"))),"(superseded)",IF(OR($J7="",$J7="Pending"),"Pending",IF($J7="Pass","Qualified",IF(AND($J7="Fail",$N7>=$F7),"FAILED OUT","Needs Remediation"))))) | P7: =IF($C7="","",IF($O7="FAILED OUT","Yes","No")) | S7: =IF($C7="","",IF(AND($K7<>"",NOT(ISNUMBER($K7))),"SCORE NOT A NUMBER",IF(AND(ISNUMBER($K7),OR($K7<0,$K7>100)),"SCORE OUT OF RANGE - this score counts toward nothing",IF(AND($G7="Score",$K7="",$J7<>"",$J7<>"Pending"),"RESULT WITHOUT A SCORE",IF(AND($G7="Pass/Fail",$K7<>""),"SCORE ON A PASS-FAIL CATEGORY - it is ignored",IF(AND($E7="Firearms",$J7<>"",$J7<>"Pending",$R7=""),"FIREARMS ROW WITH NO COURSE OF FIRE","OK"))))))
B8: =IF($C8="","",$D8&"-"&$E8&"-"&$I8) | D8: =IF($C8="","",IFERROR(INDEX(rngCadetPIDs,MATCH($C8,rngCadetNames,0)),"?")) | F8: =IF($E8="","",IFERROR(INDEX(rngSM_max,MATCH($E8,rngSM_cat,0)),"")) | G8: =IF($E8="","",IFERROR(INDEX(rngSM_mode,MATCH($E8,rngSM_cat,0)),"")) | H8: =IF($E8="","",IFERROR(INDEX(rngSM_pass,MATCH($E8,rngSM_cat,0)),"")) | N8: =IF($C8="","",MAX(_xlfn.MAXIFS(nrSK_Att,nrSK_PID,$D8,nrSK_Cat,$E8,nrSK_Res,"Pass"),_xlfn.MAXIFS(nrSK_Att,nrSK_PID,$D8,nrSK_Cat,$E8,nrSK_Res,"Fail"))) | O8: =IF($C8="","",IF(AND(MAX(_xlfn.MAXIFS(nrSK_Att,nrSK_PID,$D8,nrSK_Cat,$E8,nrSK_Res,"Pass"),_xlfn.MAXIFS(nrSK_Att,nrSK_PID,$D8,nrSK_Cat,$E8,nrSK_Res,"Fail"))>0,N($I8)<MAX(_xlfn.MAXIFS(nrSK_Att,nrSK_PID,$D8,nrSK_Cat,$E8,nrSK_Res,"Pass"),_xlfn.MAXIFS(nrSK_Att,nrSK_PID,$D8,nrSK_Cat,$E8,nrSK_Res,"Fail"))),"(superseded)",IF(OR($J8="",$J8="Pending"),"Pending",IF($J8="Pass","Qualified",IF(AND($J8="Fail",$N8>=$F8),"FAILED OUT","Needs Remediation"))))) | P8: =IF($C8="","",IF($O8="FAILED OUT","Yes","No")) | S8: =IF($C8="","",IF(AND($K8<>"",NOT(ISNUMBER($K8))),"SCORE NOT A NUMBER",IF(AND(ISNUMBER($K8),OR($K8<0,$K8>100)),"SCORE OUT OF RANGE - this score counts toward nothing",IF(AND($G8="Score",$K8="",$J8<>"",$J8<>"Pending"),"RESULT WITHOUT A SCORE",IF(AND($G8="Pass/Fail",$K8<>""),"SCORE ON A PASS-FAIL CATEGORY - it is ignored",IF(AND($E8="Firearms",$J8<>"",$J8<>"Pending",$R8=""),"FIREARMS ROW WITH NO COURSE OF FIRE","OK"))))))
B9: =IF($C9="","",$D9&"-"&$E9&"-"&$I9) | D9: =IF($C9="","",IFERROR(INDEX(rngCadetPIDs,MATCH($C9,rngCadetNames,0)),"?")) | F9: =IF($E9="","",IFERROR(INDEX(rngSM_max,MATCH($E9,rngSM_cat,0)),"")) | G9: =IF($E9="","",IFERROR(INDEX(rngSM_mode,MATCH($E9,rngSM_cat,0)),"")) | H9: =IF($E9="","",IFERROR(INDEX(rngSM_pass,MATCH($E9,rngSM_cat,0)),"")) | N9: =IF($C9="","",MAX(_xlfn.MAXIFS(nrSK_Att,nrSK_PID,$D9,nrSK_Cat,$E9,nrSK_Res,"Pass"),_xlfn.MAXIFS(nrSK_Att,nrSK_PID,$D9,nrSK_Cat,$E9,nrSK_Res,"Fail"))) | O9: =IF($C9="","",IF(AND(MAX(_xlfn.MAXIFS(nrSK_Att,nrSK_PID,$D9,nrSK_Cat,$E9,nrSK_Res,"Pass"),_xlfn.MAXIFS(nrSK_Att,nrSK_PID,$D9,nrSK_Cat,$E9,nrSK_Res,"Fail"))>0,N($I9)<MAX(_xlfn.MAXIFS(nrSK_Att,nrSK_PID,$D9,nrSK_Cat,$E9,nrSK_Res,"Pass"),_xlfn.MAXIFS(nrSK_Att,nrSK_PID,$D9,nrSK_Cat,$E9,nrSK_Res,"Fail"))),"(superseded)",IF(OR($J9="",$J9="Pending"),"Pending",IF($J9="Pass","Qualified",IF(AND($J9="Fail",$N9>=$F9),"FAILED OUT","Needs Remediation"))))) | P9: =IF($C9="","",IF($O9="FAILED OUT","Yes","No")) | S9: =IF($C9="","",IF(AND($K9<>"",NOT(ISNUMBER($K9))),"SCORE NOT A NUMBER",IF(AND(ISNUMBER($K9),OR($K9<0,$K9>100)),"SCORE OUT OF RANGE - this score counts toward nothing",IF(AND($G9="Score",$K9="",$J9<>"",$J9<>"Pending"),"RESULT WITHOUT A SCORE",IF(AND($G9="Pass/Fail",$K9<>""),"SCORE ON A PASS-FAIL CATEGORY - it is ignored",IF(AND($E9="Firearms",$J9<>"",$J9<>"Pending",$R9=""),"FIREARMS ROW WITH NO COURSE OF FIRE","OK"))))))
B10: =IF($C10="","",$D10&"-"&$E10&"-"&$I10) | D10: =IF($C10="","",IFERROR(INDEX(rngCadetPIDs,MATCH($C10,rngCadetNames,0)),"?")) | F10: =IF($E10="","",IFERROR(INDEX(rngSM_max,MATCH($E10,rngSM_cat,0)),"")) | G10: =IF($E10="","",IFERROR(INDEX(rngSM_mode,MATCH($E10,rngSM_cat,0)),"")) | H10: =IF($E10="","",IFERROR(INDEX(rngSM_pass,MATCH($E10,rngSM_cat,0)),"")) | N10: =IF($C10="","",MAX(_xlfn.MAXIFS(nrSK_Att,nrSK_PID,$D10,nrSK_Cat,$E10,nrSK_Res,"Pass"),_xlfn.MAXIFS(nrSK_Att,nrSK_PID,$D10,nrSK_Cat,$E10,nrSK_Res,"Fail"))) | O10: =IF($C10="","",IF(AND(MAX(_xlfn.MAXIFS(nrSK_Att,nrSK_PID,$D10,nrSK_Cat,$E10,nrSK_Res,"Pass"),_xlfn.MAXIFS(nrSK_Att,nrSK_PID,$D10,nrSK_Cat,$E10,nrSK_Res,"Fail"))>0,N($I10)<MAX(_xlfn.MAXIFS(nrSK_Att,nrSK_PID,$D10,nrSK_Cat,$E10,nrSK_Res,"Pass"),_xlfn.MAXIFS(nrSK_Att,nrSK_PID,$D10,nrSK_Cat,$E10,nrSK_Res,"Fail"))),"(superseded)",IF(OR($J10="",$J10="Pending"),"Pending",IF($J10="Pass","Qualified",IF(AND($J10="Fail",$N10>=$F10),"FAILED OUT","Needs Remediation"))))) | P10: =IF($C10="","",IF($O10="FAILED OUT","Yes","No")) | S10: =IF($C10="","",IF(AND($K10<>"",NOT(ISNUMBER($K10))),"SCORE NOT A NUMBER",IF(AND(ISNUMBER($K10),OR($K10<0,$K10>100)),"SCORE OUT OF RANGE - this score counts toward nothing",IF(AND($G10="Score",$K10="",$J10<>"",$J10<>"Pending"),"RESULT WITHOUT A SCORE",IF(AND($G10="Pass/Fail",$K10<>""),"SCORE ON A PASS-FAIL CATEGORY - it is ignored",IF(AND($E10="Firearms",$J10<>"",$J10<>"Pending",$R10=""),"FIREARMS ROW WITH NO COURSE OF FIRE","OK"))))))
B11: =IF($C11="","",$D11&"-"&$E11&"-"&$I11) | D11: =IF($C11="","",IFERROR(INDEX(rngCadetPIDs,MATCH($C11,rngCadetNames,0)),"?")) | F11: =IF($E11="","",IFERROR(INDEX(rngSM_max,MATCH($E11,rngSM_cat,0)),"")) | G11: =IF($E11="","",IFERROR(INDEX(rngSM_mode,MATCH($E11,rngSM_cat,0)),"")) | H11: =IF($E11="","",IFERROR(INDEX(rngSM_pass,MATCH($E11,rngSM_cat,0)),"")) | N11: =IF($C11="","",MAX(_xlfn.MAXIFS(nrSK_Att,nrSK_PID,$D11,nrSK_Cat,$E11,nrSK_Res,"Pass"),_xlfn.MAXIFS(nrSK_Att,nrSK_PID,$D11,nrSK_Cat,$E11,nrSK_Res,"Fail"))) | O11: =IF($C11="","",IF(AND(MAX(_xlfn.MAXIFS(nrSK_Att,nrSK_PID,$D11,nrSK_Cat,$E11,nrSK_Res,"Pass"),_xlfn.MAXIFS(nrSK_Att,nrSK_PID,$D11,nrSK_Cat,$E11,nrSK_Res,"Fail"))>0,N($I11)<MAX(_xlfn.MAXIFS(nrSK_Att,nrSK_PID,$D11,nrSK_Cat,$E11,nrSK_Res,"Pass"),_xlfn.MAXIFS(nrSK_Att,nrSK_PID,$D11,nrSK_Cat,$E11,nrSK_Res,"Fail"))),"(superseded)",IF(OR($J11="",$J11="Pending"),"Pending",IF($J11="Pass","Qualified",IF(AND($J11="Fail",$N11>=$F11),"FAILED OUT","Needs Remediation"))))) | P11: =IF($C11="","",IF($O11="FAILED OUT","Yes","No")) | S11: =IF($C11="","",IF(AND($K11<>"",NOT(ISNUMBER($K11))),"SCORE NOT A NUMBER",IF(AND(ISNUMBER($K11),OR($K11<0,$K11>100)),"SCORE OUT OF RANGE - this score counts toward nothing",IF(AND($G11="Score",$K11="",$J11<>"",$J11<>"Pending"),"RESULT WITHOUT A SCORE",IF(AND($G11="Pass/Fail",$K11<>""),"SCORE ON A PASS-FAIL CATEGORY - it is ignored",IF(AND($E11="Firearms",$J11<>"",$J11<>"Pending",$R11=""),"FIREARMS ROW WITH NO COURSE OF FIRE","OK"))))))
B12: =IF($C12="","",$D12&"-"&$E12&"-"&$I12) | D12: =IF($C12="","",IFERROR(INDEX(rngCadetPIDs,MATCH($C12,rngCadetNames,0)),"?")) | F12: =IF($E12="","",IFERROR(INDEX(rngSM_max,MATCH($E12,rngSM_cat,0)),"")) | G12: =IF($E12="","",IFERROR(INDEX(rngSM_mode,MATCH($E12,rngSM_cat,0)),"")) | H12: =IF($E12="","",IFERROR(INDEX(rngSM_pass,MATCH($E12,rngSM_cat,0)),"")) | N12: =IF($C12="","",MAX(_xlfn.MAXIFS(nrSK_Att,nrSK_PID,$D12,nrSK_Cat,$E12,nrSK_Res,"Pass"),_xlfn.MAXIFS(nrSK_Att,nrSK_PID,$D12,nrSK_Cat,$E12,nrSK_Res,"Fail"))) | O12: =IF($C12="","",IF(AND(MAX(_xlfn.MAXIFS(nrSK_Att,nrSK_PID,$D12,nrSK_Cat,$E12,nrSK_Res,"Pass"),_xlfn.MAXIFS(nrSK_Att,nrSK_PID,$D12,nrSK_Cat,$E12,nrSK_Res,"Fail"))>0,N($I12)<MAX(_xlfn.MAXIFS(nrSK_Att,nrSK_PID,$D12,nrSK_Cat,$E12,nrSK_Res,"Pass"),_xlfn.MAXIFS(nrSK_Att,nrSK_PID,$D12,nrSK_Cat,$E12,nrSK_Res,"Fail"))),"(superseded)",IF(OR($J12="",$J12="Pending"),"Pending",IF($J12="Pass","Qualified",IF(AND($J12="Fail",$N12>=$F12),"FAILED OUT","Needs Remediation"))))) | P12: =IF($C12="","",IF($O12="FAILED OUT","Yes","No")) | S12: =IF($C12="","",IF(AND($K12<>"",NOT(ISNUMBER($K12))),"SCORE NOT A NUMBER",IF(AND(ISNUMBER($K12),OR($K12<0,$K12>100)),"SCORE OUT OF RANGE - this score counts toward nothing",IF(AND($G12="Score",$K12="",$J12<>"",$J12<>"Pending"),"RESULT WITHOUT A SCORE",IF(AND($G12="Pass/Fail",$K12<>""),"SCORE ON A PASS-FAIL CATEGORY - it is ignored",IF(AND($E12="Firearms",$J12<>"",$J12<>"Pending",$R12=""),"FIREARMS ROW WITH NO COURSE OF FIRE","OK"))))))
B13: =IF($C13="","",$D13&"-"&$E13&"-"&$I13) | D13: =IF($C13="","",IFERROR(INDEX(rngCadetPIDs,MATCH($C13,rngCadetNames,0)),"?")) | F13: =IF($E13="","",IFERROR(INDEX(rngSM_max,MATCH($E13,rngSM_cat,0)),"")) | G13: =IF($E13="","",IFERROR(INDEX(rngSM_mode,MATCH($E13,rngSM_cat,0)),"")) | H13: =IF($E13="","",IFERROR(INDEX(rngSM_pass,MATCH($E13,rngSM_cat,0)),"")) | N13: =IF($C13="","",MAX(_xlfn.MAXIFS(nrSK_Att,nrSK_PID,$D13,nrSK_Cat,$E13,nrSK_Res,"Pass"),_xlfn.MAXIFS(nrSK_Att,nrSK_PID,$D13,nrSK_Cat,$E13,nrSK_Res,"Fail"))) | O13: =IF($C13="","",IF(AND(MAX(_xlfn.MAXIFS(nrSK_Att,nrSK_PID,$D13,nrSK_Cat,$E13,nrSK_Res,"Pass"),_xlfn.MAXIFS(nrSK_Att,nrSK_PID,$D13,nrSK_Cat,$E13,nrSK_Res,"Fail"))>0,N($I13)<MAX(_xlfn.MAXIFS(nrSK_Att,nrSK_PID,$D13,nrSK_Cat,$E13,nrSK_Res,"Pass"),_xlfn.MAXIFS(nrSK_Att,nrSK_PID,$D13,nrSK_Cat,$E13,nrSK_Res,"Fail"))),"(superseded)",IF(OR($J13="",$J13="Pending"),"Pending",IF($J13="Pass","Qualified",IF(AND($J13="Fail",$N13>=$F13),"FAILED OUT","Needs Remediation"))))) | P13: =IF($C13="","",IF($O13="FAILED OUT","Yes","No")) | S13: =IF($C13="","",IF(AND($K13<>"",NOT(ISNUMBER($K13))),"SCORE NOT A NUMBER",IF(AND(ISNUMBER($K13),OR($K13<0,$K13>100)),"SCORE OUT OF RANGE - this score counts toward nothing",IF(AND($G13="Score",$K13="",$J13<>"",$J13<>"Pending"),"RESULT WITHOUT A SCORE",IF(AND($G13="Pass/Fail",$K13<>""),"SCORE ON A PASS-FAIL CATEGORY - it is ignored",IF(AND($E13="Firearms",$J13<>"",$J13<>"Pending",$R13=""),"FIREARMS ROW WITH NO COURSE OF FIRE","OK"))))))
B14: =IF($C14="","",$D14&"-"&$E14&"-"&$I14) | D14: =IF($C14="","",IFERROR(INDEX(rngCadetPIDs,MATCH($C14,rngCadetNames,0)),"?")) | F14: =IF($E14="","",IFERROR(INDEX(rngSM_max,MATCH($E14,rngSM_cat,0)),"")) | G14: =IF($E14="","",IFERROR(INDEX(rngSM_mode,MATCH($E14,rngSM_cat,0)),"")) | H14: =IF($E14="","",IFERROR(INDEX(rngSM_pass,MATCH($E14,rngSM_cat,0)),"")) | N14: =IF($C14="","",MAX(_xlfn.MAXIFS(nrSK_Att,nrSK_PID,$D14,nrSK_Cat,$E14,nrSK_Res,"Pass"),_xlfn.MAXIFS(nrSK_Att,nrSK_PID,$D14,nrSK_Cat,$E14,nrSK_Res,"Fail"))) | O14: =IF($C14="","",IF(AND(MAX(_xlfn.MAXIFS(nrSK_Att,nrSK_PID,$D14,nrSK_Cat,$E14,nrSK_Res,"Pass"),_xlfn.MAXIFS(nrSK_Att,nrSK_PID,$D14,nrSK_Cat,$E14,nrSK_Res,"Fail"))>0,N($I14)<MAX(_xlfn.MAXIFS(nrSK_Att,nrSK_PID,$D14,nrSK_Cat,$E14,nrSK_Res,"Pass"),_xlfn.MAXIFS(nrSK_Att,nrSK_PID,$D14,nrSK_Cat,$E14,nrSK_Res,"Fail"))),"(superseded)",IF(OR($J14="",$J14="Pending"),"Pending",IF($J14="Pass","Qualified",IF(AND($J14="Fail",$N14>=$F14),"FAILED OUT","Needs Remediation"))))) | P14: =IF($C14="","",IF($O14="FAILED OUT","Yes","No")) | S14: =IF($C14="","",IF(AND($K14<>"",NOT(ISNUMBER($K14))),"SCORE NOT A NUMBER",IF(AND(ISNUMBER($K14),OR($K14<0,$K14>100)),"SCORE OUT OF RANGE - this score counts toward nothing",IF(AND($G14="Score",$K14="",$J14<>"",$J14<>"Pending"),"RESULT WITHOUT A SCORE",IF(AND($G14="Pass/Fail",$K14<>""),"SCORE ON A PASS-FAIL CATEGORY - it is ignored",IF(AND($E14="Firearms",$J14<>"",$J14<>"Pending",$R14=""),"FIREARMS ROW WITH NO COURSE OF FIRE","OK"))))))
B15: =IF($C15="","",$D15&"-"&$E15&"-"&$I15) | D15: =IF($C15="","",IFERROR(INDEX(rngCadetPIDs,MATCH($C15,rngCadetNames,0)),"?")) | F15: =IF($E15="","",IFERROR(INDEX(rngSM_max,MATCH($E15,rngSM_cat,0)),"")) | G15: =IF($E15="","",IFERROR(INDEX(rngSM_mode,MATCH($E15,rngSM_cat,0)),"")) | H15: =IF($E15="","",IFERROR(INDEX(rngSM_pass,MATCH($E15,rngSM_cat,0)),"")) | N15: =IF($C15="","",MAX(_xlfn.MAXIFS(nrSK_Att,nrSK_PID,$D15,nrSK_Cat,$E15,nrSK_Res,"Pass"),_xlfn.MAXIFS(nrSK_Att,nrSK_PID,$D15,nrSK_Cat,$E15,nrSK_Res,"Fail"))) | O15: =IF($C15="","",IF(AND(MAX(_xlfn.MAXIFS(nrSK_Att,nrSK_PID,$D15,nrSK_Cat,$E15,nrSK_Res,"Pass"),_xlfn.MAXIFS(nrSK_Att,nrSK_PID,$D15,nrSK_Cat,$E15,nrSK_Res,"Fail"))>0,N($I15)<MAX(_xlfn.MAXIFS(nrSK_Att,nrSK_PID,$D15,nrSK_Cat,$E15,nrSK_Res,"Pass"),_xlfn.MAXIFS(nrSK_Att,nrSK_PID,$D15,nrSK_Cat,$E15,nrSK_Res,"Fail"))),"(superseded)",IF(OR($J15="",$J15="Pending"),"Pending",IF($J15="Pass","Qualified",IF(AND($J15="Fail",$N15>=$F15),"FAILED OUT","Needs Remediation"))))) | P15: =IF($C15="","",IF($O15="FAILED OUT","Yes","No")) | S15: =IF($C15="","",IF(AND($K15<>"",NOT(ISNUMBER($K15))),"SCORE NOT A NUMBER",IF(AND(ISNUMBER($K15),OR($K15<0,$K15>100)),"SCORE OUT OF RANGE - this score counts toward nothing",IF(AND($G15="Score",$K15="",$J15<>"",$J15<>"Pending"),"RESULT WITHOUT A SCORE",IF(AND($G15="Pass/Fail",$K15<>""),"SCORE ON A PASS-FAIL CATEGORY - it is ignored",IF(AND($E15="Firearms",$J15<>"",$J15<>"Pending",$R15=""),"FIREARMS ROW WITH NO COURSE OF FIRE","OK"))))))
B16: =IF($C16="","",$D16&"-"&$E16&"-"&$I16) | D16: =IF($C16="","",IFERROR(INDEX(rngCadetPIDs,MATCH($C16,rngCadetNames,0)),"?")) | F16: =IF($E16="","",IFERROR(INDEX(rngSM_max,MATCH($E16,rngSM_cat,0)),"")) | G16: =IF($E16="","",IFERROR(INDEX(rngSM_mode,MATCH($E16,rngSM_cat,0)),"")) | H16: =IF($E16="","",IFERROR(INDEX(rngSM_pass,MATCH($E16,rngSM_cat,0)),"")) | N16: =IF($C16="","",MAX(_xlfn.MAXIFS(nrSK_Att,nrSK_PID,$D16,nrSK_Cat,$E16,nrSK_Res,"Pass"),_xlfn.MAXIFS(nrSK_Att,nrSK_PID,$D16,nrSK_Cat,$E16,nrSK_Res,"Fail"))) | O16: =IF($C16="","",IF(AND(MAX(_xlfn.MAXIFS(nrSK_Att,nrSK_PID,$D16,nrSK_Cat,$E16,nrSK_Res,"Pass"),_xlfn.MAXIFS(nrSK_Att,nrSK_PID,$D16,nrSK_Cat,$E16,nrSK_Res,"Fail"))>0,N($I16)<MAX(_xlfn.MAXIFS(nrSK_Att,nrSK_PID,$D16,nrSK_Cat,$E16,nrSK_Res,"Pass"),_xlfn.MAXIFS(nrSK_Att,nrSK_PID,$D16,nrSK_Cat,$E16,nrSK_Res,"Fail"))),"(superseded)",IF(OR($J16="",$J16="Pending"),"Pending",IF($J16="Pass","Qualified",IF(AND($J16="Fail",$N16>=$F16),"FAILED OUT","Needs Remediation"))))) | P16: =IF($C16="","",IF($O16="FAILED OUT","Yes","No")) | S16: =IF($C16="","",IF(AND($K16<>"",NOT(ISNUMBER($K16))),"SCORE NOT A NUMBER",IF(AND(ISNUMBER($K16),OR($K16<0,$K16>100)),"SCORE OUT OF RANGE - this score counts toward nothing",IF(AND($G16="Score",$K16="",$J16<>"",$J16<>"Pending"),"RESULT WITHOUT A SCORE",IF(AND($G16="Pass/Fail",$K16<>""),"SCORE ON A PASS-FAIL CATEGORY - it is ignored",IF(AND($E16="Firearms",$J16<>"",$J16<>"Pending",$R16=""),"FIREARMS ROW WITH NO COURSE OF FIRE","OK"))))))
B17: =IF($C17="","",$D17&"-"&$E17&"-"&$I17) | D17: =IF($C17="","",IFERROR(INDEX(rngCadetPIDs,MATCH($C17,rngCadetNames,0)),"?")) | F17: =IF($E17="","",IFERROR(INDEX(rngSM_max,MATCH($E17,rngSM_cat,0)),"")) | G17: =IF($E17="","",IFERROR(INDEX(rngSM_mode,MATCH($E17,rngSM_cat,0)),"")) | H17: =IF($E17="","",IFERROR(INDEX(rngSM_pass,MATCH($E17,rngSM_cat,0)),"")) | N17: =IF($C17="","",MAX(_xlfn.MAXIFS(nrSK_Att,nrSK_PID,$D17,nrSK_Cat,$E17,nrSK_Res,"Pass"),_xlfn.MAXIFS(nrSK_Att,nrSK_PID,$D17,nrSK_Cat,$E17,nrSK_Res,"Fail"))) | O17: =IF($C17="","",IF(AND(MAX(_xlfn.MAXIFS(nrSK_Att,nrSK_PID,$D17,nrSK_Cat,$E17,nrSK_Res,"Pass"),_xlfn.MAXIFS(nrSK_Att,nrSK_PID,$D17,nrSK_Cat,$E17,nrSK_Res,"Fail"))>0,N($I17)<MAX(_xlfn.MAXIFS(nrSK_Att,nrSK_PID,$D17,nrSK_Cat,$E17,nrSK_Res,"Pass"),_xlfn.MAXIFS(nrSK_Att,nrSK_PID,$D17,nrSK_Cat,$E17,nrSK_Res,"Fail"))),"(superseded)",IF(OR($J17="",$J17="Pending"),"Pending",IF($J17="Pass","Qualified",IF(AND($J17="Fail",$N17>=$F17),"FAILED OUT","Needs Remediation"))))) | P17: =IF($C17="","",IF($O17="FAILED OUT","Yes","No")) | S17: =IF($C17="","",IF(AND($K17<>"",NOT(ISNUMBER($K17))),"SCORE NOT A NUMBER",IF(AND(ISNUMBER($K17),OR($K17<0,$K17>100)),"SCORE OUT OF RANGE - this score counts toward nothing",IF(AND($G17="Score",$K17="",$J17<>"",$J17<>"Pending"),"RESULT WITHOUT A SCORE",IF(AND($G17="Pass/Fail",$K17<>""),"SCORE ON A PASS-FAIL CATEGORY - it is ignored",IF(AND($E17="Firearms",$J17<>"",$J17<>"Pending",$R17=""),"FIREARMS ROW WITH NO COURSE OF FIRE","OK"))))))
... B605: =IF($C605="","",$D605&"-"&$E605&"-"&$I605) | D605: =IF($C605="","",IFERROR(INDEX(rngCadetPIDs,MATCH($C605,rngCadetNames,0)),"?")) | F605: =IF($E605="","",IFERROR(INDEX(rngSM_max,MATCH($E605,rngSM_cat,0)),"")) | G605: =IF($E605="","",IFERROR(INDEX(rngSM_mode,MATCH($E605,rngSM_cat,0)),"")) | H605: =IF($E605="","",IFERROR(INDEX(rngSM_pass,MATCH($E605,rngSM_cat,0)),"")) | N605: =IF($C605="","",MAX(_xlfn.MAXIFS(nrSK_Att,nrSK_PID,$D605,nrSK_Cat,$E605,nrSK_Res,"Pass"),_xlfn.MAXIFS(nrSK_Att,nrSK_PID,$D605,nrSK_Cat,$E605,nrSK_Res,"Fail"))) | O605: =IF($C605="","",IF(AND(MAX(_xlfn.MAXIFS(nrSK_Att,nrSK_PID,$D605,nrSK_Cat,$E605,nrSK_Res,"Pass"),_xlfn.MAXIFS(nrSK_Att,nrSK_PID,$D605,nrSK_Cat,$E605,nrSK_Res,"Fail"))>0,N($I605)<MAX(_xlfn.MAXIFS(nrSK_Att,nrSK_PID,$D605,nrSK_Cat,$E605,nrSK_Res,"Pass"),_xlfn.MAXIFS(nrSK_Att,nrSK_PID,$D605,nrSK_Cat,$E605,nrSK_Res,"Fail"))),"(superseded)",IF(OR($J605="",$J605="Pending"),"Pending",IF($J605="Pass","Qualified",IF(AND($J605="Fail",$N605>=$F605),"FAILED OUT","Needs Remediation"))))) | P605: =IF($C605="","",IF($O605="FAILED OUT","Yes","No")) | S605: =IF($C605="","",IF(AND($K605<>"",NOT(ISNUMBER($K605))),"SCORE NOT A NUMBER",IF(AND(ISNUMBER($K605),OR($K605<0,$K605>100)),"SCORE OUT OF RANGE - this score counts toward nothing",IF(AND($G605="Score",$K605="",$J605<>"",$J605<>"Pending"),"RESULT WITHOUT A SCORE",IF(AND($G605="Pass/Fail",$K605<>""),"SCORE ON A PASS-FAIL CATEGORY - it is ignored",IF(AND($E605="Firearms",$J605<>"",$J605<>"Pending",$R605=""),"FIREARMS ROW WITH NO COURSE OF FIRE","OK"))))))

Sheet SkillsCheck
B1: =HYPERLINK("#Dashboard!B5","◄ Dashboard")
B4: One Pass/Fail per skills training, per cadet - your call, not the attempt log's. EVERY skill must read Pass before a cadet can graduate: a Fail blocks and names that skill in Blocking Issues, and a skill left BLANK blocks too (it counts under 'Not Assessed'). Nothing here is automatic - missed skills time does not mark anything, because in practice parts of skills training can be made up - so the block lifts the moment you mark the skill Pass. A column only counts if its category exists on SkillsMaster; the spare columns are ignored until you name them there.
B5: PID | C5: Cadet Name | D5: Firearms | E5: Driving | F5: MOA | G5: OC | H5: SFST | I5: Medical | J5: =IF(SkillsMaster!$B$12="","(spare)",SkillsMaster!$B$12) | K5: =IF(SkillsMaster!$B$13="","(spare)",SkillsMaster!$B$13) | L5: =IF(SkillsMaster!$B$14="","(spare)",SkillsMaster!$B$14) | M5: =IF(SkillsMaster!$B$15="","(spare)",SkillsMaster!$B$15) | N5: Failed | O5: Not Assessed | P5: Skills P/F OK? | Q5: Cadet Status
B6: =IF(Cadets!$B6="","",Cadets!$B6) | C6: =IF(Cadets!$B6="","",Cadets!$F6) | N6: =IF($C6="","",_xlfn.TEXTJOIN(", ",TRUE,IF($D6="Fail",SkillsMaster!$B$6,""),IF($E6="Fail",SkillsMaster!$B$7,""),IF($F6="Fail",SkillsMaster!$B$8,""),IF($G6="Fail",SkillsMaster!$B$9,""),IF($H6="Fail",SkillsMaster!$B$10,""),IF($I6="Fail",SkillsMaster!$B$11,""),IF($J6="Fail",SkillsMaster!$B$12,""),IF($K6="Fail",SkillsMaster!$B$13,""),IF($L6="Fail",SkillsMaster!$B$14,""),IF($M6="Fail",SkillsMaster!$B$15,""))) | O6: =IF($C6="","",IF(SkillsMaster!$B$6="",0,IF($D6="",1,0))+IF(SkillsMaster!$B$7="",0,IF($E6="",1,0))+IF(SkillsMaster!$B$8="",0,IF($F6="",1,0))+IF(SkillsMaster!$B$9="",0,IF($G6="",1,0))+IF(SkillsMaster!$B$10="",0,IF($H6="",1,0))+IF(SkillsMaster!$B$11="",0,IF($I6="",1,0))+IF(SkillsMaster!$B$12="",0,IF($J6="",1,0))+IF(SkillsMaster!$B$13="",0,IF($K6="",1,0))+IF(SkillsMaster!$B$14="",0,IF($L6="",1,0))+IF(SkillsMaster!$B$15="",0,IF($M6="",1,0))) | P6: =IF($C6="","",IF(AND($N6="",$O6=0),"Yes","No")) | Q6: =IF(Cadets!$B6="","",Cadets!$I6)
B7: =IF(Cadets!$B7="","",Cadets!$B7) | C7: =IF(Cadets!$B7="","",Cadets!$F7) | N7: =IF($C7="","",_xlfn.TEXTJOIN(", ",TRUE,IF($D7="Fail",SkillsMaster!$B$6,""),IF($E7="Fail",SkillsMaster!$B$7,""),IF($F7="Fail",SkillsMaster!$B$8,""),IF($G7="Fail",SkillsMaster!$B$9,""),IF($H7="Fail",SkillsMaster!$B$10,""),IF($I7="Fail",SkillsMaster!$B$11,""),IF($J7="Fail",SkillsMaster!$B$12,""),IF($K7="Fail",SkillsMaster!$B$13,""),IF($L7="Fail",SkillsMaster!$B$14,""),IF($M7="Fail",SkillsMaster!$B$15,""))) | O7: =IF($C7="","",IF(SkillsMaster!$B$6="",0,IF($D7="",1,0))+IF(SkillsMaster!$B$7="",0,IF($E7="",1,0))+IF(SkillsMaster!$B$8="",0,IF($F7="",1,0))+IF(SkillsMaster!$B$9="",0,IF($G7="",1,0))+IF(SkillsMaster!$B$10="",0,IF($H7="",1,0))+IF(SkillsMaster!$B$11="",0,IF($I7="",1,0))+IF(SkillsMaster!$B$12="",0,IF($J7="",1,0))+IF(SkillsMaster!$B$13="",0,IF($K7="",1,0))+IF(SkillsMaster!$B$14="",0,IF($L7="",1,0))+IF(SkillsMaster!$B$15="",0,IF($M7="",1,0))) | P7: =IF($C7="","",IF(AND($N7="",$O7=0),"Yes","No")) | Q7: =IF(Cadets!$B7="","",Cadets!$I7)
B8: =IF(Cadets!$B8="","",Cadets!$B8) | C8: =IF(Cadets!$B8="","",Cadets!$F8) | N8: =IF($C8="","",_xlfn.TEXTJOIN(", ",TRUE,IF($D8="Fail",SkillsMaster!$B$6,""),IF($E8="Fail",SkillsMaster!$B$7,""),IF($F8="Fail",SkillsMaster!$B$8,""),IF($G8="Fail",SkillsMaster!$B$9,""),IF($H8="Fail",SkillsMaster!$B$10,""),IF($I8="Fail",SkillsMaster!$B$11,""),IF($J8="Fail",SkillsMaster!$B$12,""),IF($K8="Fail",SkillsMaster!$B$13,""),IF($L8="Fail",SkillsMaster!$B$14,""),IF($M8="Fail",SkillsMaster!$B$15,""))) | O8: =IF($C8="","",IF(SkillsMaster!$B$6="",0,IF($D8="",1,0))+IF(SkillsMaster!$B$7="",0,IF($E8="",1,0))+IF(SkillsMaster!$B$8="",0,IF($F8="",1,0))+IF(SkillsMaster!$B$9="",0,IF($G8="",1,0))+IF(SkillsMaster!$B$10="",0,IF($H8="",1,0))+IF(SkillsMaster!$B$11="",0,IF($I8="",1,0))+IF(SkillsMaster!$B$12="",0,IF($J8="",1,0))+IF(SkillsMaster!$B$13="",0,IF($K8="",1,0))+IF(SkillsMaster!$B$14="",0,IF($L8="",1,0))+IF(SkillsMaster!$B$15="",0,IF($M8="",1,0))) | P8: =IF($C8="","",IF(AND($N8="",$O8=0),"Yes","No")) | Q8: =IF(Cadets!$B8="","",Cadets!$I8)
B9: =IF(Cadets!$B9="","",Cadets!$B9) | C9: =IF(Cadets!$B9="","",Cadets!$F9) | N9: =IF($C9="","",_xlfn.TEXTJOIN(", ",TRUE,IF($D9="Fail",SkillsMaster!$B$6,""),IF($E9="Fail",SkillsMaster!$B$7,""),IF($F9="Fail",SkillsMaster!$B$8,""),IF($G9="Fail",SkillsMaster!$B$9,""),IF($H9="Fail",SkillsMaster!$B$10,""),IF($I9="Fail",SkillsMaster!$B$11,""),IF($J9="Fail",SkillsMaster!$B$12,""),IF($K9="Fail",SkillsMaster!$B$13,""),IF($L9="Fail",SkillsMaster!$B$14,""),IF($M9="Fail",SkillsMaster!$B$15,""))) | O9: =IF($C9="","",IF(SkillsMaster!$B$6="",0,IF($D9="",1,0))+IF(SkillsMaster!$B$7="",0,IF($E9="",1,0))+IF(SkillsMaster!$B$8="",0,IF($F9="",1,0))+IF(SkillsMaster!$B$9="",0,IF($G9="",1,0))+IF(SkillsMaster!$B$10="",0,IF($H9="",1,0))+IF(SkillsMaster!$B$11="",0,IF($I9="",1,0))+IF(SkillsMaster!$B$12="",0,IF($J9="",1,0))+IF(SkillsMaster!$B$13="",0,IF($K9="",1,0))+IF(SkillsMaster!$B$14="",0,IF($L9="",1,0))+IF(SkillsMaster!$B$15="",0,IF($M9="",1,0))) | P9: =IF($C9="","",IF(AND($N9="",$O9=0),"Yes","No")) | Q9: =IF(Cadets!$B9="","",Cadets!$I9)
B10: =IF(Cadets!$B10="","",Cadets!$B10) | C10: =IF(Cadets!$B10="","",Cadets!$F10) | N10: =IF($C10="","",_xlfn.TEXTJOIN(", ",TRUE,IF($D10="Fail",SkillsMaster!$B$6,""),IF($E10="Fail",SkillsMaster!$B$7,""),IF($F10="Fail",SkillsMaster!$B$8,""),IF($G10="Fail",SkillsMaster!$B$9,""),IF($H10="Fail",SkillsMaster!$B$10,""),IF($I10="Fail",SkillsMaster!$B$11,""),IF($J10="Fail",SkillsMaster!$B$12,""),IF($K10="Fail",SkillsMaster!$B$13,""),IF($L10="Fail",SkillsMaster!$B$14,""),IF($M10="Fail",SkillsMaster!$B$15,""))) | O10: =IF($C10="","",IF(SkillsMaster!$B$6="",0,IF($D10="",1,0))+IF(SkillsMaster!$B$7="",0,IF($E10="",1,0))+IF(SkillsMaster!$B$8="",0,IF($F10="",1,0))+IF(SkillsMaster!$B$9="",0,IF($G10="",1,0))+IF(SkillsMaster!$B$10="",0,IF($H10="",1,0))+IF(SkillsMaster!$B$11="",0,IF($I10="",1,0))+IF(SkillsMaster!$B$12="",0,IF($J10="",1,0))+IF(SkillsMaster!$B$13="",0,IF($K10="",1,0))+IF(SkillsMaster!$B$14="",0,IF($L10="",1,0))+IF(SkillsMaster!$B$15="",0,IF($M10="",1,0))) | P10: =IF($C10="","",IF(AND($N10="",$O10=0),"Yes","No")) | Q10: =IF(Cadets!$B10="","",Cadets!$I10)
B11: =IF(Cadets!$B11="","",Cadets!$B11) | C11: =IF(Cadets!$B11="","",Cadets!$F11) | N11: =IF($C11="","",_xlfn.TEXTJOIN(", ",TRUE,IF($D11="Fail",SkillsMaster!$B$6,""),IF($E11="Fail",SkillsMaster!$B$7,""),IF($F11="Fail",SkillsMaster!$B$8,""),IF($G11="Fail",SkillsMaster!$B$9,""),IF($H11="Fail",SkillsMaster!$B$10,""),IF($I11="Fail",SkillsMaster!$B$11,""),IF($J11="Fail",SkillsMaster!$B$12,""),IF($K11="Fail",SkillsMaster!$B$13,""),IF($L11="Fail",SkillsMaster!$B$14,""),IF($M11="Fail",SkillsMaster!$B$15,""))) | O11: =IF($C11="","",IF(SkillsMaster!$B$6="",0,IF($D11="",1,0))+IF(SkillsMaster!$B$7="",0,IF($E11="",1,0))+IF(SkillsMaster!$B$8="",0,IF($F11="",1,0))+IF(SkillsMaster!$B$9="",0,IF($G11="",1,0))+IF(SkillsMaster!$B$10="",0,IF($H11="",1,0))+IF(SkillsMaster!$B$11="",0,IF($I11="",1,0))+IF(SkillsMaster!$B$12="",0,IF($J11="",1,0))+IF(SkillsMaster!$B$13="",0,IF($K11="",1,0))+IF(SkillsMaster!$B$14="",0,IF($L11="",1,0))+IF(SkillsMaster!$B$15="",0,IF($M11="",1,0))) | P11: =IF($C11="","",IF(AND($N11="",$O11=0),"Yes","No")) | Q11: =IF(Cadets!$B11="","",Cadets!$I11)
B12: =IF(Cadets!$B12="","",Cadets!$B12) | C12: =IF(Cadets!$B12="","",Cadets!$F12) | N12: =IF($C12="","",_xlfn.TEXTJOIN(", ",TRUE,IF($D12="Fail",SkillsMaster!$B$6,""),IF($E12="Fail",SkillsMaster!$B$7,""),IF($F12="Fail",SkillsMaster!$B$8,""),IF($G12="Fail",SkillsMaster!$B$9,""),IF($H12="Fail",SkillsMaster!$B$10,""),IF($I12="Fail",SkillsMaster!$B$11,""),IF($J12="Fail",SkillsMaster!$B$12,""),IF($K12="Fail",SkillsMaster!$B$13,""),IF($L12="Fail",SkillsMaster!$B$14,""),IF($M12="Fail",SkillsMaster!$B$15,""))) | O12: =IF($C12="","",IF(SkillsMaster!$B$6="",0,IF($D12="",1,0))+IF(SkillsMaster!$B$7="",0,IF($E12="",1,0))+IF(SkillsMaster!$B$8="",0,IF($F12="",1,0))+IF(SkillsMaster!$B$9="",0,IF($G12="",1,0))+IF(SkillsMaster!$B$10="",0,IF($H12="",1,0))+IF(SkillsMaster!$B$11="",0,IF($I12="",1,0))+IF(SkillsMaster!$B$12="",0,IF($J12="",1,0))+IF(SkillsMaster!$B$13="",0,IF($K12="",1,0))+IF(SkillsMaster!$B$14="",0,IF($L12="",1,0))+IF(SkillsMaster!$B$15="",0,IF($M12="",1,0))) | P12: =IF($C12="","",IF(AND($N12="",$O12=0),"Yes","No")) | Q12: =IF(Cadets!$B12="","",Cadets!$I12)
B13: =IF(Cadets!$B13="","",Cadets!$B13) | C13: =IF(Cadets!$B13="","",Cadets!$F13) | N13: =IF($C13="","",_xlfn.TEXTJOIN(", ",TRUE,IF($D13="Fail",SkillsMaster!$B$6,""),IF($E13="Fail",SkillsMaster!$B$7,""),IF($F13="Fail",SkillsMaster!$B$8,""),IF($G13="Fail",SkillsMaster!$B$9,""),IF($H13="Fail",SkillsMaster!$B$10,""),IF($I13="Fail",SkillsMaster!$B$11,""),IF($J13="Fail",SkillsMaster!$B$12,""),IF($K13="Fail",SkillsMaster!$B$13,""),IF($L13="Fail",SkillsMaster!$B$14,""),IF($M13="Fail",SkillsMaster!$B$15,""))) | O13: =IF($C13="","",IF(SkillsMaster!$B$6="",0,IF($D13="",1,0))+IF(SkillsMaster!$B$7="",0,IF($E13="",1,0))+IF(SkillsMaster!$B$8="",0,IF($F13="",1,0))+IF(SkillsMaster!$B$9="",0,IF($G13="",1,0))+IF(SkillsMaster!$B$10="",0,IF($H13="",1,0))+IF(SkillsMaster!$B$11="",0,IF($I13="",1,0))+IF(SkillsMaster!$B$12="",0,IF($J13="",1,0))+IF(SkillsMaster!$B$13="",0,IF($K13="",1,0))+IF(SkillsMaster!$B$14="",0,IF($L13="",1,0))+IF(SkillsMaster!$B$15="",0,IF($M13="",1,0))) | P13: =IF($C13="","",IF(AND($N13="",$O13=0),"Yes","No")) | Q13: =IF(Cadets!$B13="","",Cadets!$I13)
B14: =IF(Cadets!$B14="","",Cadets!$B14) | C14: =IF(Cadets!$B14="","",Cadets!$F14) | N14: =IF($C14="","",_xlfn.TEXTJOIN(", ",TRUE,IF($D14="Fail",SkillsMaster!$B$6,""),IF($E14="Fail",SkillsMaster!$B$7,""),IF($F14="Fail",SkillsMaster!$B$8,""),IF($G14="Fail",SkillsMaster!$B$9,""),IF($H14="Fail",SkillsMaster!$B$10,""),IF($I14="Fail",SkillsMaster!$B$11,""),IF($J14="Fail",SkillsMaster!$B$12,""),IF($K14="Fail",SkillsMaster!$B$13,""),IF($L14="Fail",SkillsMaster!$B$14,""),IF($M14="Fail",SkillsMaster!$B$15,""))) | O14: =IF($C14="","",IF(SkillsMaster!$B$6="",0,IF($D14="",1,0))+IF(SkillsMaster!$B$7="",0,IF($E14="",1,0))+IF(SkillsMaster!$B$8="",0,IF($F14="",1,0))+IF(SkillsMaster!$B$9="",0,IF($G14="",1,0))+IF(SkillsMaster!$B$10="",0,IF($H14="",1,0))+IF(SkillsMaster!$B$11="",0,IF($I14="",1,0))+IF(SkillsMaster!$B$12="",0,IF($J14="",1,0))+IF(SkillsMaster!$B$13="",0,IF($K14="",1,0))+IF(SkillsMaster!$B$14="",0,IF($L14="",1,0))+IF(SkillsMaster!$B$15="",0,IF($M14="",1,0))) | P14: =IF($C14="","",IF(AND($N14="",$O14=0),"Yes","No")) | Q14: =IF(Cadets!$B14="","",Cadets!$I14)
B15: =IF(Cadets!$B15="","",Cadets!$B15) | C15: =IF(Cadets!$B15="","",Cadets!$F15) | N15: =IF($C15="","",_xlfn.TEXTJOIN(", ",TRUE,IF($D15="Fail",SkillsMaster!$B$6,""),IF($E15="Fail",SkillsMaster!$B$7,""),IF($F15="Fail",SkillsMaster!$B$8,""),IF($G15="Fail",SkillsMaster!$B$9,""),IF($H15="Fail",SkillsMaster!$B$10,""),IF($I15="Fail",SkillsMaster!$B$11,""),IF($J15="Fail",SkillsMaster!$B$12,""),IF($K15="Fail",SkillsMaster!$B$13,""),IF($L15="Fail",SkillsMaster!$B$14,""),IF($M15="Fail",SkillsMaster!$B$15,""))) | O15: =IF($C15="","",IF(SkillsMaster!$B$6="",0,IF($D15="",1,0))+IF(SkillsMaster!$B$7="",0,IF($E15="",1,0))+IF(SkillsMaster!$B$8="",0,IF($F15="",1,0))+IF(SkillsMaster!$B$9="",0,IF($G15="",1,0))+IF(SkillsMaster!$B$10="",0,IF($H15="",1,0))+IF(SkillsMaster!$B$11="",0,IF($I15="",1,0))+IF(SkillsMaster!$B$12="",0,IF($J15="",1,0))+IF(SkillsMaster!$B$13="",0,IF($K15="",1,0))+IF(SkillsMaster!$B$14="",0,IF($L15="",1,0))+IF(SkillsMaster!$B$15="",0,IF($M15="",1,0))) | P15: =IF($C15="","",IF(AND($N15="",$O15=0),"Yes","No")) | Q15: =IF(Cadets!$B15="","",Cadets!$I15)
B16: =IF(Cadets!$B16="","",Cadets!$B16) | C16: =IF(Cadets!$B16="","",Cadets!$F16) | N16: =IF($C16="","",_xlfn.TEXTJOIN(", ",TRUE,IF($D16="Fail",SkillsMaster!$B$6,""),IF($E16="Fail",SkillsMaster!$B$7,""),IF($F16="Fail",SkillsMaster!$B$8,""),IF($G16="Fail",SkillsMaster!$B$9,""),IF($H16="Fail",SkillsMaster!$B$10,""),IF($I16="Fail",SkillsMaster!$B$11,""),IF($J16="Fail",SkillsMaster!$B$12,""),IF($K16="Fail",SkillsMaster!$B$13,""),IF($L16="Fail",SkillsMaster!$B$14,""),IF($M16="Fail",SkillsMaster!$B$15,""))) | O16: =IF($C16="","",IF(SkillsMaster!$B$6="",0,IF($D16="",1,0))+IF(SkillsMaster!$B$7="",0,IF($E16="",1,0))+IF(SkillsMaster!$B$8="",0,IF($F16="",1,0))+IF(SkillsMaster!$B$9="",0,IF($G16="",1,0))+IF(SkillsMaster!$B$10="",0,IF($H16="",1,0))+IF(SkillsMaster!$B$11="",0,IF($I16="",1,0))+IF(SkillsMaster!$B$12="",0,IF($J16="",1,0))+IF(SkillsMaster!$B$13="",0,IF($K16="",1,0))+IF(SkillsMaster!$B$14="",0,IF($L16="",1,0))+IF(SkillsMaster!$B$15="",0,IF($M16="",1,0))) | P16: =IF($C16="","",IF(AND($N16="",$O16=0),"Yes","No")) | Q16: =IF(Cadets!$B16="","",Cadets!$I16)
B17: =IF(Cadets!$B17="","",Cadets!$B17) | C17: =IF(Cadets!$B17="","",Cadets!$F17) | N17: =IF($C17="","",_xlfn.TEXTJOIN(", ",TRUE,IF($D17="Fail",SkillsMaster!$B$6,""),IF($E17="Fail",SkillsMaster!$B$7,""),IF($F17="Fail",SkillsMaster!$B$8,""),IF($G17="Fail",SkillsMaster!$B$9,""),IF($H17="Fail",SkillsMaster!$B$10,""),IF($I17="Fail",SkillsMaster!$B$11,""),IF($J17="Fail",SkillsMaster!$B$12,""),IF($K17="Fail",SkillsMaster!$B$13,""),IF($L17="Fail",SkillsMaster!$B$14,""),IF($M17="Fail",SkillsMaster!$B$15,""))) | O17: =IF($C17="","",IF(SkillsMaster!$B$6="",0,IF($D17="",1,0))+IF(SkillsMaster!$B$7="",0,IF($E17="",1,0))+IF(SkillsMaster!$B$8="",0,IF($F17="",1,0))+IF(SkillsMaster!$B$9="",0,IF($G17="",1,0))+IF(SkillsMaster!$B$10="",0,IF($H17="",1,0))+IF(SkillsMaster!$B$11="",0,IF($I17="",1,0))+IF(SkillsMaster!$B$12="",0,IF($J17="",1,0))+IF(SkillsMaster!$B$13="",0,IF($K17="",1,0))+IF(SkillsMaster!$B$14="",0,IF($L17="",1,0))+IF(SkillsMaster!$B$15="",0,IF($M17="",1,0))) | P17: =IF($C17="","",IF(AND($N17="",$O17=0),"Yes","No")) | Q17: =IF(Cadets!$B17="","",Cadets!$I17)
... B55: =IF(Cadets!$B55="","",Cadets!$B55) | C55: =IF(Cadets!$B55="","",Cadets!$F55) | N55: =IF($C55="","",_xlfn.TEXTJOIN(", ",TRUE,IF($D55="Fail",SkillsMaster!$B$6,""),IF($E55="Fail",SkillsMaster!$B$7,""),IF($F55="Fail",SkillsMaster!$B$8,""),IF($G55="Fail",SkillsMaster!$B$9,""),IF($H55="Fail",SkillsMaster!$B$10,""),IF($I55="Fail",SkillsMaster!$B$11,""),IF($J55="Fail",SkillsMaster!$B$12,""),IF($K55="Fail",SkillsMaster!$B$13,""),IF($L55="Fail",SkillsMaster!$B$14,""),IF($M55="Fail",SkillsMaster!$B$15,""))) | O55: =IF($C55="","",IF(SkillsMaster!$B$6="",0,IF($D55="",1,0))+IF(SkillsMaster!$B$7="",0,IF($E55="",1,0))+IF(SkillsMaster!$B$8="",0,IF($F55="",1,0))+IF(SkillsMaster!$B$9="",0,IF($G55="",1,0))+IF(SkillsMaster!$B$10="",0,IF($H55="",1,0))+IF(SkillsMaster!$B$11="",0,IF($I55="",1,0))+IF(SkillsMaster!$B$12="",0,IF($J55="",1,0))+IF(SkillsMaster!$B$13="",0,IF($K55="",1,0))+IF(SkillsMaster!$B$14="",0,IF($L55="",1,0))+IF(SkillsMaster!$B$15="",0,IF($M55="",1,0))) | P55: =IF($C55="","",IF(AND($N55="",$O55=0),"Yes","No")) | Q55: =IF(Cadets!$B55="","",Cadets!$I55)

Sheet Writing
B1: =HYPERLINK("#Dashboard!B5","◄ Dashboard")
B4: Type X when an assignment is received (lowercase x auto-capitalizes; blank = not done). Red cells are past their computed due date (see WritingMaster).
B5: PID | C5: Cadet Name | D5: #1 | E5: #2 | F5: #3 | G5: #4 | H5: #5 | I5: #6 | J5: #7 | K5: #8 | L5: #9 | M5: #10 | N5: #11 | O5: #12 | P5: #13 | Q5: #14 | R5: #15 | S5: #16 | T5: #17 | U5: #18 | V5: #19 | W5: #20 | X5: #21 | Y5: #22 | Z5: #23 | AA5: #24 | AB5: #25 | AC5: #26 | AD5: #27 | AE5: #28 | AF5: #29 | AG5: #30 | AH5: #31 | AI5: #32 | AJ5: #33 | AK5: #34 | AL5: #35 | AM5: #36 | AN5: #37 | AO5: #38 | AP5: #39 | AQ5: #40 | AR5: Complete (of 40) | AS5: Overdue Missing | AT5: Writing Current? | AU5: Cadet Status
B6: =IF(Cadets!$B6="","",Cadets!$B6) | C6: =IF(Cadets!$B6="","",Cadets!$F6) | AR6: =IF($B6="","",COUNTIF(D6:AQ6,"X")) | AS6: =IF($B6="","",SUMPRODUCT((UPPER(D6:AQ6)<>"X")*(TRANSPOSE(rngWMdue)<>"")*(TRANSPOSE(rngWMdue)<TODAY()))) | AT6: =IF($B6="","",IF(AS6=0,"Yes","No")) | AU6: =IF(Cadets!$B6="","",Cadets!$I6)
B7: =IF(Cadets!$B7="","",Cadets!$B7) | C7: =IF(Cadets!$B7="","",Cadets!$F7) | AR7: =IF($B7="","",COUNTIF(D7:AQ7,"X")) | AS7: =IF($B7="","",SUMPRODUCT((UPPER(D7:AQ7)<>"X")*(TRANSPOSE(rngWMdue)<>"")*(TRANSPOSE(rngWMdue)<TODAY()))) | AT7: =IF($B7="","",IF(AS7=0,"Yes","No")) | AU7: =IF(Cadets!$B7="","",Cadets!$I7)
B8: =IF(Cadets!$B8="","",Cadets!$B8) | C8: =IF(Cadets!$B8="","",Cadets!$F8) | AR8: =IF($B8="","",COUNTIF(D8:AQ8,"X")) | AS8: =IF($B8="","",SUMPRODUCT((UPPER(D8:AQ8)<>"X")*(TRANSPOSE(rngWMdue)<>"")*(TRANSPOSE(rngWMdue)<TODAY()))) | AT8: =IF($B8="","",IF(AS8=0,"Yes","No")) | AU8: =IF(Cadets!$B8="","",Cadets!$I8)
B9: =IF(Cadets!$B9="","",Cadets!$B9) | C9: =IF(Cadets!$B9="","",Cadets!$F9) | AR9: =IF($B9="","",COUNTIF(D9:AQ9,"X")) | AS9: =IF($B9="","",SUMPRODUCT((UPPER(D9:AQ9)<>"X")*(TRANSPOSE(rngWMdue)<>"")*(TRANSPOSE(rngWMdue)<TODAY()))) | AT9: =IF($B9="","",IF(AS9=0,"Yes","No")) | AU9: =IF(Cadets!$B9="","",Cadets!$I9)
B10: =IF(Cadets!$B10="","",Cadets!$B10) | C10: =IF(Cadets!$B10="","",Cadets!$F10) | AR10: =IF($B10="","",COUNTIF(D10:AQ10,"X")) | AS10: =IF($B10="","",SUMPRODUCT((UPPER(D10:AQ10)<>"X")*(TRANSPOSE(rngWMdue)<>"")*(TRANSPOSE(rngWMdue)<TODAY()))) | AT10: =IF($B10="","",IF(AS10=0,"Yes","No")) | AU10: =IF(Cadets!$B10="","",Cadets!$I10)
B11: =IF(Cadets!$B11="","",Cadets!$B11) | C11: =IF(Cadets!$B11="","",Cadets!$F11) | AR11: =IF($B11="","",COUNTIF(D11:AQ11,"X")) | AS11: =IF($B11="","",SUMPRODUCT((UPPER(D11:AQ11)<>"X")*(TRANSPOSE(rngWMdue)<>"")*(TRANSPOSE(rngWMdue)<TODAY()))) | AT11: =IF($B11="","",IF(AS11=0,"Yes","No")) | AU11: =IF(Cadets!$B11="","",Cadets!$I11)
B12: =IF(Cadets!$B12="","",Cadets!$B12) | C12: =IF(Cadets!$B12="","",Cadets!$F12) | AR12: =IF($B12="","",COUNTIF(D12:AQ12,"X")) | AS12: =IF($B12="","",SUMPRODUCT((UPPER(D12:AQ12)<>"X")*(TRANSPOSE(rngWMdue)<>"")*(TRANSPOSE(rngWMdue)<TODAY()))) | AT12: =IF($B12="","",IF(AS12=0,"Yes","No")) | AU12: =IF(Cadets!$B12="","",Cadets!$I12)
B13: =IF(Cadets!$B13="","",Cadets!$B13) | C13: =IF(Cadets!$B13="","",Cadets!$F13) | AR13: =IF($B13="","",COUNTIF(D13:AQ13,"X")) | AS13: =IF($B13="","",SUMPRODUCT((UPPER(D13:AQ13)<>"X")*(TRANSPOSE(rngWMdue)<>"")*(TRANSPOSE(rngWMdue)<TODAY()))) | AT13: =IF($B13="","",IF(AS13=0,"Yes","No")) | AU13: =IF(Cadets!$B13="","",Cadets!$I13)
B14: =IF(Cadets!$B14="","",Cadets!$B14) | C14: =IF(Cadets!$B14="","",Cadets!$F14) | AR14: =IF($B14="","",COUNTIF(D14:AQ14,"X")) | AS14: =IF($B14="","",SUMPRODUCT((UPPER(D14:AQ14)<>"X")*(TRANSPOSE(rngWMdue)<>"")*(TRANSPOSE(rngWMdue)<TODAY()))) | AT14: =IF($B14="","",IF(AS14=0,"Yes","No")) | AU14: =IF(Cadets!$B14="","",Cadets!$I14)
B15: =IF(Cadets!$B15="","",Cadets!$B15) | C15: =IF(Cadets!$B15="","",Cadets!$F15) | AR15: =IF($B15="","",COUNTIF(D15:AQ15,"X")) | AS15: =IF($B15="","",SUMPRODUCT((UPPER(D15:AQ15)<>"X")*(TRANSPOSE(rngWMdue)<>"")*(TRANSPOSE(rngWMdue)<TODAY()))) | AT15: =IF($B15="","",IF(AS15=0,"Yes","No")) | AU15: =IF(Cadets!$B15="","",Cadets!$I15)
B16: =IF(Cadets!$B16="","",Cadets!$B16) | C16: =IF(Cadets!$B16="","",Cadets!$F16) | AR16: =IF($B16="","",COUNTIF(D16:AQ16,"X")) | AS16: =IF($B16="","",SUMPRODUCT((UPPER(D16:AQ16)<>"X")*(TRANSPOSE(rngWMdue)<>"")*(TRANSPOSE(rngWMdue)<TODAY()))) | AT16: =IF($B16="","",IF(AS16=0,"Yes","No")) | AU16: =IF(Cadets!$B16="","",Cadets!$I16)
B17: =IF(Cadets!$B17="","",Cadets!$B17) | C17: =IF(Cadets!$B17="","",Cadets!$F17) | AR17: =IF($B17="","",COUNTIF(D17:AQ17,"X")) | AS17: =IF($B17="","",SUMPRODUCT((UPPER(D17:AQ17)<>"X")*(TRANSPOSE(rngWMdue)<>"")*(TRANSPOSE(rngWMdue)<TODAY()))) | AT17: =IF($B17="","",IF(AS17=0,"Yes","No")) | AU17: =IF(Cadets!$B17="","",Cadets!$I17)
... B55: =IF(Cadets!$B55="","",Cadets!$B55) | C55: =IF(Cadets!$B55="","",Cadets!$F55) | AR55: =IF($B55="","",COUNTIF(D55:AQ55,"X")) | AS55: =IF($B55="","",SUMPRODUCT((UPPER(D55:AQ55)<>"X")*(TRANSPOSE(rngWMdue)<>"")*(TRANSPOSE(rngWMdue)<TODAY()))) | AT55: =IF($B55="","",IF(AS55=0,"Yes","No")) | AU55: =IF(Cadets!$B55="","",Cadets!$I55)

Sheet Incidents
B1: =HYPERLINK("#Dashboard!B5","◄ Dashboard")
B4: Positive and negative incidents. Negative Major/Critical trigger chain-of-command review (policy 600). 'Report to Agency?' = Yes includes it in that agency's next email digest; blank keeps it an academy teaching moment.
B5: IncidentID | C5: Date | D5: Cadet Name | E5: PID | F5: Direction | G5: Severity | H5: Category | I5: Description | J5: Reported By | K5: Doc Ref | L5: ChainReview | M5: Resolution | N5: Notes | O5: Report to Agency?
B6: =IF($D6="","","I"&TEXT(ROW()-5,"000")) | E6: =IF($D6="","",IFERROR(INDEX(rngCadetPIDs,MATCH($D6,rngCadetNames,0)),"?")) | L6: =IF($D6="","",IF(AND($F6="Negative",OR($G6="Critical",$G6="Major")),"Yes","No"))
B7: =IF($D7="","","I"&TEXT(ROW()-5,"000")) | E7: =IF($D7="","",IFERROR(INDEX(rngCadetPIDs,MATCH($D7,rngCadetNames,0)),"?")) | L7: =IF($D7="","",IF(AND($F7="Negative",OR($G7="Critical",$G7="Major")),"Yes","No"))
B8: =IF($D8="","","I"&TEXT(ROW()-5,"000")) | E8: =IF($D8="","",IFERROR(INDEX(rngCadetPIDs,MATCH($D8,rngCadetNames,0)),"?")) | L8: =IF($D8="","",IF(AND($F8="Negative",OR($G8="Critical",$G8="Major")),"Yes","No"))
B9: =IF($D9="","","I"&TEXT(ROW()-5,"000")) | E9: =IF($D9="","",IFERROR(INDEX(rngCadetPIDs,MATCH($D9,rngCadetNames,0)),"?")) | L9: =IF($D9="","",IF(AND($F9="Negative",OR($G9="Critical",$G9="Major")),"Yes","No"))
B10: =IF($D10="","","I"&TEXT(ROW()-5,"000")) | E10: =IF($D10="","",IFERROR(INDEX(rngCadetPIDs,MATCH($D10,rngCadetNames,0)),"?")) | L10: =IF($D10="","",IF(AND($F10="Negative",OR($G10="Critical",$G10="Major")),"Yes","No"))
B11: =IF($D11="","","I"&TEXT(ROW()-5,"000")) | E11: =IF($D11="","",IFERROR(INDEX(rngCadetPIDs,MATCH($D11,rngCadetNames,0)),"?")) | L11: =IF($D11="","",IF(AND($F11="Negative",OR($G11="Critical",$G11="Major")),"Yes","No"))
B12: =IF($D12="","","I"&TEXT(ROW()-5,"000")) | E12: =IF($D12="","",IFERROR(INDEX(rngCadetPIDs,MATCH($D12,rngCadetNames,0)),"?")) | L12: =IF($D12="","",IF(AND($F12="Negative",OR($G12="Critical",$G12="Major")),"Yes","No"))
B13: =IF($D13="","","I"&TEXT(ROW()-5,"000")) | E13: =IF($D13="","",IFERROR(INDEX(rngCadetPIDs,MATCH($D13,rngCadetNames,0)),"?")) | L13: =IF($D13="","",IF(AND($F13="Negative",OR($G13="Critical",$G13="Major")),"Yes","No"))
B14: =IF($D14="","","I"&TEXT(ROW()-5,"000")) | E14: =IF($D14="","",IFERROR(INDEX(rngCadetPIDs,MATCH($D14,rngCadetNames,0)),"?")) | L14: =IF($D14="","",IF(AND($F14="Negative",OR($G14="Critical",$G14="Major")),"Yes","No"))
B15: =IF($D15="","","I"&TEXT(ROW()-5,"000")) | E15: =IF($D15="","",IFERROR(INDEX(rngCadetPIDs,MATCH($D15,rngCadetNames,0)),"?")) | L15: =IF($D15="","",IF(AND($F15="Negative",OR($G15="Critical",$G15="Major")),"Yes","No"))
B16: =IF($D16="","","I"&TEXT(ROW()-5,"000")) | E16: =IF($D16="","",IFERROR(INDEX(rngCadetPIDs,MATCH($D16,rngCadetNames,0)),"?")) | L16: =IF($D16="","",IF(AND($F16="Negative",OR($G16="Critical",$G16="Major")),"Yes","No"))
B17: =IF($D17="","","I"&TEXT(ROW()-5,"000")) | E17: =IF($D17="","",IFERROR(INDEX(rngCadetPIDs,MATCH($D17,rngCadetNames,0)),"?")) | L17: =IF($D17="","",IF(AND($F17="Negative",OR($G17="Critical",$G17="Major")),"Yes","No"))
... B405: =IF($D405="","","I"&TEXT(ROW()-5,"000")) | E405: =IF($D405="","",IFERROR(INDEX(rngCadetPIDs,MATCH($D405,rngCadetNames,0)),"?")) | L405: =IF($D405="","",IF(AND($F405="Negative",OR($G405="Critical",$G405="Major")),"Yes","No"))

Sheet Counseling
B1: =HYPERLINK("#Dashboard!B5","◄ Dashboard")
B4: Documents every intervention (tutoring, counseling, agency notification, performance plan) — the early-intervention paper trail policy 300.4.B expects. 'Agency Notified?' = Yes includes the entry in that agency's next email digest; blank keeps it academy-only.
B5: EntryID | C5: Date | D5: Cadet Name | E5: PID | F5: Type | G5: Trigger / Related Flag | H5: Description / Plan | I5: Conducted By | J5: Agency Notified? | K5: Notified Date | L5: Follow-up Date | M5: Status | N5: Notes
B6: =IF($D6="","","C"&TEXT(ROW()-5,"000")) | E6: =IF($D6="","",IFERROR(INDEX(rngCadetPIDs,MATCH($D6,rngCadetNames,0)),"?"))
B7: =IF($D7="","","C"&TEXT(ROW()-5,"000")) | E7: =IF($D7="","",IFERROR(INDEX(rngCadetPIDs,MATCH($D7,rngCadetNames,0)),"?"))
B8: =IF($D8="","","C"&TEXT(ROW()-5,"000")) | E8: =IF($D8="","",IFERROR(INDEX(rngCadetPIDs,MATCH($D8,rngCadetNames,0)),"?"))
B9: =IF($D9="","","C"&TEXT(ROW()-5,"000")) | E9: =IF($D9="","",IFERROR(INDEX(rngCadetPIDs,MATCH($D9,rngCadetNames,0)),"?"))
B10: =IF($D10="","","C"&TEXT(ROW()-5,"000")) | E10: =IF($D10="","",IFERROR(INDEX(rngCadetPIDs,MATCH($D10,rngCadetNames,0)),"?"))
B11: =IF($D11="","","C"&TEXT(ROW()-5,"000")) | E11: =IF($D11="","",IFERROR(INDEX(rngCadetPIDs,MATCH($D11,rngCadetNames,0)),"?"))
B12: =IF($D12="","","C"&TEXT(ROW()-5,"000")) | E12: =IF($D12="","",IFERROR(INDEX(rngCadetPIDs,MATCH($D12,rngCadetNames,0)),"?"))
B13: =IF($D13="","","C"&TEXT(ROW()-5,"000")) | E13: =IF($D13="","",IFERROR(INDEX(rngCadetPIDs,MATCH($D13,rngCadetNames,0)),"?"))
B14: =IF($D14="","","C"&TEXT(ROW()-5,"000")) | E14: =IF($D14="","",IFERROR(INDEX(rngCadetPIDs,MATCH($D14,rngCadetNames,0)),"?"))
B15: =IF($D15="","","C"&TEXT(ROW()-5,"000")) | E15: =IF($D15="","",IFERROR(INDEX(rngCadetPIDs,MATCH($D15,rngCadetNames,0)),"?"))
B16: =IF($D16="","","C"&TEXT(ROW()-5,"000")) | E16: =IF($D16="","",IFERROR(INDEX(rngCadetPIDs,MATCH($D16,rngCadetNames,0)),"?"))
B17: =IF($D17="","","C"&TEXT(ROW()-5,"000")) | E17: =IF($D17="","",IFERROR(INDEX(rngCadetPIDs,MATCH($D17,rngCadetNames,0)),"?"))
... B405: =IF($D405="","","C"&TEXT(ROW()-5,"000")) | E405: =IF($D405="","",IFERROR(INDEX(rngCadetPIDs,MATCH($D405,rngCadetNames,0)),"?"))

Sheet Memos
B1: =HYPERLINK("#Dashboard!B5","◄ Dashboard")
B4: Assigned for deficiencies: lessons learned + plan of action. Linked Ref dropdown offers Incident (I), Attendance (A) and Counseling (C) IDs — or leave blank for stand-alone. Due auto-computes from the class-day calendar (Settings: Memo Due). 'Report to Agency?' = Yes puts it in that agency's next email digest; blank keeps it an academy teaching moment.
B5: MemoID | C5: Assigned | D5: Cadet Name | E5: PID | F5: Linked Ref | G5: Deficiency / Subject | H5: Due (computed) | I5: Due Override | J5: Due | K5: Received | L5: Status | M5: Report to Agency? | N5: Notes
B6: =IF($D6="","","ME"&TEXT(ROW()-5,"000")) | E6: =IF($D6="","",IFERROR(INDEX(rngCadetPIDs,MATCH($D6,rngCadetNames,0)),"?")) | H6: =IF($D6="","",IF($C6="","(enter date)",_xlfn.LET(_xlpm.dn,_xlfn.XLOOKUP($C6,nrCDdate,nrCDnum,"",1),IF(_xlpm.dn="","(after last class day)",_xlfn.LET(_xlpm.dd,_xlfn.XLOOKUP(_xlpm.dn+cfgMemoDueClassDays,nrCDnum,nrCDdate,""),_xlpm.ok,_xlfn.XLOOKUP(_xlpm.dn+cfgMemoDueClassDays,nrCDnum,nrCDinsession,"No"),IF(OR(_xlpm.dd="",_xlpm.ok<>"Yes"),"(after last class day)",_xlpm.dd)))))) | J6: =IF($D6="","",IF($I6<>"",$I6,IF(ISNUMBER($H6),$H6,""))) | L6: =IF($D6="","",IF($K6<>"","Received "&TEXT($K6,"mm/dd"),IF(ISNUMBER($J6),IF(TODAY()>$J6,"OVERDUE","Pending"),IF($H6="","Pending","CHECK DATE"))))
B7: =IF($D7="","","ME"&TEXT(ROW()-5,"000")) | E7: =IF($D7="","",IFERROR(INDEX(rngCadetPIDs,MATCH($D7,rngCadetNames,0)),"?")) | H7: =IF($D7="","",IF($C7="","(enter date)",_xlfn.LET(_xlpm.dn,_xlfn.XLOOKUP($C7,nrCDdate,nrCDnum,"",1),IF(_xlpm.dn="","(after last class day)",_xlfn.LET(_xlpm.dd,_xlfn.XLOOKUP(_xlpm.dn+cfgMemoDueClassDays,nrCDnum,nrCDdate,""),_xlpm.ok,_xlfn.XLOOKUP(_xlpm.dn+cfgMemoDueClassDays,nrCDnum,nrCDinsession,"No"),IF(OR(_xlpm.dd="",_xlpm.ok<>"Yes"),"(after last class day)",_xlpm.dd)))))) | J7: =IF($D7="","",IF($I7<>"",$I7,IF(ISNUMBER($H7),$H7,""))) | L7: =IF($D7="","",IF($K7<>"","Received "&TEXT($K7,"mm/dd"),IF(ISNUMBER($J7),IF(TODAY()>$J7,"OVERDUE","Pending"),IF($H7="","Pending","CHECK DATE"))))
B8: =IF($D8="","","ME"&TEXT(ROW()-5,"000")) | E8: =IF($D8="","",IFERROR(INDEX(rngCadetPIDs,MATCH($D8,rngCadetNames,0)),"?")) | H8: =IF($D8="","",IF($C8="","(enter date)",_xlfn.LET(_xlpm.dn,_xlfn.XLOOKUP($C8,nrCDdate,nrCDnum,"",1),IF(_xlpm.dn="","(after last class day)",_xlfn.LET(_xlpm.dd,_xlfn.XLOOKUP(_xlpm.dn+cfgMemoDueClassDays,nrCDnum,nrCDdate,""),_xlpm.ok,_xlfn.XLOOKUP(_xlpm.dn+cfgMemoDueClassDays,nrCDnum,nrCDinsession,"No"),IF(OR(_xlpm.dd="",_xlpm.ok<>"Yes"),"(after last class day)",_xlpm.dd)))))) | J8: =IF($D8="","",IF($I8<>"",$I8,IF(ISNUMBER($H8),$H8,""))) | L8: =IF($D8="","",IF($K8<>"","Received "&TEXT($K8,"mm/dd"),IF(ISNUMBER($J8),IF(TODAY()>$J8,"OVERDUE","Pending"),IF($H8="","Pending","CHECK DATE"))))
B9: =IF($D9="","","ME"&TEXT(ROW()-5,"000")) | E9: =IF($D9="","",IFERROR(INDEX(rngCadetPIDs,MATCH($D9,rngCadetNames,0)),"?")) | H9: =IF($D9="","",IF($C9="","(enter date)",_xlfn.LET(_xlpm.dn,_xlfn.XLOOKUP($C9,nrCDdate,nrCDnum,"",1),IF(_xlpm.dn="","(after last class day)",_xlfn.LET(_xlpm.dd,_xlfn.XLOOKUP(_xlpm.dn+cfgMemoDueClassDays,nrCDnum,nrCDdate,""),_xlpm.ok,_xlfn.XLOOKUP(_xlpm.dn+cfgMemoDueClassDays,nrCDnum,nrCDinsession,"No"),IF(OR(_xlpm.dd="",_xlpm.ok<>"Yes"),"(after last class day)",_xlpm.dd)))))) | J9: =IF($D9="","",IF($I9<>"",$I9,IF(ISNUMBER($H9),$H9,""))) | L9: =IF($D9="","",IF($K9<>"","Received "&TEXT($K9,"mm/dd"),IF(ISNUMBER($J9),IF(TODAY()>$J9,"OVERDUE","Pending"),IF($H9="","Pending","CHECK DATE"))))
B10: =IF($D10="","","ME"&TEXT(ROW()-5,"000")) | E10: =IF($D10="","",IFERROR(INDEX(rngCadetPIDs,MATCH($D10,rngCadetNames,0)),"?")) | H10: =IF($D10="","",IF($C10="","(enter date)",_xlfn.LET(_xlpm.dn,_xlfn.XLOOKUP($C10,nrCDdate,nrCDnum,"",1),IF(_xlpm.dn="","(after last class day)",_xlfn.LET(_xlpm.dd,_xlfn.XLOOKUP(_xlpm.dn+cfgMemoDueClassDays,nrCDnum,nrCDdate,""),_xlpm.ok,_xlfn.XLOOKUP(_xlpm.dn+cfgMemoDueClassDays,nrCDnum,nrCDinsession,"No"),IF(OR(_xlpm.dd="",_xlpm.ok<>"Yes"),"(after last class day)",_xlpm.dd)))))) | J10: =IF($D10="","",IF($I10<>"",$I10,IF(ISNUMBER($H10),$H10,""))) | L10: =IF($D10="","",IF($K10<>"","Received "&TEXT($K10,"mm/dd"),IF(ISNUMBER($J10),IF(TODAY()>$J10,"OVERDUE","Pending"),IF($H10="","Pending","CHECK DATE"))))
B11: =IF($D11="","","ME"&TEXT(ROW()-5,"000")) | E11: =IF($D11="","",IFERROR(INDEX(rngCadetPIDs,MATCH($D11,rngCadetNames,0)),"?")) | H11: =IF($D11="","",IF($C11="","(enter date)",_xlfn.LET(_xlpm.dn,_xlfn.XLOOKUP($C11,nrCDdate,nrCDnum,"",1),IF(_xlpm.dn="","(after last class day)",_xlfn.LET(_xlpm.dd,_xlfn.XLOOKUP(_xlpm.dn+cfgMemoDueClassDays,nrCDnum,nrCDdate,""),_xlpm.ok,_xlfn.XLOOKUP(_xlpm.dn+cfgMemoDueClassDays,nrCDnum,nrCDinsession,"No"),IF(OR(_xlpm.dd="",_xlpm.ok<>"Yes"),"(after last class day)",_xlpm.dd)))))) | J11: =IF($D11="","",IF($I11<>"",$I11,IF(ISNUMBER($H11),$H11,""))) | L11: =IF($D11="","",IF($K11<>"","Received "&TEXT($K11,"mm/dd"),IF(ISNUMBER($J11),IF(TODAY()>$J11,"OVERDUE","Pending"),IF($H11="","Pending","CHECK DATE"))))
B12: =IF($D12="","","ME"&TEXT(ROW()-5,"000")) | E12: =IF($D12="","",IFERROR(INDEX(rngCadetPIDs,MATCH($D12,rngCadetNames,0)),"?")) | H12: =IF($D12="","",IF($C12="","(enter date)",_xlfn.LET(_xlpm.dn,_xlfn.XLOOKUP($C12,nrCDdate,nrCDnum,"",1),IF(_xlpm.dn="","(after last class day)",_xlfn.LET(_xlpm.dd,_xlfn.XLOOKUP(_xlpm.dn+cfgMemoDueClassDays,nrCDnum,nrCDdate,""),_xlpm.ok,_xlfn.XLOOKUP(_xlpm.dn+cfgMemoDueClassDays,nrCDnum,nrCDinsession,"No"),IF(OR(_xlpm.dd="",_xlpm.ok<>"Yes"),"(after last class day)",_xlpm.dd)))))) | J12: =IF($D12="","",IF($I12<>"",$I12,IF(ISNUMBER($H12),$H12,""))) | L12: =IF($D12="","",IF($K12<>"","Received "&TEXT($K12,"mm/dd"),IF(ISNUMBER($J12),IF(TODAY()>$J12,"OVERDUE","Pending"),IF($H12="","Pending","CHECK DATE"))))
B13: =IF($D13="","","ME"&TEXT(ROW()-5,"000")) | E13: =IF($D13="","",IFERROR(INDEX(rngCadetPIDs,MATCH($D13,rngCadetNames,0)),"?")) | H13: =IF($D13="","",IF($C13="","(enter date)",_xlfn.LET(_xlpm.dn,_xlfn.XLOOKUP($C13,nrCDdate,nrCDnum,"",1),IF(_xlpm.dn="","(after last class day)",_xlfn.LET(_xlpm.dd,_xlfn.XLOOKUP(_xlpm.dn+cfgMemoDueClassDays,nrCDnum,nrCDdate,""),_xlpm.ok,_xlfn.XLOOKUP(_xlpm.dn+cfgMemoDueClassDays,nrCDnum,nrCDinsession,"No"),IF(OR(_xlpm.dd="",_xlpm.ok<>"Yes"),"(after last class day)",_xlpm.dd)))))) | J13: =IF($D13="","",IF($I13<>"",$I13,IF(ISNUMBER($H13),$H13,""))) | L13: =IF($D13="","",IF($K13<>"","Received "&TEXT($K13,"mm/dd"),IF(ISNUMBER($J13),IF(TODAY()>$J13,"OVERDUE","Pending"),IF($H13="","Pending","CHECK DATE"))))
B14: =IF($D14="","","ME"&TEXT(ROW()-5,"000")) | E14: =IF($D14="","",IFERROR(INDEX(rngCadetPIDs,MATCH($D14,rngCadetNames,0)),"?")) | H14: =IF($D14="","",IF($C14="","(enter date)",_xlfn.LET(_xlpm.dn,_xlfn.XLOOKUP($C14,nrCDdate,nrCDnum,"",1),IF(_xlpm.dn="","(after last class day)",_xlfn.LET(_xlpm.dd,_xlfn.XLOOKUP(_xlpm.dn+cfgMemoDueClassDays,nrCDnum,nrCDdate,""),_xlpm.ok,_xlfn.XLOOKUP(_xlpm.dn+cfgMemoDueClassDays,nrCDnum,nrCDinsession,"No"),IF(OR(_xlpm.dd="",_xlpm.ok<>"Yes"),"(after last class day)",_xlpm.dd)))))) | J14: =IF($D14="","",IF($I14<>"",$I14,IF(ISNUMBER($H14),$H14,""))) | L14: =IF($D14="","",IF($K14<>"","Received "&TEXT($K14,"mm/dd"),IF(ISNUMBER($J14),IF(TODAY()>$J14,"OVERDUE","Pending"),IF($H14="","Pending","CHECK DATE"))))
B15: =IF($D15="","","ME"&TEXT(ROW()-5,"000")) | E15: =IF($D15="","",IFERROR(INDEX(rngCadetPIDs,MATCH($D15,rngCadetNames,0)),"?")) | H15: =IF($D15="","",IF($C15="","(enter date)",_xlfn.LET(_xlpm.dn,_xlfn.XLOOKUP($C15,nrCDdate,nrCDnum,"",1),IF(_xlpm.dn="","(after last class day)",_xlfn.LET(_xlpm.dd,_xlfn.XLOOKUP(_xlpm.dn+cfgMemoDueClassDays,nrCDnum,nrCDdate,""),_xlpm.ok,_xlfn.XLOOKUP(_xlpm.dn+cfgMemoDueClassDays,nrCDnum,nrCDinsession,"No"),IF(OR(_xlpm.dd="",_xlpm.ok<>"Yes"),"(after last class day)",_xlpm.dd)))))) | J15: =IF($D15="","",IF($I15<>"",$I15,IF(ISNUMBER($H15),$H15,""))) | L15: =IF($D15="","",IF($K15<>"","Received "&TEXT($K15,"mm/dd"),IF(ISNUMBER($J15),IF(TODAY()>$J15,"OVERDUE","Pending"),IF($H15="","Pending","CHECK DATE"))))
B16: =IF($D16="","","ME"&TEXT(ROW()-5,"000")) | E16: =IF($D16="","",IFERROR(INDEX(rngCadetPIDs,MATCH($D16,rngCadetNames,0)),"?")) | H16: =IF($D16="","",IF($C16="","(enter date)",_xlfn.LET(_xlpm.dn,_xlfn.XLOOKUP($C16,nrCDdate,nrCDnum,"",1),IF(_xlpm.dn="","(after last class day)",_xlfn.LET(_xlpm.dd,_xlfn.XLOOKUP(_xlpm.dn+cfgMemoDueClassDays,nrCDnum,nrCDdate,""),_xlpm.ok,_xlfn.XLOOKUP(_xlpm.dn+cfgMemoDueClassDays,nrCDnum,nrCDinsession,"No"),IF(OR(_xlpm.dd="",_xlpm.ok<>"Yes"),"(after last class day)",_xlpm.dd)))))) | J16: =IF($D16="","",IF($I16<>"",$I16,IF(ISNUMBER($H16),$H16,""))) | L16: =IF($D16="","",IF($K16<>"","Received "&TEXT($K16,"mm/dd"),IF(ISNUMBER($J16),IF(TODAY()>$J16,"OVERDUE","Pending"),IF($H16="","Pending","CHECK DATE"))))
B17: =IF($D17="","","ME"&TEXT(ROW()-5,"000")) | E17: =IF($D17="","",IFERROR(INDEX(rngCadetPIDs,MATCH($D17,rngCadetNames,0)),"?")) | H17: =IF($D17="","",IF($C17="","(enter date)",_xlfn.LET(_xlpm.dn,_xlfn.XLOOKUP($C17,nrCDdate,nrCDnum,"",1),IF(_xlpm.dn="","(after last class day)",_xlfn.LET(_xlpm.dd,_xlfn.XLOOKUP(_xlpm.dn+cfgMemoDueClassDays,nrCDnum,nrCDdate,""),_xlpm.ok,_xlfn.XLOOKUP(_xlpm.dn+cfgMemoDueClassDays,nrCDnum,nrCDinsession,"No"),IF(OR(_xlpm.dd="",_xlpm.ok<>"Yes"),"(after last class day)",_xlpm.dd)))))) | J17: =IF($D17="","",IF($I17<>"",$I17,IF(ISNUMBER($H17),$H17,""))) | L17: =IF($D17="","",IF($K17<>"","Received "&TEXT($K17,"mm/dd"),IF(ISNUMBER($J17),IF(TODAY()>$J17,"OVERDUE","Pending"),IF($H17="","Pending","CHECK DATE"))))
... B305: =IF($D305="","","ME"&TEXT(ROW()-5,"000")) | E305: =IF($D305="","",IFERROR(INDEX(rngCadetPIDs,MATCH($D305,rngCadetNames,0)),"?")) | H305: =IF($D305="","",IF($C305="","(enter date)",_xlfn.LET(_xlpm.dn,_xlfn.XLOOKUP($C305,nrCDdate,nrCDnum,"",1),IF(_xlpm.dn="","(after last class day)",_xlfn.LET(_xlpm.dd,_xlfn.XLOOKUP(_xlpm.dn+cfgMemoDueClassDays,nrCDnum,nrCDdate,""),_xlpm.ok,_xlfn.XLOOKUP(_xlpm.dn+cfgMemoDueClassDays,nrCDnum,nrCDinsession,"No"),IF(OR(_xlpm.dd="",_xlpm.ok<>"Yes"),"(after last class day)",_xlpm.dd)))))) | J305: =IF($D305="","",IF($I305<>"",$I305,IF(ISNUMBER($H305),$H305,""))) | L305: =IF($D305="","",IF($K305<>"","Received "&TEXT($K305,"mm/dd"),IF(ISNUMBER($J305),IF(TODAY()>$J305,"OVERDUE","Pending"),IF($H305="","Pending","CHECK DATE"))))

Sheet DailyLog
B1: =HYPERLINK("#Dashboard!B5","◄ Dashboard")
B4: The digital daily report — one row per training day, 30 seconds after the class leader briefs you. Counters (incidents, early departures, memos received) compute from the logs; Issues=Yes highlights for follow-up. Mark when the signed leader report is scanned into the file.
B5: Date | C5: Day # | D5: Class Type | E5: Present | F5: Absent/Late (names & reason) | G5: AM Notes (roll call / PT) | H5: PM Notes (changes / departures) | I5: Incidents | J5: Early Departs | K5: Memos In | L5: Issues? | M5: Leader Report Scanned? | N5: Notes
C6: =IF($B6="","",IFERROR(_xlfn.XLOOKUP($B6,nrCDdate,nrCDnum),"")) | D6: =IF($B6="","",TRIM(IF(COUNTIFS(nrSCH_Date,$B6,nrSCH_Act,"PT*")>0,"PT + ","")&IF(COUNTIFS(nrSCH_Date,$B6,nrSCH_Act,"*Test*")>0,"Test + ","")&"Classroom")) | I6: =IF($B6="","",COUNTIFS(nrIN_Date,$B6)) | J6: =IF($B6="","",COUNTIFS(nrAT_Date,$B6,nrAT_Type,"Early Departure")) | K6: =IF($B6="","",COUNTIFS(nrME_Received,$B6))
C7: =IF($B7="","",IFERROR(_xlfn.XLOOKUP($B7,nrCDdate,nrCDnum),"")) | D7: =IF($B7="","",TRIM(IF(COUNTIFS(nrSCH_Date,$B7,nrSCH_Act,"PT*")>0,"PT + ","")&IF(COUNTIFS(nrSCH_Date,$B7,nrSCH_Act,"*Test*")>0,"Test + ","")&"Classroom")) | I7: =IF($B7="","",COUNTIFS(nrIN_Date,$B7)) | J7: =IF($B7="","",COUNTIFS(nrAT_Date,$B7,nrAT_Type,"Early Departure")) | K7: =IF($B7="","",COUNTIFS(nrME_Received,$B7))
C8: =IF($B8="","",IFERROR(_xlfn.XLOOKUP($B8,nrCDdate,nrCDnum),"")) | D8: =IF($B8="","",TRIM(IF(COUNTIFS(nrSCH_Date,$B8,nrSCH_Act,"PT*")>0,"PT + ","")&IF(COUNTIFS(nrSCH_Date,$B8,nrSCH_Act,"*Test*")>0,"Test + ","")&"Classroom")) | I8: =IF($B8="","",COUNTIFS(nrIN_Date,$B8)) | J8: =IF($B8="","",COUNTIFS(nrAT_Date,$B8,nrAT_Type,"Early Departure")) | K8: =IF($B8="","",COUNTIFS(nrME_Received,$B8))
C9: =IF($B9="","",IFERROR(_xlfn.XLOOKUP($B9,nrCDdate,nrCDnum),"")) | D9: =IF($B9="","",TRIM(IF(COUNTIFS(nrSCH_Date,$B9,nrSCH_Act,"PT*")>0,"PT + ","")&IF(COUNTIFS(nrSCH_Date,$B9,nrSCH_Act,"*Test*")>0,"Test + ","")&"Classroom")) | I9: =IF($B9="","",COUNTIFS(nrIN_Date,$B9)) | J9: =IF($B9="","",COUNTIFS(nrAT_Date,$B9,nrAT_Type,"Early Departure")) | K9: =IF($B9="","",COUNTIFS(nrME_Received,$B9))
C10: =IF($B10="","",IFERROR(_xlfn.XLOOKUP($B10,nrCDdate,nrCDnum),"")) | D10: =IF($B10="","",TRIM(IF(COUNTIFS(nrSCH_Date,$B10,nrSCH_Act,"PT*")>0,"PT + ","")&IF(COUNTIFS(nrSCH_Date,$B10,nrSCH_Act,"*Test*")>0,"Test + ","")&"Classroom")) | I10: =IF($B10="","",COUNTIFS(nrIN_Date,$B10)) | J10: =IF($B10="","",COUNTIFS(nrAT_Date,$B10,nrAT_Type,"Early Departure")) | K10: =IF($B10="","",COUNTIFS(nrME_Received,$B10))
C11: =IF($B11="","",IFERROR(_xlfn.XLOOKUP($B11,nrCDdate,nrCDnum),"")) | D11: =IF($B11="","",TRIM(IF(COUNTIFS(nrSCH_Date,$B11,nrSCH_Act,"PT*")>0,"PT + ","")&IF(COUNTIFS(nrSCH_Date,$B11,nrSCH_Act,"*Test*")>0,"Test + ","")&"Classroom")) | I11: =IF($B11="","",COUNTIFS(nrIN_Date,$B11)) | J11: =IF($B11="","",COUNTIFS(nrAT_Date,$B11,nrAT_Type,"Early Departure")) | K11: =IF($B11="","",COUNTIFS(nrME_Received,$B11))
C12: =IF($B12="","",IFERROR(_xlfn.XLOOKUP($B12,nrCDdate,nrCDnum),"")) | D12: =IF($B12="","",TRIM(IF(COUNTIFS(nrSCH_Date,$B12,nrSCH_Act,"PT*")>0,"PT + ","")&IF(COUNTIFS(nrSCH_Date,$B12,nrSCH_Act,"*Test*")>0,"Test + ","")&"Classroom")) | I12: =IF($B12="","",COUNTIFS(nrIN_Date,$B12)) | J12: =IF($B12="","",COUNTIFS(nrAT_Date,$B12,nrAT_Type,"Early Departure")) | K12: =IF($B12="","",COUNTIFS(nrME_Received,$B12))
C13: =IF($B13="","",IFERROR(_xlfn.XLOOKUP($B13,nrCDdate,nrCDnum),"")) | D13: =IF($B13="","",TRIM(IF(COUNTIFS(nrSCH_Date,$B13,nrSCH_Act,"PT*")>0,"PT + ","")&IF(COUNTIFS(nrSCH_Date,$B13,nrSCH_Act,"*Test*")>0,"Test + ","")&"Classroom")) | I13: =IF($B13="","",COUNTIFS(nrIN_Date,$B13)) | J13: =IF($B13="","",COUNTIFS(nrAT_Date,$B13,nrAT_Type,"Early Departure")) | K13: =IF($B13="","",COUNTIFS(nrME_Received,$B13))
C14: =IF($B14="","",IFERROR(_xlfn.XLOOKUP($B14,nrCDdate,nrCDnum),"")) | D14: =IF($B14="","",TRIM(IF(COUNTIFS(nrSCH_Date,$B14,nrSCH_Act,"PT*")>0,"PT + ","")&IF(COUNTIFS(nrSCH_Date,$B14,nrSCH_Act,"*Test*")>0,"Test + ","")&"Classroom")) | I14: =IF($B14="","",COUNTIFS(nrIN_Date,$B14)) | J14: =IF($B14="","",COUNTIFS(nrAT_Date,$B14,nrAT_Type,"Early Departure")) | K14: =IF($B14="","",COUNTIFS(nrME_Received,$B14))
C15: =IF($B15="","",IFERROR(_xlfn.XLOOKUP($B15,nrCDdate,nrCDnum),"")) | D15: =IF($B15="","",TRIM(IF(COUNTIFS(nrSCH_Date,$B15,nrSCH_Act,"PT*")>0,"PT + ","")&IF(COUNTIFS(nrSCH_Date,$B15,nrSCH_Act,"*Test*")>0,"Test + ","")&"Classroom")) | I15: =IF($B15="","",COUNTIFS(nrIN_Date,$B15)) | J15: =IF($B15="","",COUNTIFS(nrAT_Date,$B15,nrAT_Type,"Early Departure")) | K15: =IF($B15="","",COUNTIFS(nrME_Received,$B15))
C16: =IF($B16="","",IFERROR(_xlfn.XLOOKUP($B16,nrCDdate,nrCDnum),"")) | D16: =IF($B16="","",TRIM(IF(COUNTIFS(nrSCH_Date,$B16,nrSCH_Act,"PT*")>0,"PT + ","")&IF(COUNTIFS(nrSCH_Date,$B16,nrSCH_Act,"*Test*")>0,"Test + ","")&"Classroom")) | I16: =IF($B16="","",COUNTIFS(nrIN_Date,$B16)) | J16: =IF($B16="","",COUNTIFS(nrAT_Date,$B16,nrAT_Type,"Early Departure")) | K16: =IF($B16="","",COUNTIFS(nrME_Received,$B16))
C17: =IF($B17="","",IFERROR(_xlfn.XLOOKUP($B17,nrCDdate,nrCDnum),"")) | D17: =IF($B17="","",TRIM(IF(COUNTIFS(nrSCH_Date,$B17,nrSCH_Act,"PT*")>0,"PT + ","")&IF(COUNTIFS(nrSCH_Date,$B17,nrSCH_Act,"*Test*")>0,"Test + ","")&"Classroom")) | I17: =IF($B17="","",COUNTIFS(nrIN_Date,$B17)) | J17: =IF($B17="","",COUNTIFS(nrAT_Date,$B17,nrAT_Type,"Early Departure")) | K17: =IF($B17="","",COUNTIFS(nrME_Received,$B17))
... C175: =IF($B175="","",IFERROR(_xlfn.XLOOKUP($B175,nrCDdate,nrCDnum),"")) | D175: =IF($B175="","",TRIM(IF(COUNTIFS(nrSCH_Date,$B175,nrSCH_Act,"PT*")>0,"PT + ","")&IF(COUNTIFS(nrSCH_Date,$B175,nrSCH_Act,"*Test*")>0,"Test + ","")&"Classroom")) | I175: =IF($B175="","",COUNTIFS(nrIN_Date,$B175)) | J175: =IF($B175="","",COUNTIFS(nrAT_Date,$B175,nrAT_Type,"Early Departure")) | K175: =IF($B175="","",COUNTIFS(nrME_Received,$B175))

Sheet PT
B1: =HYPERLINK("#Dashboard!B5","◄ Dashboard")
B4: BASELINE columns are the ENTRY standard (policy manual); FINAL columns are graded against the approved PT Test Score Chart, which is the EXIT standard. They differ on purpose — cadets are expected to improve, so every final minimum is higher than its baseline, and the push-up protocol differs too (baseline 18 reps in 1:00, final 23 reps with no time limit). That is not a contradiction to reconcile. Raw values per event: bench lbs, jump inches, pushup/situp reps, agility & 300m seconds, 1.5mi minutes DECIMAL (12:35 = 12.5833 — the engine converts to seconds to score it). Pts columns COMPUTE from the approved PT Test Score Chart in the rubric block on Settings: the points of the best tier the result reaches, 0 if it is below the Tier 1 minimum. Bench and vertical jump are baseline standards only and are not scored at the final. All five scored events must be recorded before Final PT Pass? resolves — until then it reads Incomplete, which blocks. Final PT failure blocks the Final Exam (policy 500.1.H).
B5: PID | C5: Cadet Name | D5: Base Bench | E5: Base VertJump | F5: Base Pushups | G5: Base Situps | H5: Base Agility | I5: Base 1.5Mi | J5: Base 300m | K5: Baseline Pass? | L5: Midpoint Done? | M5: Final Bench | N5: Final VertJump | O5: Final Pushups | P5: Final Situps | Q5: Final Agility | R5: Final 1.5Mi | S5: Final 300m | T5: Pts Bench | U5: Pts VertJump | V5: Pts Pushups | W5: Pts Situps | X5: Pts Agility | Y5: Pts 1.5Mi | Z5: Pts 300m | AA5: Final Points | AB5: Final PT Pass? | AC5: Improvement Index | AD5: Cadet Status
B6: =IF(Cadets!$B6="","",Cadets!$B6) | C6: =IF(Cadets!$B6="","",Cadets!$F6) | T6: =IF($B6="","","n/a (baseline only)") | U6: =IF($B6="","","n/a") | V6: =IF($B6="","",IF($O6="","",IF(COUNT(INDEX(nrPTBands,1,0))<5,"",SUMPRODUCT(MAX(($O6>=INDEX(nrPTBands,1,0))*nrPTTierPts))))) | W6: =IF($B6="","",IF($P6="","",IF(COUNT(INDEX(nrPTBands,2,0))<5,"",SUMPRODUCT(MAX(($P6>=INDEX(nrPTBands,2,0))*nrPTTierPts))))) | X6: =IF($B6="","",IF($Q6="","",IF(COUNT(INDEX(nrPTBands,3,0))<5,"",SUMPRODUCT(MAX(($Q6<=INDEX(nrPTBands,3,0))*nrPTTierPts))))) | Y6: =IF($B6="","",IF($R6="","",IF(COUNT(INDEX(nrPTBands,4,0))<5,"",SUMPRODUCT(MAX(($R6*60<=INDEX(nrPTBands,4,0))*nrPTTierPts))))) | Z6: =IF($B6="","",IF($S6="","",IF(COUNT(INDEX(nrPTBands,5,0))<5,"",SUMPRODUCT(MAX(($S6<=INDEX(nrPTBands,5,0))*nrPTTierPts))))) | AA6: =IF($B6="","",IF(COUNT($V6:$Z6)=0,"",SUM($V6:$Z6))) | AB6: =IF($B6="","",IF($AA6="","",IF(cfgPTFinalMinPoints=0,"(rubric pending)",IF(COUNT($V6:$Z6)<5,"Incomplete",IF($AA6>=cfgPTFinalMinPoints,"Yes","No"))))) | AC6: =IF($B6="","",_xlfn.LET(_xlpm.pu,IF(COUNT($F6,$O6)=2,IFERROR(($O6-$F6)/$F6,""),""),_xlpm.su,IF(COUNT($G6,$P6)=2,IFERROR(($P6-$G6)/$G6,""),""),_xlpm.ag,IF(COUNT($H6,$Q6)=2,IFERROR(($H6-$Q6)/$H6,""),""),_xlpm.mi,IF(COUNT($I6,$R6)=2,IFERROR(($I6-$R6)/$I6,""),""),_xlpm.tm,IF(COUNT($J6,$S6)=2,IFERROR(($J6-$S6)/$J6,""),""),_xlpm.vals,IFERROR(_xlfn._xlws.FILTER(_xlfn.HSTACK(_xlpm.pu,_xlpm.su,_xlpm.ag,_xlpm.mi,_xlpm.tm),ISNUMBER(_xlfn.HSTACK(_xlpm.pu,_xlpm.su,_xlpm.ag,_xlpm.mi,_xlpm.tm))),""),IF(COUNT(_xlpm.vals)=0,"",ROUND(AVERAGE(_xlpm.vals)*100,1)))) | AD6: =IF(Cadets!$B6="","",Cadets!$I6)
B7: =IF(Cadets!$B7="","",Cadets!$B7) | C7: =IF(Cadets!$B7="","",Cadets!$F7) | T7: =IF($B7="","","n/a (baseline only)") | U7: =IF($B7="","","n/a") | V7: =IF($B7="","",IF($O7="","",IF(COUNT(INDEX(nrPTBands,1,0))<5,"",SUMPRODUCT(MAX(($O7>=INDEX(nrPTBands,1,0))*nrPTTierPts))))) | W7: =IF($B7="","",IF($P7="","",IF(COUNT(INDEX(nrPTBands,2,0))<5,"",SUMPRODUCT(MAX(($P7>=INDEX(nrPTBands,2,0))*nrPTTierPts))))) | X7: =IF($B7="","",IF($Q7="","",IF(COUNT(INDEX(nrPTBands,3,0))<5,"",SUMPRODUCT(MAX(($Q7<=INDEX(nrPTBands,3,0))*nrPTTierPts))))) | Y7: =IF($B7="","",IF($R7="","",IF(COUNT(INDEX(nrPTBands,4,0))<5,"",SUMPRODUCT(MAX(($R7*60<=INDEX(nrPTBands,4,0))*nrPTTierPts))))) | Z7: =IF($B7="","",IF($S7="","",IF(COUNT(INDEX(nrPTBands,5,0))<5,"",SUMPRODUCT(MAX(($S7<=INDEX(nrPTBands,5,0))*nrPTTierPts))))) | AA7: =IF($B7="","",IF(COUNT($V7:$Z7)=0,"",SUM($V7:$Z7))) | AB7: =IF($B7="","",IF($AA7="","",IF(cfgPTFinalMinPoints=0,"(rubric pending)",IF(COUNT($V7:$Z7)<5,"Incomplete",IF($AA7>=cfgPTFinalMinPoints,"Yes","No"))))) | AC7: =IF($B7="","",_xlfn.LET(_xlpm.pu,IF(COUNT($F7,$O7)=2,IFERROR(($O7-$F7)/$F7,""),""),_xlpm.su,IF(COUNT($G7,$P7)=2,IFERROR(($P7-$G7)/$G7,""),""),_xlpm.ag,IF(COUNT($H7,$Q7)=2,IFERROR(($H7-$Q7)/$H7,""),""),_xlpm.mi,IF(COUNT($I7,$R7)=2,IFERROR(($I7-$R7)/$I7,""),""),_xlpm.tm,IF(COUNT($J7,$S7)=2,IFERROR(($J7-$S7)/$J7,""),""),_xlpm.vals,IFERROR(_xlfn._xlws.FILTER(_xlfn.HSTACK(_xlpm.pu,_xlpm.su,_xlpm.ag,_xlpm.mi,_xlpm.tm),ISNUMBER(_xlfn.HSTACK(_xlpm.pu,_xlpm.su,_xlpm.ag,_xlpm.mi,_xlpm.tm))),""),IF(COUNT(_xlpm.vals)=0,"",ROUND(AVERAGE(_xlpm.vals)*100,1)))) | AD7: =IF(Cadets!$B7="","",Cadets!$I7)
B8: =IF(Cadets!$B8="","",Cadets!$B8) | C8: =IF(Cadets!$B8="","",Cadets!$F8) | T8: =IF($B8="","","n/a (baseline only)") | U8: =IF($B8="","","n/a") | V8: =IF($B8="","",IF($O8="","",IF(COUNT(INDEX(nrPTBands,1,0))<5,"",SUMPRODUCT(MAX(($O8>=INDEX(nrPTBands,1,0))*nrPTTierPts))))) | W8: =IF($B8="","",IF($P8="","",IF(COUNT(INDEX(nrPTBands,2,0))<5,"",SUMPRODUCT(MAX(($P8>=INDEX(nrPTBands,2,0))*nrPTTierPts))))) | X8: =IF($B8="","",IF($Q8="","",IF(COUNT(INDEX(nrPTBands,3,0))<5,"",SUMPRODUCT(MAX(($Q8<=INDEX(nrPTBands,3,0))*nrPTTierPts))))) | Y8: =IF($B8="","",IF($R8="","",IF(COUNT(INDEX(nrPTBands,4,0))<5,"",SUMPRODUCT(MAX(($R8*60<=INDEX(nrPTBands,4,0))*nrPTTierPts))))) | Z8: =IF($B8="","",IF($S8="","",IF(COUNT(INDEX(nrPTBands,5,0))<5,"",SUMPRODUCT(MAX(($S8<=INDEX(nrPTBands,5,0))*nrPTTierPts))))) | AA8: =IF($B8="","",IF(COUNT($V8:$Z8)=0,"",SUM($V8:$Z8))) | AB8: =IF($B8="","",IF($AA8="","",IF(cfgPTFinalMinPoints=0,"(rubric pending)",IF(COUNT($V8:$Z8)<5,"Incomplete",IF($AA8>=cfgPTFinalMinPoints,"Yes","No"))))) | AC8: =IF($B8="","",_xlfn.LET(_xlpm.pu,IF(COUNT($F8,$O8)=2,IFERROR(($O8-$F8)/$F8,""),""),_xlpm.su,IF(COUNT($G8,$P8)=2,IFERROR(($P8-$G8)/$G8,""),""),_xlpm.ag,IF(COUNT($H8,$Q8)=2,IFERROR(($H8-$Q8)/$H8,""),""),_xlpm.mi,IF(COUNT($I8,$R8)=2,IFERROR(($I8-$R8)/$I8,""),""),_xlpm.tm,IF(COUNT($J8,$S8)=2,IFERROR(($J8-$S8)/$J8,""),""),_xlpm.vals,IFERROR(_xlfn._xlws.FILTER(_xlfn.HSTACK(_xlpm.pu,_xlpm.su,_xlpm.ag,_xlpm.mi,_xlpm.tm),ISNUMBER(_xlfn.HSTACK(_xlpm.pu,_xlpm.su,_xlpm.ag,_xlpm.mi,_xlpm.tm))),""),IF(COUNT(_xlpm.vals)=0,"",ROUND(AVERAGE(_xlpm.vals)*100,1)))) | AD8: =IF(Cadets!$B8="","",Cadets!$I8)
B9: =IF(Cadets!$B9="","",Cadets!$B9) | C9: =IF(Cadets!$B9="","",Cadets!$F9) | T9: =IF($B9="","","n/a (baseline only)") | U9: =IF($B9="","","n/a") | V9: =IF($B9="","",IF($O9="","",IF(COUNT(INDEX(nrPTBands,1,0))<5,"",SUMPRODUCT(MAX(($O9>=INDEX(nrPTBands,1,0))*nrPTTierPts))))) | W9: =IF($B9="","",IF($P9="","",IF(COUNT(INDEX(nrPTBands,2,0))<5,"",SUMPRODUCT(MAX(($P9>=INDEX(nrPTBands,2,0))*nrPTTierPts))))) | X9: =IF($B9="","",IF($Q9="","",IF(COUNT(INDEX(nrPTBands,3,0))<5,"",SUMPRODUCT(MAX(($Q9<=INDEX(nrPTBands,3,0))*nrPTTierPts))))) | Y9: =IF($B9="","",IF($R9="","",IF(COUNT(INDEX(nrPTBands,4,0))<5,"",SUMPRODUCT(MAX(($R9*60<=INDEX(nrPTBands,4,0))*nrPTTierPts))))) | Z9: =IF($B9="","",IF($S9="","",IF(COUNT(INDEX(nrPTBands,5,0))<5,"",SUMPRODUCT(MAX(($S9<=INDEX(nrPTBands,5,0))*nrPTTierPts))))) | AA9: =IF($B9="","",IF(COUNT($V9:$Z9)=0,"",SUM($V9:$Z9))) | AB9: =IF($B9="","",IF($AA9="","",IF(cfgPTFinalMinPoints=0,"(rubric pending)",IF(COUNT($V9:$Z9)<5,"Incomplete",IF($AA9>=cfgPTFinalMinPoints,"Yes","No"))))) | AC9: =IF($B9="","",_xlfn.LET(_xlpm.pu,IF(COUNT($F9,$O9)=2,IFERROR(($O9-$F9)/$F9,""),""),_xlpm.su,IF(COUNT($G9,$P9)=2,IFERROR(($P9-$G9)/$G9,""),""),_xlpm.ag,IF(COUNT($H9,$Q9)=2,IFERROR(($H9-$Q9)/$H9,""),""),_xlpm.mi,IF(COUNT($I9,$R9)=2,IFERROR(($I9-$R9)/$I9,""),""),_xlpm.tm,IF(COUNT($J9,$S9)=2,IFERROR(($J9-$S9)/$J9,""),""),_xlpm.vals,IFERROR(_xlfn._xlws.FILTER(_xlfn.HSTACK(_xlpm.pu,_xlpm.su,_xlpm.ag,_xlpm.mi,_xlpm.tm),ISNUMBER(_xlfn.HSTACK(_xlpm.pu,_xlpm.su,_xlpm.ag,_xlpm.mi,_xlpm.tm))),""),IF(COUNT(_xlpm.vals)=0,"",ROUND(AVERAGE(_xlpm.vals)*100,1)))) | AD9: =IF(Cadets!$B9="","",Cadets!$I9)
B10: =IF(Cadets!$B10="","",Cadets!$B10) | C10: =IF(Cadets!$B10="","",Cadets!$F10) | T10: =IF($B10="","","n/a (baseline only)") | U10: =IF($B10="","","n/a") | V10: =IF($B10="","",IF($O10="","",IF(COUNT(INDEX(nrPTBands,1,0))<5,"",SUMPRODUCT(MAX(($O10>=INDEX(nrPTBands,1,0))*nrPTTierPts))))) | W10: =IF($B10="","",IF($P10="","",IF(COUNT(INDEX(nrPTBands,2,0))<5,"",SUMPRODUCT(MAX(($P10>=INDEX(nrPTBands,2,0))*nrPTTierPts))))) | X10: =IF($B10="","",IF($Q10="","",IF(COUNT(INDEX(nrPTBands,3,0))<5,"",SUMPRODUCT(MAX(($Q10<=INDEX(nrPTBands,3,0))*nrPTTierPts))))) | Y10: =IF($B10="","",IF($R10="","",IF(COUNT(INDEX(nrPTBands,4,0))<5,"",SUMPRODUCT(MAX(($R10*60<=INDEX(nrPTBands,4,0))*nrPTTierPts))))) | Z10: =IF($B10="","",IF($S10="","",IF(COUNT(INDEX(nrPTBands,5,0))<5,"",SUMPRODUCT(MAX(($S10<=INDEX(nrPTBands,5,0))*nrPTTierPts))))) | AA10: =IF($B10="","",IF(COUNT($V10:$Z10)=0,"",SUM($V10:$Z10))) | AB10: =IF($B10="","",IF($AA10="","",IF(cfgPTFinalMinPoints=0,"(rubric pending)",IF(COUNT($V10:$Z10)<5,"Incomplete",IF($AA10>=cfgPTFinalMinPoints,"Yes","No"))))) | AC10: =IF($B10="","",_xlfn.LET(_xlpm.pu,IF(COUNT($F10,$O10)=2,IFERROR(($O10-$F10)/$F10,""),""),_xlpm.su,IF(COUNT($G10,$P10)=2,IFERROR(($P10-$G10)/$G10,""),""),_xlpm.ag,IF(COUNT($H10,$Q10)=2,IFERROR(($H10-$Q10)/$H10,""),""),_xlpm.mi,IF(COUNT($I10,$R10)=2,IFERROR(($I10-$R10)/$I10,""),""),_xlpm.tm,IF(COUNT($J10,$S10)=2,IFERROR(($J10-$S10)/$J10,""),""),_xlpm.vals,IFERROR(_xlfn._xlws.FILTER(_xlfn.HSTACK(_xlpm.pu,_xlpm.su,_xlpm.ag,_xlpm.mi,_xlpm.tm),ISNUMBER(_xlfn.HSTACK(_xlpm.pu,_xlpm.su,_xlpm.ag,_xlpm.mi,_xlpm.tm))),""),IF(COUNT(_xlpm.vals)=0,"",ROUND(AVERAGE(_xlpm.vals)*100,1)))) | AD10: =IF(Cadets!$B10="","",Cadets!$I10)
B11: =IF(Cadets!$B11="","",Cadets!$B11) | C11: =IF(Cadets!$B11="","",Cadets!$F11) | T11: =IF($B11="","","n/a (baseline only)") | U11: =IF($B11="","","n/a") | V11: =IF($B11="","",IF($O11="","",IF(COUNT(INDEX(nrPTBands,1,0))<5,"",SUMPRODUCT(MAX(($O11>=INDEX(nrPTBands,1,0))*nrPTTierPts))))) | W11: =IF($B11="","",IF($P11="","",IF(COUNT(INDEX(nrPTBands,2,0))<5,"",SUMPRODUCT(MAX(($P11>=INDEX(nrPTBands,2,0))*nrPTTierPts))))) | X11: =IF($B11="","",IF($Q11="","",IF(COUNT(INDEX(nrPTBands,3,0))<5,"",SUMPRODUCT(MAX(($Q11<=INDEX(nrPTBands,3,0))*nrPTTierPts))))) | Y11: =IF($B11="","",IF($R11="","",IF(COUNT(INDEX(nrPTBands,4,0))<5,"",SUMPRODUCT(MAX(($R11*60<=INDEX(nrPTBands,4,0))*nrPTTierPts))))) | Z11: =IF($B11="","",IF($S11="","",IF(COUNT(INDEX(nrPTBands,5,0))<5,"",SUMPRODUCT(MAX(($S11<=INDEX(nrPTBands,5,0))*nrPTTierPts))))) | AA11: =IF($B11="","",IF(COUNT($V11:$Z11)=0,"",SUM($V11:$Z11))) | AB11: =IF($B11="","",IF($AA11="","",IF(cfgPTFinalMinPoints=0,"(rubric pending)",IF(COUNT($V11:$Z11)<5,"Incomplete",IF($AA11>=cfgPTFinalMinPoints,"Yes","No"))))) | AC11: =IF($B11="","",_xlfn.LET(_xlpm.pu,IF(COUNT($F11,$O11)=2,IFERROR(($O11-$F11)/$F11,""),""),_xlpm.su,IF(COUNT($G11,$P11)=2,IFERROR(($P11-$G11)/$G11,""),""),_xlpm.ag,IF(COUNT($H11,$Q11)=2,IFERROR(($H11-$Q11)/$H11,""),""),_xlpm.mi,IF(COUNT($I11,$R11)=2,IFERROR(($I11-$R11)/$I11,""),""),_xlpm.tm,IF(COUNT($J11,$S11)=2,IFERROR(($J11-$S11)/$J11,""),""),_xlpm.vals,IFERROR(_xlfn._xlws.FILTER(_xlfn.HSTACK(_xlpm.pu,_xlpm.su,_xlpm.ag,_xlpm.mi,_xlpm.tm),ISNUMBER(_xlfn.HSTACK(_xlpm.pu,_xlpm.su,_xlpm.ag,_xlpm.mi,_xlpm.tm))),""),IF(COUNT(_xlpm.vals)=0,"",ROUND(AVERAGE(_xlpm.vals)*100,1)))) | AD11: =IF(Cadets!$B11="","",Cadets!$I11)
B12: =IF(Cadets!$B12="","",Cadets!$B12) | C12: =IF(Cadets!$B12="","",Cadets!$F12) | T12: =IF($B12="","","n/a (baseline only)") | U12: =IF($B12="","","n/a") | V12: =IF($B12="","",IF($O12="","",IF(COUNT(INDEX(nrPTBands,1,0))<5,"",SUMPRODUCT(MAX(($O12>=INDEX(nrPTBands,1,0))*nrPTTierPts))))) | W12: =IF($B12="","",IF($P12="","",IF(COUNT(INDEX(nrPTBands,2,0))<5,"",SUMPRODUCT(MAX(($P12>=INDEX(nrPTBands,2,0))*nrPTTierPts))))) | X12: =IF($B12="","",IF($Q12="","",IF(COUNT(INDEX(nrPTBands,3,0))<5,"",SUMPRODUCT(MAX(($Q12<=INDEX(nrPTBands,3,0))*nrPTTierPts))))) | Y12: =IF($B12="","",IF($R12="","",IF(COUNT(INDEX(nrPTBands,4,0))<5,"",SUMPRODUCT(MAX(($R12*60<=INDEX(nrPTBands,4,0))*nrPTTierPts))))) | Z12: =IF($B12="","",IF($S12="","",IF(COUNT(INDEX(nrPTBands,5,0))<5,"",SUMPRODUCT(MAX(($S12<=INDEX(nrPTBands,5,0))*nrPTTierPts))))) | AA12: =IF($B12="","",IF(COUNT($V12:$Z12)=0,"",SUM($V12:$Z12))) | AB12: =IF($B12="","",IF($AA12="","",IF(cfgPTFinalMinPoints=0,"(rubric pending)",IF(COUNT($V12:$Z12)<5,"Incomplete",IF($AA12>=cfgPTFinalMinPoints,"Yes","No"))))) | AC12: =IF($B12="","",_xlfn.LET(_xlpm.pu,IF(COUNT($F12,$O12)=2,IFERROR(($O12-$F12)/$F12,""),""),_xlpm.su,IF(COUNT($G12,$P12)=2,IFERROR(($P12-$G12)/$G12,""),""),_xlpm.ag,IF(COUNT($H12,$Q12)=2,IFERROR(($H12-$Q12)/$H12,""),""),_xlpm.mi,IF(COUNT($I12,$R12)=2,IFERROR(($I12-$R12)/$I12,""),""),_xlpm.tm,IF(COUNT($J12,$S12)=2,IFERROR(($J12-$S12)/$J12,""),""),_xlpm.vals,IFERROR(_xlfn._xlws.FILTER(_xlfn.HSTACK(_xlpm.pu,_xlpm.su,_xlpm.ag,_xlpm.mi,_xlpm.tm),ISNUMBER(_xlfn.HSTACK(_xlpm.pu,_xlpm.su,_xlpm.ag,_xlpm.mi,_xlpm.tm))),""),IF(COUNT(_xlpm.vals)=0,"",ROUND(AVERAGE(_xlpm.vals)*100,1)))) | AD12: =IF(Cadets!$B12="","",Cadets!$I12)
B13: =IF(Cadets!$B13="","",Cadets!$B13) | C13: =IF(Cadets!$B13="","",Cadets!$F13) | T13: =IF($B13="","","n/a (baseline only)") | U13: =IF($B13="","","n/a") | V13: =IF($B13="","",IF($O13="","",IF(COUNT(INDEX(nrPTBands,1,0))<5,"",SUMPRODUCT(MAX(($O13>=INDEX(nrPTBands,1,0))*nrPTTierPts))))) | W13: =IF($B13="","",IF($P13="","",IF(COUNT(INDEX(nrPTBands,2,0))<5,"",SUMPRODUCT(MAX(($P13>=INDEX(nrPTBands,2,0))*nrPTTierPts))))) | X13: =IF($B13="","",IF($Q13="","",IF(COUNT(INDEX(nrPTBands,3,0))<5,"",SUMPRODUCT(MAX(($Q13<=INDEX(nrPTBands,3,0))*nrPTTierPts))))) | Y13: =IF($B13="","",IF($R13="","",IF(COUNT(INDEX(nrPTBands,4,0))<5,"",SUMPRODUCT(MAX(($R13*60<=INDEX(nrPTBands,4,0))*nrPTTierPts))))) | Z13: =IF($B13="","",IF($S13="","",IF(COUNT(INDEX(nrPTBands,5,0))<5,"",SUMPRODUCT(MAX(($S13<=INDEX(nrPTBands,5,0))*nrPTTierPts))))) | AA13: =IF($B13="","",IF(COUNT($V13:$Z13)=0,"",SUM($V13:$Z13))) | AB13: =IF($B13="","",IF($AA13="","",IF(cfgPTFinalMinPoints=0,"(rubric pending)",IF(COUNT($V13:$Z13)<5,"Incomplete",IF($AA13>=cfgPTFinalMinPoints,"Yes","No"))))) | AC13: =IF($B13="","",_xlfn.LET(_xlpm.pu,IF(COUNT($F13,$O13)=2,IFERROR(($O13-$F13)/$F13,""),""),_xlpm.su,IF(COUNT($G13,$P13)=2,IFERROR(($P13-$G13)/$G13,""),""),_xlpm.ag,IF(COUNT($H13,$Q13)=2,IFERROR(($H13-$Q13)/$H13,""),""),_xlpm.mi,IF(COUNT($I13,$R13)=2,IFERROR(($I13-$R13)/$I13,""),""),_xlpm.tm,IF(COUNT($J13,$S13)=2,IFERROR(($J13-$S13)/$J13,""),""),_xlpm.vals,IFERROR(_xlfn._xlws.FILTER(_xlfn.HSTACK(_xlpm.pu,_xlpm.su,_xlpm.ag,_xlpm.mi,_xlpm.tm),ISNUMBER(_xlfn.HSTACK(_xlpm.pu,_xlpm.su,_xlpm.ag,_xlpm.mi,_xlpm.tm))),""),IF(COUNT(_xlpm.vals)=0,"",ROUND(AVERAGE(_xlpm.vals)*100,1)))) | AD13: =IF(Cadets!$B13="","",Cadets!$I13)
B14: =IF(Cadets!$B14="","",Cadets!$B14) | C14: =IF(Cadets!$B14="","",Cadets!$F14) | T14: =IF($B14="","","n/a (baseline only)") | U14: =IF($B14="","","n/a") | V14: =IF($B14="","",IF($O14="","",IF(COUNT(INDEX(nrPTBands,1,0))<5,"",SUMPRODUCT(MAX(($O14>=INDEX(nrPTBands,1,0))*nrPTTierPts))))) | W14: =IF($B14="","",IF($P14="","",IF(COUNT(INDEX(nrPTBands,2,0))<5,"",SUMPRODUCT(MAX(($P14>=INDEX(nrPTBands,2,0))*nrPTTierPts))))) | X14: =IF($B14="","",IF($Q14="","",IF(COUNT(INDEX(nrPTBands,3,0))<5,"",SUMPRODUCT(MAX(($Q14<=INDEX(nrPTBands,3,0))*nrPTTierPts))))) | Y14: =IF($B14="","",IF($R14="","",IF(COUNT(INDEX(nrPTBands,4,0))<5,"",SUMPRODUCT(MAX(($R14*60<=INDEX(nrPTBands,4,0))*nrPTTierPts))))) | Z14: =IF($B14="","",IF($S14="","",IF(COUNT(INDEX(nrPTBands,5,0))<5,"",SUMPRODUCT(MAX(($S14<=INDEX(nrPTBands,5,0))*nrPTTierPts))))) | AA14: =IF($B14="","",IF(COUNT($V14:$Z14)=0,"",SUM($V14:$Z14))) | AB14: =IF($B14="","",IF($AA14="","",IF(cfgPTFinalMinPoints=0,"(rubric pending)",IF(COUNT($V14:$Z14)<5,"Incomplete",IF($AA14>=cfgPTFinalMinPoints,"Yes","No"))))) | AC14: =IF($B14="","",_xlfn.LET(_xlpm.pu,IF(COUNT($F14,$O14)=2,IFERROR(($O14-$F14)/$F14,""),""),_xlpm.su,IF(COUNT($G14,$P14)=2,IFERROR(($P14-$G14)/$G14,""),""),_xlpm.ag,IF(COUNT($H14,$Q14)=2,IFERROR(($H14-$Q14)/$H14,""),""),_xlpm.mi,IF(COUNT($I14,$R14)=2,IFERROR(($I14-$R14)/$I14,""),""),_xlpm.tm,IF(COUNT($J14,$S14)=2,IFERROR(($J14-$S14)/$J14,""),""),_xlpm.vals,IFERROR(_xlfn._xlws.FILTER(_xlfn.HSTACK(_xlpm.pu,_xlpm.su,_xlpm.ag,_xlpm.mi,_xlpm.tm),ISNUMBER(_xlfn.HSTACK(_xlpm.pu,_xlpm.su,_xlpm.ag,_xlpm.mi,_xlpm.tm))),""),IF(COUNT(_xlpm.vals)=0,"",ROUND(AVERAGE(_xlpm.vals)*100,1)))) | AD14: =IF(Cadets!$B14="","",Cadets!$I14)
B15: =IF(Cadets!$B15="","",Cadets!$B15) | C15: =IF(Cadets!$B15="","",Cadets!$F15) | T15: =IF($B15="","","n/a (baseline only)") | U15: =IF($B15="","","n/a") | V15: =IF($B15="","",IF($O15="","",IF(COUNT(INDEX(nrPTBands,1,0))<5,"",SUMPRODUCT(MAX(($O15>=INDEX(nrPTBands,1,0))*nrPTTierPts))))) | W15: =IF($B15="","",IF($P15="","",IF(COUNT(INDEX(nrPTBands,2,0))<5,"",SUMPRODUCT(MAX(($P15>=INDEX(nrPTBands,2,0))*nrPTTierPts))))) | X15: =IF($B15="","",IF($Q15="","",IF(COUNT(INDEX(nrPTBands,3,0))<5,"",SUMPRODUCT(MAX(($Q15<=INDEX(nrPTBands,3,0))*nrPTTierPts))))) | Y15: =IF($B15="","",IF($R15="","",IF(COUNT(INDEX(nrPTBands,4,0))<5,"",SUMPRODUCT(MAX(($R15*60<=INDEX(nrPTBands,4,0))*nrPTTierPts))))) | Z15: =IF($B15="","",IF($S15="","",IF(COUNT(INDEX(nrPTBands,5,0))<5,"",SUMPRODUCT(MAX(($S15<=INDEX(nrPTBands,5,0))*nrPTTierPts))))) | AA15: =IF($B15="","",IF(COUNT($V15:$Z15)=0,"",SUM($V15:$Z15))) | AB15: =IF($B15="","",IF($AA15="","",IF(cfgPTFinalMinPoints=0,"(rubric pending)",IF(COUNT($V15:$Z15)<5,"Incomplete",IF($AA15>=cfgPTFinalMinPoints,"Yes","No"))))) | AC15: =IF($B15="","",_xlfn.LET(_xlpm.pu,IF(COUNT($F15,$O15)=2,IFERROR(($O15-$F15)/$F15,""),""),_xlpm.su,IF(COUNT($G15,$P15)=2,IFERROR(($P15-$G15)/$G15,""),""),_xlpm.ag,IF(COUNT($H15,$Q15)=2,IFERROR(($H15-$Q15)/$H15,""),""),_xlpm.mi,IF(COUNT($I15,$R15)=2,IFERROR(($I15-$R15)/$I15,""),""),_xlpm.tm,IF(COUNT($J15,$S15)=2,IFERROR(($J15-$S15)/$J15,""),""),_xlpm.vals,IFERROR(_xlfn._xlws.FILTER(_xlfn.HSTACK(_xlpm.pu,_xlpm.su,_xlpm.ag,_xlpm.mi,_xlpm.tm),ISNUMBER(_xlfn.HSTACK(_xlpm.pu,_xlpm.su,_xlpm.ag,_xlpm.mi,_xlpm.tm))),""),IF(COUNT(_xlpm.vals)=0,"",ROUND(AVERAGE(_xlpm.vals)*100,1)))) | AD15: =IF(Cadets!$B15="","",Cadets!$I15)
B16: =IF(Cadets!$B16="","",Cadets!$B16) | C16: =IF(Cadets!$B16="","",Cadets!$F16) | T16: =IF($B16="","","n/a (baseline only)") | U16: =IF($B16="","","n/a") | V16: =IF($B16="","",IF($O16="","",IF(COUNT(INDEX(nrPTBands,1,0))<5,"",SUMPRODUCT(MAX(($O16>=INDEX(nrPTBands,1,0))*nrPTTierPts))))) | W16: =IF($B16="","",IF($P16="","",IF(COUNT(INDEX(nrPTBands,2,0))<5,"",SUMPRODUCT(MAX(($P16>=INDEX(nrPTBands,2,0))*nrPTTierPts))))) | X16: =IF($B16="","",IF($Q16="","",IF(COUNT(INDEX(nrPTBands,3,0))<5,"",SUMPRODUCT(MAX(($Q16<=INDEX(nrPTBands,3,0))*nrPTTierPts))))) | Y16: =IF($B16="","",IF($R16="","",IF(COUNT(INDEX(nrPTBands,4,0))<5,"",SUMPRODUCT(MAX(($R16*60<=INDEX(nrPTBands,4,0))*nrPTTierPts))))) | Z16: =IF($B16="","",IF($S16="","",IF(COUNT(INDEX(nrPTBands,5,0))<5,"",SUMPRODUCT(MAX(($S16<=INDEX(nrPTBands,5,0))*nrPTTierPts))))) | AA16: =IF($B16="","",IF(COUNT($V16:$Z16)=0,"",SUM($V16:$Z16))) | AB16: =IF($B16="","",IF($AA16="","",IF(cfgPTFinalMinPoints=0,"(rubric pending)",IF(COUNT($V16:$Z16)<5,"Incomplete",IF($AA16>=cfgPTFinalMinPoints,"Yes","No"))))) | AC16: =IF($B16="","",_xlfn.LET(_xlpm.pu,IF(COUNT($F16,$O16)=2,IFERROR(($O16-$F16)/$F16,""),""),_xlpm.su,IF(COUNT($G16,$P16)=2,IFERROR(($P16-$G16)/$G16,""),""),_xlpm.ag,IF(COUNT($H16,$Q16)=2,IFERROR(($H16-$Q16)/$H16,""),""),_xlpm.mi,IF(COUNT($I16,$R16)=2,IFERROR(($I16-$R16)/$I16,""),""),_xlpm.tm,IF(COUNT($J16,$S16)=2,IFERROR(($J16-$S16)/$J16,""),""),_xlpm.vals,IFERROR(_xlfn._xlws.FILTER(_xlfn.HSTACK(_xlpm.pu,_xlpm.su,_xlpm.ag,_xlpm.mi,_xlpm.tm),ISNUMBER(_xlfn.HSTACK(_xlpm.pu,_xlpm.su,_xlpm.ag,_xlpm.mi,_xlpm.tm))),""),IF(COUNT(_xlpm.vals)=0,"",ROUND(AVERAGE(_xlpm.vals)*100,1)))) | AD16: =IF(Cadets!$B16="","",Cadets!$I16)
B17: =IF(Cadets!$B17="","",Cadets!$B17) | C17: =IF(Cadets!$B17="","",Cadets!$F17) | T17: =IF($B17="","","n/a (baseline only)") | U17: =IF($B17="","","n/a") | V17: =IF($B17="","",IF($O17="","",IF(COUNT(INDEX(nrPTBands,1,0))<5,"",SUMPRODUCT(MAX(($O17>=INDEX(nrPTBands,1,0))*nrPTTierPts))))) | W17: =IF($B17="","",IF($P17="","",IF(COUNT(INDEX(nrPTBands,2,0))<5,"",SUMPRODUCT(MAX(($P17>=INDEX(nrPTBands,2,0))*nrPTTierPts))))) | X17: =IF($B17="","",IF($Q17="","",IF(COUNT(INDEX(nrPTBands,3,0))<5,"",SUMPRODUCT(MAX(($Q17<=INDEX(nrPTBands,3,0))*nrPTTierPts))))) | Y17: =IF($B17="","",IF($R17="","",IF(COUNT(INDEX(nrPTBands,4,0))<5,"",SUMPRODUCT(MAX(($R17*60<=INDEX(nrPTBands,4,0))*nrPTTierPts))))) | Z17: =IF($B17="","",IF($S17="","",IF(COUNT(INDEX(nrPTBands,5,0))<5,"",SUMPRODUCT(MAX(($S17<=INDEX(nrPTBands,5,0))*nrPTTierPts))))) | AA17: =IF($B17="","",IF(COUNT($V17:$Z17)=0,"",SUM($V17:$Z17))) | AB17: =IF($B17="","",IF($AA17="","",IF(cfgPTFinalMinPoints=0,"(rubric pending)",IF(COUNT($V17:$Z17)<5,"Incomplete",IF($AA17>=cfgPTFinalMinPoints,"Yes","No"))))) | AC17: =IF($B17="","",_xlfn.LET(_xlpm.pu,IF(COUNT($F17,$O17)=2,IFERROR(($O17-$F17)/$F17,""),""),_xlpm.su,IF(COUNT($G17,$P17)=2,IFERROR(($P17-$G17)/$G17,""),""),_xlpm.ag,IF(COUNT($H17,$Q17)=2,IFERROR(($H17-$Q17)/$H17,""),""),_xlpm.mi,IF(COUNT($I17,$R17)=2,IFERROR(($I17-$R17)/$I17,""),""),_xlpm.tm,IF(COUNT($J17,$S17)=2,IFERROR(($J17-$S17)/$J17,""),""),_xlpm.vals,IFERROR(_xlfn._xlws.FILTER(_xlfn.HSTACK(_xlpm.pu,_xlpm.su,_xlpm.ag,_xlpm.mi,_xlpm.tm),ISNUMBER(_xlfn.HSTACK(_xlpm.pu,_xlpm.su,_xlpm.ag,_xlpm.mi,_xlpm.tm))),""),IF(COUNT(_xlpm.vals)=0,"",ROUND(AVERAGE(_xlpm.vals)*100,1)))) | AD17: =IF(Cadets!$B17="","",Cadets!$I17)
... B55: =IF(Cadets!$B55="","",Cadets!$B55) | C55: =IF(Cadets!$B55="","",Cadets!$F55) | T55: =IF($B55="","","n/a (baseline only)") | U55: =IF($B55="","","n/a") | V55: =IF($B55="","",IF($O55="","",IF(COUNT(INDEX(nrPTBands,1,0))<5,"",SUMPRODUCT(MAX(($O55>=INDEX(nrPTBands,1,0))*nrPTTierPts))))) | W55: =IF($B55="","",IF($P55="","",IF(COUNT(INDEX(nrPTBands,2,0))<5,"",SUMPRODUCT(MAX(($P55>=INDEX(nrPTBands,2,0))*nrPTTierPts))))) | X55: =IF($B55="","",IF($Q55="","",IF(COUNT(INDEX(nrPTBands,3,0))<5,"",SUMPRODUCT(MAX(($Q55<=INDEX(nrPTBands,3,0))*nrPTTierPts))))) | Y55: =IF($B55="","",IF($R55="","",IF(COUNT(INDEX(nrPTBands,4,0))<5,"",SUMPRODUCT(MAX(($R55*60<=INDEX(nrPTBands,4,0))*nrPTTierPts))))) | Z55: =IF($B55="","",IF($S55="","",IF(COUNT(INDEX(nrPTBands,5,0))<5,"",SUMPRODUCT(MAX(($S55<=INDEX(nrPTBands,5,0))*nrPTTierPts))))) | AA55: =IF($B55="","",IF(COUNT($V55:$Z55)=0,"",SUM($V55:$Z55))) | AB55: =IF($B55="","",IF($AA55="","",IF(cfgPTFinalMinPoints=0,"(rubric pending)",IF(COUNT($V55:$Z55)<5,"Incomplete",IF($AA55>=cfgPTFinalMinPoints,"Yes","No"))))) | AC55: =IF($B55="","",_xlfn.LET(_xlpm.pu,IF(COUNT($F55,$O55)=2,IFERROR(($O55-$F55)/$F55,""),""),_xlpm.su,IF(COUNT($G55,$P55)=2,IFERROR(($P55-$G55)/$G55,""),""),_xlpm.ag,IF(COUNT($H55,$Q55)=2,IFERROR(($H55-$Q55)/$H55,""),""),_xlpm.mi,IF(COUNT($I55,$R55)=2,IFERROR(($I55-$R55)/$I55,""),""),_xlpm.tm,IF(COUNT($J55,$S55)=2,IFERROR(($J55-$S55)/$J55,""),""),_xlpm.vals,IFERROR(_xlfn._xlws.FILTER(_xlfn.HSTACK(_xlpm.pu,_xlpm.su,_xlpm.ag,_xlpm.mi,_xlpm.tm),ISNUMBER(_xlfn.HSTACK(_xlpm.pu,_xlpm.su,_xlpm.ag,_xlpm.mi,_xlpm.tm))),""),IF(COUNT(_xlpm.vals)=0,"",ROUND(AVERAGE(_xlpm.vals)*100,1)))) | AD55: =IF(Cadets!$B55="","",Cadets!$I55)

Sheet Medical
B1: =HYPERLINK("#Dashboard!B5","◄ Dashboard")
B4: Injuries, clearances and restrictions (policy 400.7/500). Modified PT inside a documented restriction is not a missed session when objectives are met — log the restriction here and the PT Modified event on Attendance.
B5: EntryID | C5: Date | D5: Cadet Name | E5: PID | F5: Type | G5: Description | H5: Restriction? | I5: Restriction Start | J5: Restriction End | K5: Cleared Date | L5: Doc Status | M5: Current Status | N5: Notes
B6: =IF($D6="","","MD"&TEXT(ROW()-5,"000")) | E6: =IF($D6="","",IFERROR(INDEX(rngCadetPIDs,MATCH($D6,rngCadetNames,0)),"?")) | M6: =IF($D6="","",IF($K6<>"","Cleared "&TEXT($K6,"mm/dd"),IF($H6="Yes",IF(AND($J6<>"",$J6<TODAY()),"RESTRICTION EXPIRED","ACTIVE RESTRICTION"),"Documented")))
B7: =IF($D7="","","MD"&TEXT(ROW()-5,"000")) | E7: =IF($D7="","",IFERROR(INDEX(rngCadetPIDs,MATCH($D7,rngCadetNames,0)),"?")) | M7: =IF($D7="","",IF($K7<>"","Cleared "&TEXT($K7,"mm/dd"),IF($H7="Yes",IF(AND($J7<>"",$J7<TODAY()),"RESTRICTION EXPIRED","ACTIVE RESTRICTION"),"Documented")))
B8: =IF($D8="","","MD"&TEXT(ROW()-5,"000")) | E8: =IF($D8="","",IFERROR(INDEX(rngCadetPIDs,MATCH($D8,rngCadetNames,0)),"?")) | M8: =IF($D8="","",IF($K8<>"","Cleared "&TEXT($K8,"mm/dd"),IF($H8="Yes",IF(AND($J8<>"",$J8<TODAY()),"RESTRICTION EXPIRED","ACTIVE RESTRICTION"),"Documented")))
B9: =IF($D9="","","MD"&TEXT(ROW()-5,"000")) | E9: =IF($D9="","",IFERROR(INDEX(rngCadetPIDs,MATCH($D9,rngCadetNames,0)),"?")) | M9: =IF($D9="","",IF($K9<>"","Cleared "&TEXT($K9,"mm/dd"),IF($H9="Yes",IF(AND($J9<>"",$J9<TODAY()),"RESTRICTION EXPIRED","ACTIVE RESTRICTION"),"Documented")))
B10: =IF($D10="","","MD"&TEXT(ROW()-5,"000")) | E10: =IF($D10="","",IFERROR(INDEX(rngCadetPIDs,MATCH($D10,rngCadetNames,0)),"?")) | M10: =IF($D10="","",IF($K10<>"","Cleared "&TEXT($K10,"mm/dd"),IF($H10="Yes",IF(AND($J10<>"",$J10<TODAY()),"RESTRICTION EXPIRED","ACTIVE RESTRICTION"),"Documented")))
B11: =IF($D11="","","MD"&TEXT(ROW()-5,"000")) | E11: =IF($D11="","",IFERROR(INDEX(rngCadetPIDs,MATCH($D11,rngCadetNames,0)),"?")) | M11: =IF($D11="","",IF($K11<>"","Cleared "&TEXT($K11,"mm/dd"),IF($H11="Yes",IF(AND($J11<>"",$J11<TODAY()),"RESTRICTION EXPIRED","ACTIVE RESTRICTION"),"Documented")))
B12: =IF($D12="","","MD"&TEXT(ROW()-5,"000")) | E12: =IF($D12="","",IFERROR(INDEX(rngCadetPIDs,MATCH($D12,rngCadetNames,0)),"?")) | M12: =IF($D12="","",IF($K12<>"","Cleared "&TEXT($K12,"mm/dd"),IF($H12="Yes",IF(AND($J12<>"",$J12<TODAY()),"RESTRICTION EXPIRED","ACTIVE RESTRICTION"),"Documented")))
B13: =IF($D13="","","MD"&TEXT(ROW()-5,"000")) | E13: =IF($D13="","",IFERROR(INDEX(rngCadetPIDs,MATCH($D13,rngCadetNames,0)),"?")) | M13: =IF($D13="","",IF($K13<>"","Cleared "&TEXT($K13,"mm/dd"),IF($H13="Yes",IF(AND($J13<>"",$J13<TODAY()),"RESTRICTION EXPIRED","ACTIVE RESTRICTION"),"Documented")))
B14: =IF($D14="","","MD"&TEXT(ROW()-5,"000")) | E14: =IF($D14="","",IFERROR(INDEX(rngCadetPIDs,MATCH($D14,rngCadetNames,0)),"?")) | M14: =IF($D14="","",IF($K14<>"","Cleared "&TEXT($K14,"mm/dd"),IF($H14="Yes",IF(AND($J14<>"",$J14<TODAY()),"RESTRICTION EXPIRED","ACTIVE RESTRICTION"),"Documented")))
B15: =IF($D15="","","MD"&TEXT(ROW()-5,"000")) | E15: =IF($D15="","",IFERROR(INDEX(rngCadetPIDs,MATCH($D15,rngCadetNames,0)),"?")) | M15: =IF($D15="","",IF($K15<>"","Cleared "&TEXT($K15,"mm/dd"),IF($H15="Yes",IF(AND($J15<>"",$J15<TODAY()),"RESTRICTION EXPIRED","ACTIVE RESTRICTION"),"Documented")))
B16: =IF($D16="","","MD"&TEXT(ROW()-5,"000")) | E16: =IF($D16="","",IFERROR(INDEX(rngCadetPIDs,MATCH($D16,rngCadetNames,0)),"?")) | M16: =IF($D16="","",IF($K16<>"","Cleared "&TEXT($K16,"mm/dd"),IF($H16="Yes",IF(AND($J16<>"",$J16<TODAY()),"RESTRICTION EXPIRED","ACTIVE RESTRICTION"),"Documented")))
B17: =IF($D17="","","MD"&TEXT(ROW()-5,"000")) | E17: =IF($D17="","",IFERROR(INDEX(rngCadetPIDs,MATCH($D17,rngCadetNames,0)),"?")) | M17: =IF($D17="","",IF($K17<>"","Cleared "&TEXT($K17,"mm/dd"),IF($H17="Yes",IF(AND($J17<>"",$J17<TODAY()),"RESTRICTION EXPIRED","ACTIVE RESTRICTION"),"Documented")))
... B205: =IF($D205="","","MD"&TEXT(ROW()-5,"000")) | E205: =IF($D205="","",IFERROR(INDEX(rngCadetPIDs,MATCH($D205,rngCadetNames,0)),"?")) | M205: =IF($D205="","",IF($K205<>"","Cleared "&TEXT($K205,"mm/dd"),IF($H205="Yes",IF(AND($J205<>"",$J205<TODAY()),"RESTRICTION EXPIRED","ACTIVE RESTRICTION"),"Documented")))

Sheet Certifications
B1: =HYPERLINK("#Dashboard!B5","◄ Dashboard")
B4: TCOLE-mandatory per-student completions. Enter the completion date and mark Copy? = Yes once the cadet's certificate copy is in the file. 'To Collect' feeds the Dashboard reminder list; All Certs GATES GRADUATION - every cert must have a date AND Copy? = Yes. Copy? = N/A waives that requirement entirely, so every waiver is named in 'Waived (N/A)' and counted on the Audit sheet; be ready to justify each one to a TCOLE field agent.
